Workbook
Name _______________________apr98: #REF!
Name _______________________apr99: #REF!
Name _______________________dec98: #REF!
Name _______________________feb98: #REF!
Name _______________________feb99: #REF!
Name _______________________jan98: #REF!
Name _______________________jan99: #REF!
Name _______________________jun99: #REF!
Name _______________________mar98: #REF!
Name _______________________mar99: #REF!
Name _______________________mei99: #REF!
Name _______________________mm02: #REF!
Name _______________________mm2: #REF!
Name _______________________nov98: #REF!
Name _______________________sep98: #REF!
Name ______________________CON1: #REF!
Name ______________________des06: #REF!
Name ______________________INC2: #REF!
Name ______________________IRB99: #REF!
Name ______________________ji1: #REF!
Name ______________________SA1: #REF!
Name ______________________YW1: #REF!
Name _____________________Apr98: #REF!
Name _____________________Apr99: #REF!
Name _____________________CON1: #REF!
Name _____________________DAT10: #REF!
Name _____________________DAT11: #REF!
Name _____________________DAT12: #REF!
Name _____________________DAT13: #REF!
Name _____________________DAT2: #REF!
Name _____________________DAT3: #REF!
Name _____________________DAT4: #REF!
Name _____________________DAT5: #REF!
Name _____________________DAT6: #REF!
Name _____________________DAT7: #REF!
Name _____________________DAT8: #REF!
Name _____________________DAT9: #REF!
Name _____________________Dec98: #REF!
Name _____________________des06: #REF!
Name _____________________Feb98: #REF!
Name _____________________Feb99: #REF!
Name _____________________INC2: #REF!
Name _____________________IRB99: #REF!
Name _____________________Jan98: #REF!
Name _____________________Jan99: #REF!
Name _____________________ji1: #REF!
Name _____________________JUN99: #REF!
Name _____________________Mar98: #REF!
Name _____________________Mar99: #REF!
Name _____________________MEI99: #REF!
Name _____________________mm02: #REF!
Name _____________________mm2: #REF!
Name _____________________Nov98: #REF!
Name _____________________SA1: #REF!
Name _____________________Sep98: #REF!
Name _____________________YW1: #REF!
Name ____________________apr98: #REF!
Name ____________________apr99: #REF!
Name ____________________CON1: #REF!
Name ____________________DAT1: #REF!

Sheet Penjelasan Rumus
B1: Penjelasan Rumus Penilaian (sederhana)
B3: 1. Capaian = REALISASI dibandingkan TARGET (untuk KPI apapun)
B4: • Maximize (makin tinggi makin baik): Capaian = Realisasi / Target
B5: • Minimize (makin rendah/cepat makin baik): Capaian = Target / Realisasi
B6: • Kalau realisasi sudah MEMENUHI atau MELEBIHI target (termasuk serah lebih cepat) -> Capaian = penuh (1,1).
B7: Rumus: =IF(realisasi<=target, 1,1, IFERROR(target/realisasi,0)) [untuk minimize, mis. rkap & kecelakaan]
B9: 2. Skor = Capaian x Bobot (maksimum 1,1 x Bobot)
B10: Rumus: =MIN(1,1*bobot ; capaian*bobot)
B12: 3. Contoh RKAP (yang tadi salah)
B13: Target serah 30/09/2025, realisasi 30/08/2025 (LEBIH CEPAT) -> memenuhi -> Capaian 1,1 -> skor penuh.
B14: Sebelumnya rumus lama (date-tier) memberi 0 untuk serah setelah Juni, padahal target 30 Sep. Itu sudah diperbaiki.
B16: 4. Beberapa perspektif (Korporat, Region Head, SEVP Operation, SEVP Business Support)
B17: Capaian sama; yang beda hanya bobot tiap jabatan, sehingga skornya beda. Rumus skor tetap sama.

Sheet Temuan & Perbaikan
A1: Temuan Audit & Perbaikan — Sheet N4 (PTPN IV)
A3: No | B3: Status | C3: Lokasi | D3: Temuan / Tindakan | E3: Dampak
A4: 1 | B4: DIPERBAIKI | C4: RKAP — semua N4 (blok atas, kolom CP/CQ/S/T) | D4: Capaian RKAP diubah ke aturan realisasi-vs-target: serah pada/atau sebelum target = penuh. Rumus date-tier lama yang memberi 0 dihapus. | E4: RKAP kini bernilai penuh; naik di perspektif Region Head & SEVP BS
A5: 2 | B5: DIPERBAIKI | C5: Kecelakaan Kerja Fatal — N4R4/5/6/7 | D5: Rekor nol kecelakaan: capaian 0 -> 1,1 (penuh). | E5: Skor Korporat Regional 4–7 naik +1,1 (mengalir ke Rekap)
A6: 3 | B6: DATA DIBENAHI | C6: N4R2 & N4R4 (tanggal serah RKAP) | D6: Tanggal serah berformat TEKS diubah jadi tanggal asli (31/07/2025; 30/09/2025). | E6: Agar bisa dihitung
A7: 4 | B7: PERLU DICEK KAMU | C7: N4R5 (tanggal serah RKAP) | D7: Isi selnya "1", bukan tanggal. Diasumsikan memenuhi (skor penuh), tapi tolong isi tanggal serah aslinya. | E7: Data sumber tidak lengkap
A8: 5 | B8: PERLU KEPUTUSAN | C8: Bobot RKAP di perspektif SEVP Operation = 0 | D8: Karena bobotnya 0, perbaikan RKAP TIDAK menambah kolom "Korporat" di Rekap (kolom itu menarik dari total SEVP Operation). Pastikan apakah bobot 0 ini disengaja. | E8: Headline Korporat tidak berubah dari RKAP
A9: 6 | B9: PERLU PERHATIAN | C9: Skor per-orang RH/SEVP di Rekap (dari "Kertas Kerja") | D9: Nilainya DIKETIK MANUAL (hardcoded), tidak tertaut ke sheet N4. Jadi perbaikan di N4 tidak otomatis mengubahnya — perlu diperbarui manual bila ingin ikut. | E9: Risiko skor per-orang tidak sinkron
A10: 7 | B10: CATATAN STRUKTUR | C10: Semua sheet N4 | D10: Tiap sheet punya DUA blok KPI kembar: blok atas (tampilan) menghitung capaian, blok bawah (scorecard) yang masuk total. Struktur antar-regional juga tidak seragam. | E10: Sumber utama kerawanan salah
A11: 8 | B11: SUDAH DIBERSIHKAN | C11: KINRA (nama nyasar) & Cascad!A1 (referensi rusak) | D11: Sampah dihapus. | E11: Kerapian; 0 error
A12: 9 | B12: BERSIH ✔ | C12: Entitas (PTPN IV/I/III, SGN), 7 anak perusahaan, N1R1–R8 | D12: Tabel hasil capaian diperiksa: arah benar, skor=capaian×bobot (maks 1,1×bobot), konsisten antar perspektif, total cocok Rekap. | E12: Tidak ada error hitung

Sheet Rekap
A1: Rekapitulasi Nilai
K2: Penilaian SEVP
C3: Korporat | D3: Region Head | E3: SEVP Ops / 1 | F3: SEVP Ops 2 | G3: SEVP BS | K3: No | L3: Entitas Penugasan | M3: Nama | N3: Jabatan | O3: Nilai 2025 | P3: Keterangan
B4: PalmCo HO | C4: ='PTPN IV'!T29 -> 94.373244 | K4: 1 | L4: PTPN I - Supporting Co HO | M4: Teddy Yunirman Danas | N4: Direktur Utama | O4: ='Kertas Kerja'!L6*12/'Kertas Kerja'!K6 -> 81.73 | P4: Skor Direktur menyusul
B5: Regional 1 | C5: =N4R1!T94 -> 89.727552 | D5: ='Kertas Kerja'!L44*12/'Kertas Kerja'!K44 -> 88.593044 | E5: ='Kertas Kerja'!L45*12/'Kertas Kerja'!K45 -> 89.727552 | F5: ='Kertas Kerja'!L46*12/'Kertas Kerja'!K46 -> 89.727552 | G5: ='Kertas Kerja'!L48*12/'Kertas Kerja'!K48 -> 87.493371 | K5: 2 | L5: PTPN I - Supporting Co HO | M5: Fauzi Omar | N5: Direktur Operasional | O5: ='Kertas Kerja'!L7*12/'Kertas Kerja'!K7 -> 83.56 | P5: Skor Direktur menyusul
B6: Regional 2 | C6: =N4R2!T100 -> 88.78702 | D6: ='Kertas Kerja'!L53*12/'Kertas Kerja'!K53 -> 87.528879 | E6: ='Kertas Kerja'!L51*12/'Kertas Kerja'!K51 -> 88.78702 | F6: ='Kertas Kerja'!L52*12/'Kertas Kerja'!K52 -> 88.78702 | G6: ='Kertas Kerja'!L55*12/'Kertas Kerja'!K55 -> 85.464029 | K6: 3 | L6: PTPN I - Supporting Co HO | M6: Landi Rizaldi Mangaweang | N6: Direktur Pemasaran dan Aset | O6: ='Kertas Kerja'!L8*12/'Kertas Kerja'!K8 -> 81.41 | P6: Skor Direktur menyusul
B7: Regional 3 | C7: =N4R3!T108 -> 90.239473 | E7: ='Kertas Kerja'!L57*12/'Kertas Kerja'!K57 -> 90.239473 | G7: ='Kertas Kerja'!L58*12/'Kertas Kerja'!K58 -> 88.893676 | K7: 4 | L7: PTPN I - Supporting Co HO | M7: Doni P Gandamihardja | N7: Direktur Keuangan dan Manajemen Risiko | O7: ='Kertas Kerja'!L9*12/'Kertas Kerja'!K9 -> 84.38 | P7: Skor Direktur menyusul
B8: Regional 4 | C8: =N4R4!T101 -> 80.595579 | D8: ='Kertas Kerja'!L60*12/'Kertas Kerja'!K60 -> 79.96698 | E8: ='Kertas Kerja'!L64*12/'Kertas Kerja'!K64 -> 80.595579 | G8: ='Kertas Kerja'!L63*12/'Kertas Kerja'!K63 -> 77.041735 | K8: 5 | L8: PTPN I - Supporting Co HO | M8: Siwi Peni | N8: Direktur SDM dan TI | O8: ='Kertas Kerja'!L10*12/'Kertas Kerja'!K10 -> 84.55 | P8: Skor Direktur menyusul
B9: Regional 5 | C9: =N4R5!T90 -> 75.639951 | D9: ='Kertas Kerja'!L65*12/'Kertas Kerja'!K65 -> 75.800929 | E9: ='Kertas Kerja'!L66*12/'Kertas Kerja'!K66 -> 75.639951 | F9: ='Kertas Kerja'!L68*12/'Kertas Kerja'!K68 -> 75.639951 | G9: ='Kertas Kerja'!L70*12/'Kertas Kerja'!K70 -> 74.484656 | K9: 6 | L9: PTPN I - Supporting Co HO | M9: Tio Handoko | N9: Direktur Hubungan Kelembagaan | O9: ='Kertas Kerja'!L11*12/'Kertas Kerja'!K11 -> 85.58 | P9: Skor Direktur menyusul
B10: Regional 6 | C10: =N4R6!T83 -> 85.485773 | D10: ='Kertas Kerja'!L71*12/'Kertas Kerja'!K71 -> 83.512711 | E10: ='Kertas Kerja'!L72*12/'Kertas Kerja'!K72 -> 85.485773 | G10: ='Kertas Kerja'!L71*12/'Kertas Kerja'!K71 -> 83.512711 | K10: 7 | L10: PTPN I - Regional 1 | M10: Didik Prasetyo | N10: Region Head R1 | O10: ='Kertas Kerja'!L12*12/'Kertas Kerja'!K12 -> 95.415993
B11: Regional 7 | C11: =N4R7!T72 -> 77.278198 | D11: ='Kertas Kerja'!L76*12/'Kertas Kerja'!K76 -> 77.3547 | E11: ='Kertas Kerja'!L78*12/'Kertas Kerja'!K78 -> 77.278198 | G11: ='Kertas Kerja'!L77*12/'Kertas Kerja'!K77 -> 77.399186 | K11: 8 | L11: PTPN I - Regional 1 | M11: Wispramono Budiman | N11: SEVP Business Support R1 | O11: ='Kertas Kerja'!L13*12/'Kertas Kerja'!K13 -> 96.051929
K12: 9 | L12: PTPN I - Regional 1 | M12: Wispramono Budiman | N12: Plt Region Head R1 | O12: ='Kertas Kerja'!L14*12/'Kertas Kerja'!K14 -> 95.4
C13: Korporat | D13: Region Head | E13: SEVP Ops | F13: SEVP BS | G13: SEVP Aset | K13: 10 | L13: PTPN I - Regional 1 | M13: Ganda Wiatmaja | N13: SEVP Aset R1 | O13: ='Kertas Kerja'!L15*12/'Kertas Kerja'!K15 -> 96.051929
B14: SuppCo HO | C14: ='PTPN I'!U29 -> 81.726071 | K14: 11 | L14: PTPN I - Regional 2 | M14: Desmanto | N14: Region Head R2 | O14: ='Kertas Kerja'!L16*12/'Kertas Kerja'!K16 -> 81.971293
B15: Regional 1 | C15: =N1R1!O36 -> 93.508259 | D15: ='Kertas Kerja'!L12*12/'Kertas Kerja'!K12 -> 95.415993 | F15: ='Kertas Kerja'!L13*12/'Kertas Kerja'!K13 -> 96.051929 | G15: ='Kertas Kerja'!L15*12/'Kertas Kerja'!K15 -> 96.051929 | K15: 12 | L15: PTPN I - Regional 2 | M15: Iyan Heryanto | N15: SEVP Operation R2 | O15: ='Kertas Kerja'!L17*12/'Kertas Kerja'!K17 -> 80.074079
B16: Regional 2 | C16: =N1R2!O51 -> 85.73579 | D16: ='Kertas Kerja'!L16*12/'Kertas Kerja'!K16 -> 81.971293 | E16: ='Kertas Kerja'!L17*12/'Kertas Kerja'!K17 -> 80.074079 | F16: ='Kertas Kerja'!L18*12/'Kertas Kerja'!K18 -> 85.58976 | G16: ='Kertas Kerja'!L19*12/'Kertas Kerja'!K19 -> 85.58976 | K16: 13 | L16: PTPN I - Regional 2 | M16: Okta Kurniawan | N16: SEVP Business Support R2 | O16: ='Kertas Kerja'!L18*12/'Kertas Kerja'!K18 -> 85.58976
B17: Regional 3 | C17: =N1R3!O52 -> 89.82181 | D17: ='Kertas Kerja'!L20*12/'Kertas Kerja'!K20 -> 93.716363 | E17: ='Kertas Kerja'!L21*12/'Kertas Kerja'!K21 -> 91.091047 | K17: 14 | L17: PTPN I - Regional 2 | M17: Pulung Rinandoro | N17: SEVP Aset R2 | O17: ='Kertas Kerja'!L19*12/'Kertas Kerja'!K19 -> 85.58976
B18: Regional 4 | C18: =N1R4!O40 -> 78.91782 | D18: ='Kertas Kerja'!L22*12/'Kertas Kerja'!K22 -> 78.014818 | F18: ='Kertas Kerja'!L23*12/'Kertas Kerja'!K23 -> 76.285714 | K18: 15 | L18: PTPN I - Regional 3 | M18: Tri Septiono | N18: Region Head R3 | O18: ='Kertas Kerja'!L20*12/'Kertas Kerja'!K20 -> 93.716363
B19: Regional 5 | C19: =N1R5!O53 -> 91.736908 | D19: ='Kertas Kerja'!L25*12/'Kertas Kerja'!K25 -> 94.20555 | E19: ='Kertas Kerja'!L26*12/'Kertas Kerja'!K26 -> 91.818108 | F19: ='Kertas Kerja'!L27*12/'Kertas Kerja'!K27 -> 96.033058 | K19: 16 | L19: PTPN I - Regional 3 | M19: Budiyono | N19: SEVP Operation R3 | O19: ='Kertas Kerja'!L21*12/'Kertas Kerja'!K21 -> 91.091047
B20: Regional 6 | K20: 17 | L20: PTPN I - Regional 4 | M20: Subagiyo | N20: Region Head R4 | O20: ='Kertas Kerja'!L22*12/'Kertas Kerja'!K22 -> 78.014818
B21: Regional 7 | C21: =N1R7!O49 -> 82.061196 | D21: ='Kertas Kerja'!L28*12/'Kertas Kerja'!K28 -> 82.927896 | E21: ='Kertas Kerja'!L30*12/'Kertas Kerja'!K30 -> 82.078565 | F21: ='Kertas Kerja'!L29*12/'Kertas Kerja'!K29 -> 83.943905 | K21: 18 | L21: PTPN I - Regional 4 | M21: Subagiyo | N21: SEVP Business Support R5 | O21: ='Kertas Kerja'!L23*12/'Kertas Kerja'!K23 -> 76.285714
B22: Regional 8 | C22: =N1R8!O40 -> 80.194877 | D22: ='Kertas Kerja'!L32*12/'Kertas Kerja'!K32 -> 80.724997 | E22: ='Kertas Kerja'!L35*12/'Kertas Kerja'!K35 -> 81.1915 | F22: ='Kertas Kerja'!L33*12/'Kertas Kerja'!K33 -> 80.258495 | K22: 19 | L22: PTPN I - Regional 4 | M22: Subagiyo | N22: Ptr Region Head R5 | O22: ='Kertas Kerja'!L24*12/'Kertas Kerja'!K24 -> 78
K23: 20 | L23: PTPN I - Regional 5 | M23: Winarto | N23: Region Head R5 | O23: ='Kertas Kerja'!L25*12/'Kertas Kerja'!K25 -> 94.20555
C24: Korporat | D24: SEVP Koordinator KSO | E24: SEVP Operation | F24: SEVP Strategic Business | K24: 21 | L24: PTPN I - Regional 5 | M24: Asep Sontani | N24: SEVP Operation R5 | O24: ='Kertas Kerja'!L26*12/'Kertas Kerja'!K26 -> 91.818108
B25: SGN | C25: ='PT SGN'!AJ29 -> 73.663065 | D25: ='Kertas Kerja'!L87*12/'Kertas Kerja'!K87 -> 80.874179 | E25: ='Kertas Kerja'!L90*12/'Kertas Kerja'!K90 -> 80.874179 | F25: ='Kertas Kerja'!L85*12/'Kertas Kerja'!K85 -> 80.874179 | K25: 22 | L25: PTPN I - Regional 5 | M25: Benny Sandjaya | N25: SEVP Business Support R5 | O25: ='Kertas Kerja'!L27*12/'Kertas Kerja'!K27 -> 96.033058
K26: 23 | L26: PTPN I - Regional 7 | M26: Tuhu Bangun | N26: Regional Head R7 | O26: ='Kertas Kerja'!L28*12/'Kertas Kerja'!K28 -> 82.927896
C27: Korporat | D27: SEVP Ops | E27: SEVP BS | F27: SEVP Riset | G27: SEVP Ops 2 | K27: 24 | L27: PTPN I - Regional 7 | M27: Bambang Agustian | N27: SEVP Business Support R7 | O27: ='Kertas Kerja'!L29*12/'Kertas Kerja'!K29 -> 83.943905
B28: KPBN | C28: =KPBN!R29 -> 61.784112 | D28: =KPBN!Y29 -> 67.267769 | E28: =KPBN!AB29 -> 55.92232 | K28: 25 | L28: PTPN I - Regional 7 | M28: Wiyoso | N28: SEVP Operation R7 | O28: ='Kertas Kerja'!L30*12/'Kertas Kerja'!K30 -> 82.078565
B29: LPPAN | C29: =LPP!Q30 -> 101.12832 | D29: =LPP!X30 -> 104.94083 | E29: =LPP!AA30 -> 97.775816 | K29: 26 | L29: PTPN I - Regional 7 | M29: Iskandar Dewantara | N29: SEVP Busines Support R7 | O29: ='Kertas Kerja'!L31*12/'Kertas Kerja'!K31 -> 83.943905
B30: IKN | C30: =IKN!R33 -> 81.424634 | D30: =IKN!Y33 -> 84.960581 | K30: 27 | L30: PTPN I - Regional 8 | M30: R Tulus Panduwidjaja | N30: Regional Head R8 | O30: ='Kertas Kerja'!L32*12/'Kertas Kerja'!K32 -> 80.724997
B31: KINRA | C31: =KINRA!T35 -> 89.77349 | D31: =KINRA!AA35 -> 84.408548 | E31: =KINRA!AD35 -> 86.492949 | K31: 28 | L31: PTPN I - Regional 8 | M31: Maalun Lamau | N31: SEVP Business Support R8 | O31: ='Kertas Kerja'!L33*12/'Kertas Kerja'!K33 -> 80.258495
B32: SPMN | C32: =SPMN!R42 -> 91.026695 | D32: =SPMN!Y42 -> 93.027368 | K32: 29 | M32: Maalun Lamau | N32: Plt. Region Head R8 | O32: ='Kertas Kerja'!L34*12/'Kertas Kerja'!K34 -> 80.724997
B33: RPN | C33: =RPN!R33 -> 88.099317 | D33: =RPN!Y33 -> 87.009253 | E33: =RPN!AB33 -> 87.643837 | F33: =RPN!Y33 -> 87.009253 | G33: =RPN!Y33 -> 87.009253 | K33: 30 | L33: PTPN I - Regional 8 | M33: Misran | N33: SEVP Operation R8 | O33: ='Kertas Kerja'!L35*12/'Kertas Kerja'!K35 -> 81.1915
B34: BIN | C34: =BIN!R39 -> 64.782115 | D34: =BIN!Y39 -> 68.927603 | K34: 31 | L34: PTPN IV - Palm Co HO | M34: Jatmiko Krisna Santosa | N34: Direktur Utama | O34: ='Kertas Kerja'!L36*12/'Kertas Kerja'!K36 -> 89.8 | P34: Skor Direktur menyusul
K35: 32 | L35: PTPN IV - Palm Co HO | M35: Rizal H Damanik | N35: Direktur Operasional | O35: ='Kertas Kerja'!L37*12/'Kertas Kerja'!K37 -> 86.26 | P35: Skor Direktur menyusul
K36: 33 | L36: PTPN IV - Palm Co HO | M36: Ryanto Wisnuardhy | N36: Direktur Pemasaran dan Komersial | O36: ='Kertas Kerja'!L38*12/'Kertas Kerja'!K38 -> 96.56 | P36: Skor Direktur menyusul
K37: 34 | L37: PTPN IV - Palm Co HO | M37: Hilda Savitri | N37: Direktur Keuangan dan Manajemen Risiko | O37: ='Kertas Kerja'!L39*12/'Kertas Kerja'!K39 -> 93.89 | P37: Skor Direktur menyusul
K38: 35 | L38: PTPN IV - Palm Co HO | M38: Suhendri | N38: Direktur SDM dan TI | O38: ='Kertas Kerja'!L40*12/'Kertas Kerja'!K40 -> 87.43 | P38: Skor Direktur menyusul
K39: 36 | L39: PTPN IV - Palm Co HO | M39: Irwan Perangin Angin | N39: Direktur Hubungan Kelembagaan | O39: ='Kertas Kerja'!L41*12/'Kertas Kerja'!K41 -> 90.84 | P39: Skor Direktur menyusul
A40: No | B40: Anak Perusahaan | C40: Status LHEK | D40: Tanggal | K40: 37 | L40: PTPN IV - Palm Co HO | M40: Ugun Untaryo | N40: Direktur Strategic dan Sustainability | O40: ='Kertas Kerja'!L42*12/'Kertas Kerja'!K42 -> 85.4 | P40: Skor Direktur menyusul
A41: 1 | B41: PTPN I | C41: Unaudited | K41: 38 | L41: PTPN IV - Palm Co HO | M41: Rediman Silalahi | N41: SEVP Operation HO | P41: SEVP level HO - sumber skor belum ada
A42: 2 | B42: PTPN IV | C42: Unaudited | K42: 39 | L42: PTPN IV - Regional 1 | M42: Rurianto | N42: Regional Head R1 | O42: ='Kertas Kerja'!L44*12/'Kertas Kerja'!K44 -> 88.593044
A43: 3 | B43: SGN | C43: Unaudited | K43: 40 | L43: PTPN IV - Regional 1 | M43: Budi Susilo | N43: SEVP Operation I R1 | O43: ='Kertas Kerja'!L45*12/'Kertas Kerja'!K45 -> 89.727552
A44: 4 | B44: KPBN | C44: Unaudited | K44: 41 | L44: PTPN IV - Regional 1 | M44: Joni Raja Siregar | N44: SEVP Operation II R1 | O44: ='Kertas Kerja'!L46*12/'Kertas Kerja'!K46 -> 89.727552
A45: 5 | B45: LPPAN | C45: Unaudited | K45: 42 | L45: PTPN IV - Regional 1 | M45: Tengku Rinel | N45: SEVP Business Support R1 | O45: ='Kertas Kerja'!L47*12/'Kertas Kerja'!K47 -> 87.493371
A46: 6 | B46: IKN | C46: Unaudited | K46: 43 | L46: PTPN IV - Regional 1 | M46: Ahmad Diponegoro | N46: SEVP Business Support R1 | O46: ='Kertas Kerja'!L48*12/'Kertas Kerja'!K48 -> 87.493371
A47: 7 | B47: KINRA | C47: Unaudited | K47: 44 | L47: PTPN IV - Regional 1 | M47: Budi Susanto | N47: SEVP Business Support R1 | O47: ='Kertas Kerja'!L49*12/'Kertas Kerja'!K49 -> 87.493371
A48: 8 | B48: SPMN | C48: Unaudited | K48: 45 | L48: PTPN IV - Regional 2 | M48: Sudarma Bhakti Lessan | N48: Regional Head R2 | O48: ='Kertas Kerja'!L50*12/'Kertas Kerja'!K50 -> 87.528879
A49: 9 | B49: RPN | C49: Unaudited | K49: 46 | L49: PTPN IV - Regional 2 | M49: Budi Susilo | N49: SEVP Operation I R2 | O49: ='Kertas Kerja'!L51*12/'Kertas Kerja'!K51 -> 88.78702
A50: 10 | B50: BIN | C50: Unaudited | K50: 47 | L50: PTPN IV - Regional 2 | M50: Dedy Gurning | N50: SEVP Operation II R2 | O50: ='Kertas Kerja'!L52*12/'Kertas Kerja'!K52 -> 88.78702
K51: 48 | L51: PTPN IV - Regional 2 | M51: Budi Susanto | N51: Regional Head R2 | O51: ='Kertas Kerja'!L53*12/'Kertas Kerja'!K53 -> 87.528879
K52: 50 | L52: PTPN IV - Regional 2 | M52: Arief Subhan Siregar | N52: SEVP Operation I R2 | O52: ='Kertas Kerja'!L54*12/'Kertas Kerja'!K54 -> 88.78702
K53: 51 | L53: PTPN IV - Regional 2 | M53: Arief Subhan Siregar | N53: SEVP Business Support R2 | O53: ='Kertas Kerja'!L55*12/'Kertas Kerja'!K55 -> 85.464029
K54: 52 | L54: PTPN IV - Regional 2 | M54: Mulianto | N54: SEVP Operation I | O54: ='Kertas Kerja'!L56*12/'Kertas Kerja'!K56 -> 88.78702
K55: 53 | L55: PTPN IV - Regional 3 | M55: Yudhi Cahyadi | N55: SEVP Operation R3 | O55: ='Kertas Kerja'!L57*12/'Kertas Kerja'!K57 -> 90.239473
K56: 55 | L56: PTPN IV - Regional 3 | M56: Bambang Budi Santoso | N56: SEVP Business Support | O56: ='Kertas Kerja'!L58*12/'Kertas Kerja'!K58 -> 88.893676
K57: 56 | L57: PTPN IV - Regional 3 | M57: Sori Pardomuan Ritonga | N57: SEVP Operation | O57: ='Kertas Kerja'!L59*12/'Kertas Kerja'!K59 -> 90.239473
K58: 57 | L58: PTPN IV - Regional 4 | M58: Khayamuddin Panjaitan | N58: Regional Head R4 | O58: ='Kertas Kerja'!L60*12/'Kertas Kerja'!K60 -> 79.96698
K59: 58 | L59: PTPN IV - Regional 4 | M59: Ospin Sembiring | N59: Regional Head R4 | O59: ='Kertas Kerja'!L61*12/'Kertas Kerja'!K61 -> 79.96698
K60: 59 | L60: PTPN IV - Regional 4 | M60: Ifri Handi Lubis | N60: SEVP Business Support R4 | O60: ='Kertas Kerja'!L62*12/'Kertas Kerja'!K62 -> 77.041735
K61: 60 | L61: PTPN IV - Regional 4 | M61: Achmedi Akbar | N61: SEVP Business Support R4 | O61: ='Kertas Kerja'!L63*12/'Kertas Kerja'!K63 -> 77.041735
K62: 62 | L62: PTPN IV - Regional 4 | M62: Bambang Agustian | N62: SEVP Operation | O62: ='Kertas Kerja'!L64*12/'Kertas Kerja'!K64 -> 80.595579
... K76: 76 | L76: PTPN IV - Regional 7 | M76: Rina Tanjung | N76: SEVP Operation R7 | O76: ='Kertas Kerja'!L78*12/'Kertas Kerja'!K78 -> 77.278198
K77: 77 | L77: PT SGN | M77: Mahmudi | N77: Direktur Utama | P77: Skor Direktur menyusul
K78: 78 | L78: PT SGN | M78: Dodik Ristiawan | N78: Direktur Operasional | P78: Skor Direktur menyusul
K79: 79 | L79: PT SGN | M79: Hariyanto | N79: Direktur Keuangan | P79: Skor Direktur menyusul
K80: 80 | L80: PT SGN | M80: Affan Safiq | N80: Direktur SDM dan TI | P80: Skor Direktur menyusul
K81: 81 | L81: PT SGN | M81: Aris Toharisman | N81: Direktur Hubungan Kelembagaan dan Manajemen Risiko | P81: Skor Direktur menyusul
K82: 82 | L82: PT SGN | M82: M Fakhrur Rozi | N82: Direktur Manajemen Risiko | P82: Skor Direktur menyusul
K83: 83 | L83: PT SGN | M83: Dimas Eko Prasetyo | N83: SEVP Operation I / SEVP Strategic Business | O83: ='Kertas Kerja'!L85*12/'Kertas Kerja'!K85 -> 80.874179
K84: 84 | L84: PT SGN | M84: Dimas Eko Prasetyo | N84: Direktur Strategi & Sustainability | P84: Skor Direktur menyusul
K85: 85 | L85: PT SGN | M85: Imam Cipto Suyitno | N85: SEVP Operation II / SEVP Koordinator KSO | O85: ='Kertas Kerja'!L87*12/'Kertas Kerja'!K87 -> 80.874179
K86: 86 | L86: PT SGN | M86: Putu Sukarmen | N86: SEVP Pengembangan | O86: ='Kertas Kerja'!L88*12/'Kertas Kerja'!K88 -> 80.874179
K87: 87 | L87: PT SGN | M87: R Tulus Panduwidjaja | N87: SEVP Business Support | O87: ='Kertas Kerja'!L89*12/'Kertas Kerja'!K89 -> 66.45023
K88: 88 | L88: PT SGN | M88: Febri Ari Marpaung | N88: SEVP Operasional KSO | O88: ='Kertas Kerja'!L90*12/'Kertas Kerja'!K90 -> 80.874179
K89: 89 | L89: PT SGN | M89: Febri Ari Marpaung | N89: SEVP Koordinator KSO | O89: ='Kertas Kerja'!L91*12/'Kertas Kerja'!K91 -> 80.874179
K90: 90 | L90: PT RPN | M90: Iman Yani Harahap | N90: Direktur | O90: ='Kertas Kerja'!L92*12/'Kertas Kerja'!K92 -> 88.099317
K91: 91 | L91: PT RPN | M91: Tjahjono Herawan | N91: SEVP Operation I | O91: ='Kertas Kerja'!L93*12/'Kertas Kerja'!K93 -> 87.009253
K92: 92 | L92: PT RPN | M92: Misnawi | N92: SEVP Operation II | O92: ='Kertas Kerja'!L94*12/'Kertas Kerja'!K94 -> 87.009253
K93: 93 | L93: PT RPN | M93: Edy Suprianto | N93: SEVP Business Support | O93: ='Kertas Kerja'!L95*12/'Kertas Kerja'!K95 -> 87.643837
K94: 94 | L94: PT RPN | M94: Muhammad Edwin Syahputra | N94: SEVP Riset, Inovasi, dan Sustainability | O94: ='Kertas Kerja'!L96*12/'Kertas Kerja'!K96 -> 87.009253
K95: 95 | L95: PT LPPAN | M95: Pranoto Hadi Raharjo | N95: Direktur | O95: ='Kertas Kerja'!L97*12/'Kertas Kerja'!K97 -> 101.12832
K96: 96 | L96: PT LPPAN | M96: Pugar Indriawan | N96: SEVP Operation | O96: ='Kertas Kerja'!L98*12/'Kertas Kerja'!K98 -> 104.94083
... K108: 108 | L108: PT BIN | M108: Dede Kusdiman | N108: SEVP Operation | O108: ='Kertas Kerja'!L110*12/'Kertas Kerja'!K110 -> 68.927603
K109: 109 | L109: PT INL | M109: Darwin Hasibuan | N109: Direktur | P109: Sheet KPI INL belum ada
K110: 110 | L110: PT INL | M110: Rahmanto Amin Jatmiko | N110: Direktur | P110: Sheet KPI INL belum ada
K111: 111 | L111: PT INL | M111: Ipan Gumara Siahaan | N111: SEVP Operation | P111: Sheet KPI INL belum ada
K112: 112 | L112: PT INL | M112: Zulianto | N112: SEVP Business Support | P112: Sheet KPI INL belum ada
K113: 113 | L113: PT KPBN | M113: M. Iswan Achir | N113: Direktur | O113: ='Kertas Kerja'!L115*12/'Kertas Kerja'!K115 -> 61.784112
K114: 114 | L114: PT KPBN | M114: Arif Budiman | N114: SEVP Operation I | O114: ='Kertas Kerja'!L116*12/'Kertas Kerja'!K116 -> 67.267769
K115: 115 | L115: PT KPBN | M115: Arif Budiman | N115: SEVP Operation | O115: ='Kertas Kerja'!L117*12/'Kertas Kerja'!K117 -> 67.267769
K116: 116 | L116: PT KPBN | M116: Iskandar Dewantara | N116: SEVP Business Support | O116: ='Kertas Kerja'!L118*12/'Kertas Kerja'!K118 -> 55.92232
K117: 117 | L117: PT KPBN | M117: Muhammad Zulham Rambe | N117: SEVP Operation | O117: ='Kertas Kerja'!L119*12/'Kertas Kerja'!K119 -> 67.267769
K118: 118 | L118: PT KPBN | M118: Indaruwati Trivista Andarini | N118: SEVP Business Support | O118: ='Kertas Kerja'!L120*12/'Kertas Kerja'!K120 -> 55.92232
K119: 119 | L119: PT KPBN | M119: Iskandar Dewantara | N119: SEVP Business Support | O119: ='Kertas Kerja'!L121*12/'Kertas Kerja'!K121 -> 55.92232

Sheet List
A3: No | B3: PTPN | C3: Nama Pejabat | D3: Jabatan | E3: Periode Menjabat Tahun 2025 | G3: Hari | H3: Bulan | I3: Asal Entitas | J3: Status | K3: NIK
E4: Awal Menjabat | F4: Akhir Menjabat
A5: Supporting Co
A6: 1 | B6: PTPN I - Supporting Co HO | C6: Teddy Yunirman Danas | D6: Direktur Utama | E6: 45658 | F6: 46022 | G6: =DATEDIF(E6,F6,"d")+1 -> 365 | H6: =DATEDIF(E6,F6,"M") + IF(DATEDIF(E6,F6,"MD")>=15,1,0) -> 12 | I6: PTPN I - Supporting Co HO | J6: PKWT
A7: 2 | B7: PTPN I - Supporting Co HO | C7: Fauzi Omar | D7: Direktur Operasional | E7: 45658 | F7: 46022 | G7: =DATEDIF(E7,F7,"d")+1 -> 365 | H7: =DATEDIF(E7,F7,"M") + IF(DATEDIF(E7,F7,"MD")>=15,1,0) -> 12 | I7: PTPN I - Supporting Co HO | J7: PKWT | N7: 1 | O7: N3
A8: =A7+1 -> 3 | B8: PTPN I - Supporting Co HO | C8: Landi Rizaldi Mangaweang | D8: Direktur Pemasaran dan Aset | E8: 45658 | F8: 46022 | G8: =DATEDIF(E8,F8,"d")+1 -> 365 | H8: =DATEDIF(E8,F8,"M") + IF(DATEDIF(E8,F8,"MD")>=15,1,0) -> 12 | I8: PTPN I - Supporting Co HO | J8: PKWT | N8: 2 | O8: N1
A9: =A8+1 -> 4 | B9: PTPN I - Supporting Co HO | C9: Doni P Gandamihardja | D9: Direktur Keuangan dan Manajemen Risiko | E9: 45658 | F9: 46022 | G9: =DATEDIF(E9,F9,"d")+1 -> 365 | H9: =DATEDIF(E9,F9,"M") + IF(DATEDIF(E9,F9,"MD")>=15,1,0) -> 12 | I9: PTPN I - Supporting Co HO | J9: PKWT | N9: 3 | O9: N4
A10: =A9+1 -> 5 | B10: PTPN I - Supporting Co HO | C10: Siwi Peni | D10: Direktur SDM dan TI | E10: 45658 | F10: 46022 | G10: =DATEDIF(E10,F10,"d")+1 -> 365 | H10: =DATEDIF(E10,F10,"M") + IF(DATEDIF(E10,F10,"MD")>=15,1,0) -> 12 | I10: PTPN I - Supporting Co HO | J10: PKWT | N10: 4 | O10: SGN
A11: =A10+1 -> 6 | B11: PTPN I - Supporting Co HO | C11: Tio Handoko | D11: Direktur Hubungan Kelembagaan | E11: 45658 | F11: 46022 | G11: =DATEDIF(E11,F11,"d")+1 -> 365 | H11: =DATEDIF(E11,F11,"M") + IF(DATEDIF(E11,F11,"MD")>=15,1,0) -> 12 | I11: PTPN I - Supporting Co HO | J11: PKWT | N11: 5 | O11: RPN
A12: 7 | B12: PTPN I - Regional 1 | C12: Didik Prasetyo | D12: Region Head R1 | E12: 45658 | F12: 45961 | G12: =DATEDIF(E12,F12,"d")+1 -> 304 | H12: =DATEDIF(E12,F12,"M") + IF(DATEDIF(E12,F12,"MD")>=15,1,0) -> 10 | I12: PTPN I - Regional 1 | J12: PKWT | N12: 6 | O12: KPBN
A13: =A12+1 -> 8 | B13: PTPN I - Regional 1 | C13: Wispramono Budiman | D13: SEVP Business Support R1 | E13: 45658 | F13: 46022 | G13: =DATEDIF(E13,F13,"d")+1 -> 365 | H13: =DATEDIF(E13,F13,"M") + IF(DATEDIF(E13,F13,"MD")>=15,1,0) -> 12 | I13: PTPN I - Regional 1 | J13: PKWTT | K13: 8100026 | N13: 7 | O13: LPPAN
C14: Wispramono Budiman | D14: Plt Region Head R1 | E14: 45962 | F14: 46022 | G14: =DATEDIF(E14,F14,"d")+1 -> 61 | H14: =DATEDIF(E14,F14,"M") + IF(DATEDIF(E14,F14,"MD")>=15,1,0) -> 2 | I14: PTPN I - Regional 1 | J14: PKWTT | K14: 8100026 | N14: 8 | O14: BIN
A15: =A13+1 -> 9 | B15: PTPN I - Regional 1 | C15: Ganda Wiatmaja | D15: SEVP Aset R1 | E15: 45662 | F15: 46022 | G15: =DATEDIF(E15,F15,"d")+1 -> 361 | H15: =DATEDIF(E15,F15,"M") + IF(DATEDIF(E15,F15,"MD")>=15,1,0) -> 12 | I15: PTPN I - Regional 1 | J15: PKWTT | K15: 3023289 | N15: 9 | O15: SPMN
A16: =A15+1 -> 10 | B16: PTPN I - Regional 2 | C16: Desmanto | D16: Region Head R2 | E16: 45658 | F16: 46022 | G16: =DATEDIF(E16,F16,"d")+1 -> 365 | H16: =DATEDIF(E16,F16,"M") + IF(DATEDIF(E16,F16,"MD")>=15,1,0) -> 12 | I16: PTPN I - Regional 2 | J16: PKWT | N16: 10 | O16: IKN
A17: =A16+1 -> 11 | B17: PTPN I - Regional 2 | C17: Iyan Heryanto | D17: SEVP Operation R2 | E17: 45658 | F17: 46022 | G17: =DATEDIF(E17,F17,"d")+1 -> 365 | H17: =DATEDIF(E17,F17,"M") + IF(DATEDIF(E17,F17,"MD")>=15,1,0) -> 12 | I17: PTPN I - Regional 2 | J17: PKWTT | K17: 13002790 | N17: 11 | O17: KINRA
A18: =A17+1 -> 12 | B18: PTPN I - Regional 2 | C18: Okta Kurniawan | D18: SEVP Business Support R2 | E18: 45658 | F18: 46022 | G18: =DATEDIF(E18,F18,"d")+1 -> 365 | H18: =DATEDIF(E18,F18,"M") + IF(DATEDIF(E18,F18,"MD")>=15,1,0) -> 12 | I18: PTPN I - Regional 2 | J18: PKWTT | K18: 7001902
A19: =A18+1 -> 13 | B19: PTPN I - Regional 2 | C19: Pulung Rinandoro | D19: SEVP Aset R2 | E19: 45658 | F19: 46022 | G19: =DATEDIF(E19,F19,"d")+1 -> 365 | H19: =DATEDIF(E19,F19,"M") + IF(DATEDIF(E19,F19,"MD")>=15,1,0) -> 12 | I19: PTPN I - Regional 2 | J19: PKWT
A20: =A19+1 -> 14 | B20: PTPN I - Regional 3 | C20: Tri Septiono | D20: Region Head R3 | E20: 45658 | F20: 46022 | G20: =DATEDIF(E20,F20,"d")+1 -> 365 | H20: =DATEDIF(E20,F20,"M") + IF(DATEDIF(E20,F20,"MD")>=15,1,0) -> 12 | I20: PTPN I - Regional 3 | J20: PKWT
A21: =A20+1 -> 15 | B21: PTPN I - Regional 3 | C21: Budiyono | D21: SEVP Operation R3 | E21: 45658 | F21: 46022 | G21: =DATEDIF(E21,F21,"d")+1 -> 365 | H21: =DATEDIF(E21,F21,"M") + IF(DATEDIF(E21,F21,"MD")>=15,1,0) -> 12 | I21: PTPN I - Regional 3 | J21: PKWTT | K21: 9000134
A22: =A21+1 -> 16 | B22: PTPN I - Regional 4 | C22: Subagiyo | D22: Region Head R4 | E22: 45658 | F22: 45808 | G22: =DATEDIF(E22,F22,"d")+1 -> 151 | H22: =DATEDIF(E22,F22,"M") + IF(DATEDIF(E22,F22,"MD")>=15,1,0) -> 5 | I22: PTPN I - Regional 5 | J22: PKWTT | K22: 11000154
C23: Subagiyo | D23: SEVP Business Support R5 | E23: 45809 | F23: 46022 | G23: =DATEDIF(E23,F23,"d")+1 -> 214 | H23: =DATEDIF(E23,F23,"M") + IF(DATEDIF(E23,F23,"MD")>=15,1,0) -> 7 | I23: PTPN I - Regional 5 | J23: PKWTT | K23: 11000154
C24: Subagiyo | D24: Ptr Region Head R5 | E24: 45992 | F24: 46022 | G24: =DATEDIF(E24,F24,"d")+1 -> 31 | H24: =DATEDIF(E24,F24,"M") + IF(DATEDIF(E24,F24,"MD")>=15,1,0) -> 1 | I24: PTPN I - Regional 5 | J24: PKWTT | K24: 11000154
A25: 17 | B25: PTPN I - Regional 5 | C25: Winarto | D25: Region Head R5 | E25: 45658 | F25: 45991 | G25: =DATEDIF(E25,F25,"d")+1 -> 334 | H25: =DATEDIF(E25,F25,"M") + IF(DATEDIF(E25,F25,"MD")>=15,1,0) -> 11 | I25: PTPN I - Regional 5 | J25: PKWTT | K25: 12020544
A26: =A25+1 -> 18 | B26: PTPN I - Regional 5 | C26: Asep Sontani | D26: SEVP Operation R5 | E26: 45658 | F26: 46022 | G26: =DATEDIF(E26,F26,"d")+1 -> 365 | H26: =DATEDIF(E26,F26,"M") + IF(DATEDIF(E26,F26,"MD")>=15,1,0) -> 12 | I26: PTPN I - Regional 5 | J26: PKWTT | K26: 9005498
A27: =A26+1 -> 19 | B27: PTPN I - Regional 5 | C27: Benny Sandjaya | D27: SEVP Business Support R5 | E27: 45658 | F27: 45808 | G27: =DATEDIF(E27,F27,"d")+1 -> 151 | H27: =DATEDIF(E27,F27,"M") + IF(DATEDIF(E27,F27,"MD")>=15,1,0) -> 5 | I27: PTPN I - Regional 5 | J27: PKWTT | K27: 10000045
A28: =A27+1 -> 20 | B28: PTPN I - Regional 7 | C28: Tuhu Bangun | D28: Regional Head R7 | E28: 45658 | F28: 46022 | G28: =DATEDIF(E28,F28,"d")+1 -> 365 | H28: =DATEDIF(E28,F28,"M") + IF(DATEDIF(E28,F28,"MD")>=15,1,0) -> 12 | I28: PTPN I - Regional 7 | J28: PKWT
A29: =A28+1 -> 21 | B29: PTPN I - Regional 7 | C29: Bambang Agustian | D29: SEVP Business Support R7 | E29: 45658 | F29: 45808 | G29: =DATEDIF(E29,F29,"d")+1 -> 151 | H29: =DATEDIF(E29,F29,"M") + IF(DATEDIF(E29,F29,"MD")>=15,1,0) -> 5 | I29: PTPN I - Regional 7 | J29: PKWTT | K29: 4009842
A30: =A29+1 -> 22 | B30: PTPN I - Regional 7 | C30: Wiyoso | D30: SEVP Operation R7 | E30: 45658 | F30: 46022 | G30: =DATEDIF(E30,F30,"d")+1 -> 365 | H30: =DATEDIF(E30,F30,"M") + IF(DATEDIF(E30,F30,"MD")>=15,1,0) -> 12 | I30: PTPN I - Regional 7 | J30: PKWTT | K30: 7003199
A31: =A30+1 -> 23 | B31: PTPN I - Regional 7 | C31: Iskandar Dewantara | D31: SEVP Busines Support R7 | E31: 45809 | F31: 46022 | G31: =DATEDIF(E31,F31,"d")+1 -> 214 | H31: =DATEDIF(E31,F31,"M") + IF(DATEDIF(E31,F31,"MD")>=15,1,0) -> 7 | I31: PTPN I - Regional 7 | J31: PKWTT | K31: 4000040
A32: =A31+1 -> 24 | B32: PTPN I - Regional 8 | C32: R Tulus Panduwidjaja | D32: Regional Head R8 | E32: 45658 | F32: 45808 | G32: =DATEDIF(E32,F32,"d")+1 -> 151 | H32: =DATEDIF(E32,F32,"M") + IF(DATEDIF(E32,F32,"MD")>=15,1,0) -> 5 | I32: PTPN I - Regional 8 | J32: PKWT
A33: =A32+1 -> 25 | B33: PTPN I - Regional 8 | C33: Maalun Lamau | D33: SEVP Business Support R8 | E33: 45658 | F33: 46022 | G33: =DATEDIF(E33,F33,"d")+1 -> 365 | H33: =DATEDIF(E33,F33,"M") + IF(DATEDIF(E33,F33,"MD")>=15,1,0) -> 12 | I33: PTPN I - Regional 8 | J33: PKWTT | K33: 14000204
C34: Maalun Lamau | D34: Plt. Region Head R8 | E34: 45658 | F34: 46022 | G34: =DATEDIF(E34,F34,"d")+1 -> 365 | H34: =DATEDIF(E34,F34,"M") + IF(DATEDIF(E34,F34,"MD")>=15,1,0) -> 12 | I34: PTPN I - Regional 8 | J34: PKWTT | K34: 14000204
A35: 26 | B35: PTPN I - Regional 8 | C35: Misran | D35: SEVP Operation R8 | E35: 45809 | F35: 46022 | G35: =DATEDIF(E35,F35,"d")+1 -> 214 | H35: =DATEDIF(E35,F35,"M") + IF(DATEDIF(E35,F35,"MD")>=15,1,0) -> 7 | I35: PTPN I - Regional 8 | J35: PKWTT
A39: Palm Co
A40: 1 | B40: PTPN IV - Palm Co HO | C40: Jatmiko Krisna Santosa | D40: Direktur Utama | E40: 45658 | F40: 46022 | G40: =DATEDIF(E40,F40,"d")+1 -> 365 | H40: =DATEDIF(E40,F40,"M") + IF(DATEDIF(E40,F40,"MD")>=15,1,0) -> 12 | I40: PTPN IV - Palm Co HO | J40: PKWT
A41: 2 | B41: PTPN IV - Palm Co HO | C41: Rizal H Damanik | D41: Direktur Operasional | E41: 45658 | F41: 45823 | G41: =DATEDIF(E41,F41,"d")+1 -> 166 | H41: =DATEDIF(E41,F41,"M") + IF(DATEDIF(E41,F41,"MD")>=15,1,0) -> 5 | I41: PTPN IV - Palm Co HO | J41: PKWT
A42: 3 | B42: PTPN IV - Palm Co HO | C42: Ryanto Wisnuardhy | D42: Direktur Pemasaran dan Komersial | E42: 45658 | F42: 45823 | G42: =DATEDIF(E42,F42,"d")+1 -> 166 | H42: =DATEDIF(E42,F42,"M") + IF(DATEDIF(E42,F42,"MD")>=15,1,0) -> 5 | I42: PTPN IV - Palm Co HO | J42: PKWT
A43: 4 | B43: PTPN IV - Palm Co HO | C43: Hilda Savitri | D43: Direktur Keuangan dan Manajemen Risiko | E43: 45658 | F43: 46022 | G43: =DATEDIF(E43,F43,"d")+1 -> 365 | H43: =DATEDIF(E43,F43,"M") + IF(DATEDIF(E43,F43,"MD")>=15,1,0) -> 12 | I43: PTPN IV - Palm Co HO | J43: PKWT
A44: 5 | B44: PTPN IV - Palm Co HO | C44: Suhendri | D44: Direktur SDM dan TI | E44: 45658 | F44: 46022 | G44: =DATEDIF(E44,F44,"d")+1 -> 365 | H44: =DATEDIF(E44,F44,"M") + IF(DATEDIF(E44,F44,"MD")>=15,1,0) -> 12 | I44: PTPN IV - Palm Co HO | J44: PKWT
A45: 6 | B45: PTPN IV - Palm Co HO | C45: Irwan Perangin Angin | D45: Direktur Hubungan Kelembagaan | E45: 45658 | F45: 45972 | G45: =DATEDIF(E45,F45,"d")+1 -> 315 | H45: =DATEDIF(E45,F45,"M") + IF(DATEDIF(E45,F45,"MD")>=15,1,0) -> 10 | I45: PTPN IV - Palm Co HO | J45: PKWT
A46: 7 | B46: PTPN IV - Palm Co HO | C46: Ugun Untaryo | D46: Direktur Strategic dan Sustainability | E46: 45658 | F46: 46022 | G46: =DATEDIF(E46,F46,"d")+1 -> 365 | H46: =DATEDIF(E46,F46,"M") + IF(DATEDIF(E46,F46,"MD")>=15,1,0) -> 12 | I46: PTPN IV - Palm Co HO | J46: PKWT
A47: 8 | B47: PTPN IV - Regional 1 | C47: Rurianto | D47: Regional Head R1 | E47: 45658 | F47: 46022 | G47: =DATEDIF(E47,F47,"d")+1 -> 365 | H47: =DATEDIF(E47,F47,"M") + IF(DATEDIF(E47,F47,"MD")>=15,1,0) -> 12 | I47: PTPN IV - Regional 1 | J47: PKWT
A48: 9 | B48: PTPN IV - Regional 1 | C48: Budi Susilo | D48: SEVP Operation I R1 | E48: 45658 | F48: 46022 | G48: =DATEDIF(E48,F48,"d")+1 -> 365 | H48: =DATEDIF(E48,F48,"M") + IF(DATEDIF(E48,F48,"MD")>=15,1,0) -> 12 | I48: PTPN IV - Regional 1 | J48: PKWTT | K48: 7015491
A49: 10 | B49: PTPN IV - Regional 1 | C49: Joni Raja Siregar | D49: SEVP Operation II R1 | E49: 45658 | F49: 46022 | G49: =DATEDIF(E49,F49,"d")+1 -> 365 | H49: =DATEDIF(E49,F49,"M") + IF(DATEDIF(E49,F49,"MD")>=15,1,0) -> 12 | I49: PTPN IV - Regional 1 | J49: PKWT
A50: 11 | B50: PTPN IV - Regional 1 | C50: Tengku Rinel | D50: SEVP Business Support R1 | E50: 45658 | F50: 45691 | G50: =DATEDIF(E50,F50,"d")+1 -> 34 | H50: =DATEDIF(E50,F50,"M") + IF(DATEDIF(E50,F50,"MD")>=15,1,0) -> 1 | I50: PTPN IV - Regional 1 | J50: PKWT
A51: 12 | B51: PTPN IV - Regional 1 | C51: Ahmad Diponegoro | D51: SEVP Business Support R1 | E51: 45809 | F51: 46022 | G51: =DATEDIF(E51,F51,"d")+1 -> 214 | H51: =DATEDIF(E51,F51,"M") + IF(DATEDIF(E51,F51,"MD")>=15,1,0) -> 7 | I51: PTPN IV - Regional 1 | J51: PKWTT | K51: 14002084
A52: 13 | B52: PTPN IV - Regional 1 | C52: Budi Susanto | D52: SEVP Business Support R1 | E52: 45658 | F52: 45727 | G52: =DATEDIF(E52,F52,"d")+1 -> 70 | H52: =DATEDIF(E52,F52,"M") + IF(DATEDIF(E52,F52,"MD")>=15,1,0) -> 2 | I52: PTPN IV - Regional 1 | J52: PKWTT | K52: 4000041
A53: 14 | B53: PTPN IV - Regional 2 | C53: Sudarma Bhakti Lessan | D53: Regional Head R2 | E53: 45658 | F53: 45728 | G53: =DATEDIF(E53,F53,"d")+1 -> 71 | H53: =DATEDIF(E53,F53,"M") + IF(DATEDIF(E53,F53,"MD")>=15,1,0) -> 2 | I53: PTPN IV - Regional 2 | J53: PKWT | K53: 3023272
A54: 15 | B54: PTPN IV - Regional 2 | C54: Budi Susilo | D54: SEVP Operation I R2 | E54: 45658 | F54: 45992 | G54: =DATEDIF(E54,F54,"d")+1 -> 335 | H54: =DATEDIF(E54,F54,"M") + IF(DATEDIF(E54,F54,"MD")>=15,1,0) -> 11 | I54: PTPN IV - Regional 2 | J54: PKWTT | K54: 7015491
A55: 16 | B55: PTPN IV - Regional 2 | C55: Dedy Gurning | D55: SEVP Operation II R2 | E55: 45658 | F55: 46022 | G55: =DATEDIF(E55,F55,"d")+1 -> 365 | H55: =DATEDIF(E55,F55,"M") + IF(DATEDIF(E55,F55,"MD")>=15,1,0) -> 12 | I55: PTPN IV - Regional 2 | J55: PKWTT | K55: 2000309
A56: 17 | B56: PTPN IV - Regional 2 | C56: Budi Susanto | D56: Regional Head R2 | E56: 45727 | F56: 46022 | G56: =DATEDIF(E56,F56,"d")+1 -> 296 | H56: =DATEDIF(E56,F56,"M") + IF(DATEDIF(E56,F56,"MD")>=15,1,0) -> 10 | I56: PTPN IV - Regional 2 | J56: PKWTT | K56: 4000041
A57: 18 | B57: PTPN IV - Regional 2 | C57: Ahmad Diponegoro | D57: SEVP Business Support R2 | E57: 45692 | F57: 45809 | G57: =DATEDIF(E57,F57,"d")+1 -> 118 | H57: =DATEDIF(E57,F57,"M") + IF(DATEDIF(E57,F57,"MD")>=15,1,0) -> 4 | I57: PTPN IV - Regional 2 | J57: PKWTT | K57: 14002084
A58: 19 | B58: PTPN IV - Regional 2 | C58: Arief Subhan Siregar | D58: SEVP Operation I R2 | E58: 45658 | F58: 45808 | G58: =DATEDIF(E58,F58,"d")+1 -> 151 | H58: =DATEDIF(E58,F58,"M") + IF(DATEDIF(E58,F58,"MD")>=15,1,0) -> 5 | I58: PTPN IV - Regional 2 | J58: PKWTT | K58: 5000189
A59: 20 | B59: PTPN IV - Regional 2 | C59: Arief Subhan Siregar | D59: SEVP Business Support R2 | E59: 45809 | F59: 46022 | G59: =DATEDIF(E59,F59,"d")+1 -> 214 | H59: =DATEDIF(E59,F59,"M") + IF(DATEDIF(E59,F59,"MD")>=15,1,0) -> 7 | I59: PTPN IV - Regional 2 | J59: PKWTT | K59: 5000189
A60: 21 | B60: PTPN IV - Regional 2 | C60: Mulianto | D60: SEVP Operation I | E60: 45809 | F60: 46022 | G60: =DATEDIF(E60,F60,"d")+1 -> 214 | H60: =DATEDIF(E60,F60,"M") + IF(DATEDIF(E60,F60,"MD")>=15,1,0) -> 7 | I60: PTPN IV - Regional 2 | J60: PKWTT
A61: 22 | B61: PTPN IV - Regional 3 | C61: Yudhi Cahyadi | D61: SEVP Operation R3 | E61: 45658 | F61: 45916 | G61: =DATEDIF(E61,F61,"d")+1 -> 259 | H61: =DATEDIF(E61,F61,"M") + IF(DATEDIF(E61,F61,"MD")>=15,1,0) -> 9 | I61: PTPN IV - Regional 3 | J61: PKWTT | K61: 3000783
A62: 23 | B62: PTPN IV - Regional 3 | C62: Ahmad Diponegoro | D62: SEVP Business Support R3 | E62: 45658 | F62: 45691 | G62: =DATEDIF(E62,F62,"d")+1 -> 34 | H62: =DATEDIF(E62,F62,"M") + IF(DATEDIF(E62,F62,"MD")>=15,1,0) -> 1 | I62: PTPN IV - Regional 3 | J62: PKWTT | K62: 14002084
A63: 24 | B63: PTPN IV - Regional 3 | C63: Bambang Budi Santoso | D63: SEVP Business Support | E63: 45692 | F63: 46022 | G63: =DATEDIF(E63,F63,"d")+1 -> 331 | H63: =DATEDIF(E63,F63,"M") + IF(DATEDIF(E63,F63,"MD")>=15,1,0) -> 11 | I63: PTPN IV - Regional 3 | J63: PKWTT
A64: 25 | B64: PTPN IV - Regional 3 | C64: Sori Pardomuan Ritonga | D64: SEVP Operation | E64: 45922 | F64: 46022 | G64: =DATEDIF(E64,F64,"d")+1 -> 101 | H64: =DATEDIF(E64,F64,"M") + IF(DATEDIF(E64,F64,"MD")>=15,1,0) -> 3 | I64: PTPN IV - Regional 3 | J64: PKWTT
A65: 26 | B65: PTPN IV - Regional 4 | C65: Khayamuddin Panjaitan | D65: Regional Head R4 | E65: 45658 | F65: 46022 | G65: =DATEDIF(E65,F65,"d")+1 -> 365 | H65: =DATEDIF(E65,F65,"M") + IF(DATEDIF(E65,F65,"MD")>=15,1,0) -> 12 | I65: PTPN IV - Regional 4 | J65: PKWTT | K65: 13000002
A66: 27 | B66: PTPN IV - Regional 4 | C66: Ospin Sembiring | D66: Regional Head R4 | E66: 45658 | F66: 45728 | G66: =DATEDIF(E66,F66,"d")+1 -> 71 | H66: =DATEDIF(E66,F66,"M") + IF(DATEDIF(E66,F66,"MD")>=15,1,0) -> 2 | I66: PTPN IV - Regional 4 | J66: PKWTT
A67: 28 | B67: PTPN IV - Regional 4 | C67: Ifri Handi Lubis | D67: SEVP Business Support R4 | E67: 45658 | F67: 45809 | G67: =DATEDIF(E67,F67,"d")+1 -> 152 | H67: =DATEDIF(E67,F67,"M") + IF(DATEDIF(E67,F67,"MD")>=15,1,0) -> 5 | I67: PTPN IV - Regional 4 | J67: PKWTT | K67: 5000222
A68: 29 | B68: PTPN IV - Regional 4 | C68: Achmedi Akbar | D68: SEVP Business Support R4 | E68: 45809 | F68: 46022 | G68: =DATEDIF(E68,F68,"d")+1 -> 214 | H68: =DATEDIF(E68,F68,"M") + IF(DATEDIF(E68,F68,"MD")>=15,1,0) -> 7 | I68: PTPN IV - Regional 4 | J68: PKWTT | K68: 6608005
A69: 30 | B69: PTPN IV - Regional 4 | C69: Achmedi Akbar | D69: SEVP Operation | E69: 45658 | F69: 45809 | G69: =DATEDIF(E69,F69,"d")+1 -> 152 | H69: =DATEDIF(E69,F69,"M") + IF(DATEDIF(E69,F69,"MD")>=15,1,0) -> 5 | I69: PTPN IV - Regional 4 | J69: PKWTT | K69: 6608005
A70: 30 | B70: PTPN IV - Regional 4 | C70: Bambang Agustian | D70: SEVP Operation | E70: 45658 | F70: 45809 | G70: =DATEDIF(E70,F70,"d")+1 -> 152 | H70: =DATEDIF(E70,F70,"M") + IF(DATEDIF(E70,F70,"MD")>=15,1,0) -> 5 | I70: PTPN IV - Regional 4 | J70: PKWTT | K70: 6608005
A71: 32 | B71: PTPN IV - Regional 5 | C71: Sudarma Bhakti Lessan | D71: Regional Head R5 | E71: 45728 | F71: 46022 | G71: =DATEDIF(E71,F71,"d")+1 -> 295 | H71: =DATEDIF(E71,F71,"M") + IF(DATEDIF(E71,F71,"MD")>=15,1,0) -> 10 | I71: PTPN IV - Regional 5 | J71: PKWT | K71: 3023272
A72: 33 | B72: PTPN IV - Regional 5 | C72: Darmansyah Siregar | D72: SEVP Operation I R5 | E72: 45658 | F72: 45879 | G72: =DATEDIF(E72,F72,"d")+1 -> 222 | H72: =DATEDIF(E72,F72,"M") + IF(DATEDIF(E72,F72,"MD")>=15,1,0) -> 7 | I72: PTPN IV - Regional 5 | J72: PKWTT | K72: 14003480
A73: 34 | B73: PTPN IV - Regional 5 | C73: Darmansyah Siregar | D73: SEVP Operation II R5 | E73: 45880 | F73: 46022 | G73: =DATEDIF(E73,F73,"d")+1 -> 143 | H73: =DATEDIF(E73,F73,"M") + IF(DATEDIF(E73,F73,"MD")>=15,1,0) -> 5 | I73: PTPN IV - Regional 5 | J73: PKWTT | K73: 14003480
A74: 35 | B74: PTPN IV - Regional 5 | C74: Ihsan | D74: SEVP Operation II R5 | E74: 45658 | F74: 45879 | G74: =DATEDIF(E74,F74,"d")+1 -> 222 | H74: =DATEDIF(E74,F74,"M") + IF(DATEDIF(E74,F74,"MD")>=15,1,0) -> 7 | I74: PTPN IV - Regional 5 | J74: PKWTT | K74: 13007996
A75: 36 | B75: PTPN IV - Regional 5 | C75: Ihsan | D75: SEVP Operation I R5 | E75: 45880 | F75: 46022 | G75: =DATEDIF(E75,F75,"d")+1 -> 143 | H75: =DATEDIF(E75,F75,"M") + IF(DATEDIF(E75,F75,"MD")>=15,1,0) -> 5 | I75: PTPN IV - Regional 5 | J75: PKWTT | K75: 13007996
A76: 37 | B76: PTPN IV - Regional 5 | C76: Donny Amril | D76: SEVP Business Support R5 | E76: 45658 | F76: 46022 | G76: =DATEDIF(E76,F76,"d")+1 -> 365 | H76: =DATEDIF(E76,F76,"M") + IF(DATEDIF(E76,F76,"MD")>=15,1,0) -> 12 | I76: PTPN IV - Regional 5 | J76: PKWTT | K76: 3000190
A77: 38 | B77: PTPN IV - Regional 6 | C77: Syahriadi Siregar | D77: Region Head R6 Merangkap Business Support | E77: 45658 | F77: 45916 | G77: =DATEDIF(E77,F77,"d")+1 -> 259 | H77: =DATEDIF(E77,F77,"M") + IF(DATEDIF(E77,F77,"MD")>=15,1,0) -> 9 | I77: PTPN IV - Regional 6 | J77: PKWTT
A78: 39 | B78: PTPN IV - Regional 6 | C78: Ir Tengku Zein Ichwan | D78: SEVP Operation R6 | E78: 45778 | F78: 46022 | G78: =DATEDIF(E78,F78,"d")+1 -> 245 | H78: =DATEDIF(E78,F78,"M") + IF(DATEDIF(E78,F78,"MD")>=15,1,0) -> 8 | I78: PTPN IV - Regional 6 | J78: PKWTT | K78: 1001865
A79: 40 | B79: PTPN IV - Regional 6 | C79: Tengku Rinel | D79: SEVP Business Support R6 | E79: 45692 | F79: 45809 | G79: =DATEDIF(E79,F79,"d")+1 -> 118 | H79: =DATEDIF(E79,F79,"M") + IF(DATEDIF(E79,F79,"MD")>=15,1,0) -> 4 | I79: PTPN IV - Regional 6 | J79: PKWT
A80: 41 | B80: PTPN IV - Regional 6 | C80: Ifri Handi Lubis | D80: SEVP Business Support | E80: 45809 | F80: 46022 | G80: =DATEDIF(E80,F80,"d")+1 -> 214 | H80: =DATEDIF(E80,F80,"M") + IF(DATEDIF(E80,F80,"MD")>=15,1,0) -> 7 | I80: PTPN IV - Regional 6 | J80: PKWTT | K80: 5000222
A81: 42 | B81: PTPN IV - Regional 6 | C81: Yudhi Cahyadi | D81: Region Head R6 | E81: 45917 | F81: 46022 | G81: =DATEDIF(E81,F81,"d")+1 -> 106 | H81: =DATEDIF(E81,F81,"M") + IF(DATEDIF(E81,F81,"MD")>=15,1,0) -> 3 | I81: PTPN IV - Regional 6 | J81: PKWTT | K81: 3000783
A82: 43 | B82: PTPN IV - Regional 7 | C82: Denny Ramadhan Nasution | D82: Regional Head R7 | E82: 45658 | F82: 46022 | G82: =DATEDIF(E82,F82,"d")+1 -> 365 | H82: =DATEDIF(E82,F82,"M") + IF(DATEDIF(E82,F82,"MD")>=15,1,0) -> 12 | I82: PTPN IV - Regional 7 | J82: PKWT
A83: 44 | B83: PTPN IV - Regional 7 | C83: Oshutri Anwar | D83: SEVP Business Support R7 | E83: 45658 | F83: 46022 | G83: =DATEDIF(E83,F83,"d")+1 -> 365 | H83: =DATEDIF(E83,F83,"M") + IF(DATEDIF(E83,F83,"MD")>=15,1,0) -> 12 | I83: PTPN IV - Regional 7 | J83: PKWTT | K83: 6610436
A84: 45 | B84: PTPN IV - Regional 7 | C84: Rina Tanjung | D84: SEVP Operation R7 | E84: 45658 | F84: 46022 | G84: =DATEDIF(E84,F84,"d")+1 -> 365 | H84: =DATEDIF(E84,F84,"M") + IF(DATEDIF(E84,F84,"MD")>=15,1,0) -> 12 | I84: PTPN IV - Regional 7 | J84: PKWTT | K84: 3000170
A85: 46 | B85: PTPN IV - Palm Co HO | C85: Rediman Silalahi | D85: SEVP Operation HO | E85: 45962 | F85: 46022 | G85: =DATEDIF(E85,F85,"d")+1 -> 61 | H85: =DATEDIF(E85,F85,"M") + IF(DATEDIF(E85,F85,"MD")>=15,1,0) -> 2 | I85: PTPN IV - Palm Co HO | J85: PKWT
A89: Sugar Co
A90: 1 | B90: PT SGN | C90: Mahmudi | D90: Direktur Utama | E90: 45658 | F90: 46022 | G90: =DATEDIF(E90,F90,"d")+1 -> 365 | H90: =DATEDIF(E90,F90,"M") + IF(DATEDIF(E90,F90,"MD")>=15,1,0) -> 12 | I90: PT SGN | J90: PKWT
A91: =A90+1 -> 2 | B91: PT SGN | C91: Dodik Ristiawan | D91: Direktur Operasional | E91: 45658 | F91: 46022 | G91: =DATEDIF(E91,F91,"d")+1 -> 365 | H91: =DATEDIF(E91,F91,"M") + IF(DATEDIF(E91,F91,"MD")>=15,1,0) -> 12 | I91: PT SGN | J91: PKWT | K91: 9016519
A92: =A91+1 -> 3 | B92: PT SGN | C92: Hariyanto | D92: Direktur Keuangan | E92: 45658 | F92: 46022 | G92: =DATEDIF(E92,F92,"d")+1 -> 365 | H92: =DATEDIF(E92,F92,"M") + IF(DATEDIF(E92,F92,"MD")>=15,1,0) -> 12 | I92: PT SGN | J92: PKWT
A93: =A92+1 -> 4 | B93: PT SGN | C93: Affan Safiq | D93: Direktur SDM dan TI | E93: 45658 | F93: 46022 | G93: =DATEDIF(E93,F93,"d")+1 -> 365 | H93: =DATEDIF(E93,F93,"M") + IF(DATEDIF(E93,F93,"MD")>=15,1,0) -> 12 | I93: PT SGN | J93: PKWT | K93: 9016341
A94: =A93+1 -> 5 | B94: PT SGN | C94: Aris Toharisman | D94: Direktur Hubungan Kelembagaan dan Manajemen Risiko | E94: 45658 | F94: 45735 | G94: =DATEDIF(E94,F94,"d")+1 -> 78 | H94: =DATEDIF(E94,F94,"M") + IF(DATEDIF(E94,F94,"MD")>=15,1,0) -> 3 | I94: PT SGN | J94: PKWT
A95: =A94+1 -> 6 | B95: PT SGN | C95: M Fakhrur Rozi | D95: Direktur Manajemen Risiko | E95: 45840 | F95: 46022 | G95: =DATEDIF(E95,F95,"d")+1 -> 183 | H95: =DATEDIF(E95,F95,"M") + IF(DATEDIF(E95,F95,"MD")>=15,1,0) -> 6 | I95: PT SGN | J95: PKWT
A96: 7 | B96: PT SGN | C96: Dimas Eko Prasetyo | D96: SEVP Operation I / SEVP Strategic Business | E96: 45658 | F96: 45840 | G96: =DATEDIF(E96,F96,"d")+1 -> 183 | H96: =DATEDIF(E96,F96,"M") + IF(DATEDIF(E96,F96,"MD")>=15,1,0) -> 6 | I96: PT SGN | J96: PKWTT | K96: 18011207
A97: 8 | B97: PT SGN | C97: Dimas Eko Prasetyo | D97: Direktur Strategi & Sustainability | E97: 45840 | F97: 46022 | G97: =DATEDIF(E97,F97,"d")+1 -> 183 | H97: =DATEDIF(E97,F97,"M") + IF(DATEDIF(E97,F97,"MD")>=15,1,0) -> 6 | I97: PT SGN | J97: PKWTT | K97: 18011207
A98: =A97+1 -> 9 | B98: PT SGN | C98: Imam Cipto Suyitno | D98: SEVP Operation II / SEVP Koordinator KSO | E98: 45658 | F98: 45991 | G98: =DATEDIF(E98,F98,"d")+1 -> 334 | H98: =DATEDIF(E98,F98,"M") + IF(DATEDIF(E98,F98,"MD")>=15,1,0) -> 11 | I98: PT SGN | J98: PKWTT | K98: 11005237
A99: =A98+1 -> 10 | B99: PT SGN | C99: Putu Sukarmen | D99: SEVP Pengembangan | E99: 45869 | F99: 46022 | G99: =DATEDIF(E99,F99,"d")+1 -> 154 | H99: =DATEDIF(E99,F99,"M") + IF(DATEDIF(E99,F99,"MD")>=15,1,0) -> 5 | I99: PT SGN | J99: PKWTT
A100: =A99+1 -> 11 | B100: PT SGN | C100: R Tulus Panduwidjaja | D100: SEVP Business Support | E100: 45809 | F100: 46022 | G100: =DATEDIF(E100,F100,"d")+1 -> 214 | H100: =DATEDIF(E100,F100,"M") + IF(DATEDIF(E100,F100,"MD")>=15,1,0) -> 7 | I100: PT SGN | J100: PKWT
A101: =A100+1 -> 12 | B101: PT SGN | C101: Febri Ari Marpaung | D101: SEVP Operasional KSO | E101: 45658 | F101: 45992 | G101: =DATEDIF(E101,F101,"d")+1 -> 335 | H101: =DATEDIF(E101,F101,"M") + IF(DATEDIF(E101,F101,"MD")>=15,1,0) -> 11 | I101: PT SGN | J101: PKWTT | K101: 10000001
A102: =A101+1 -> 13 | B102: PT SGN | C102: Febri Ari Marpaung | D102: SEVP Koordinator KSO | E102: 45992 | F102: 46022 | G102: =DATEDIF(E102,F102,"d")+1 -> 31 | H102: =DATEDIF(E102,F102,"M") + IF(DATEDIF(E102,F102,"MD")>=15,1,0) -> 1 | I102: PT SGN | J102: PKWTT | K102: 10000001
A106: Anper Non PTPN
A107: 1 | B107: PT RPN | C107: Iman Yani Harahap | D107: Direktur | E107: 45658 | F107: 46022 | G107: =DATEDIF(E107,F107,"d")+1 -> 365 | H107: =DATEDIF(E107,F107,"M") + IF(DATEDIF(E107,F107,"MD")>=15,1,0) -> 12 | I107: PT RPN | J107: PKWT
A108: 3 | B108: PT RPN | C108: Tjahjono Herawan | D108: SEVP Operation I | E108: 45658 | F108: 46022 | G108: =DATEDIF(E108,F108,"d")+1 -> 365 | H108: =DATEDIF(E108,F108,"M") + IF(DATEDIF(E108,F108,"MD")>=15,1,0) -> 12 | I108: PT RPN | J108: PKWTT
A109: 3 | B109: PT RPN | C109: Misnawi | D109: SEVP Operation II | E109: 45658 | F109: 46022 | G109: =DATEDIF(E109,F109,"d")+1 -> 365 | H109: =DATEDIF(E109,F109,"M") + IF(DATEDIF(E109,F109,"MD")>=15,1,0) -> 12 | I109: PT RPN | J109: PKWTT
A110: 4 | B110: PT RPN | C110: Edy Suprianto | D110: SEVP Business Support | E110: 45658 | F110: 46022 | G110: =DATEDIF(E110,F110,"d")+1 -> 365 | H110: =DATEDIF(E110,F110,"M") + IF(DATEDIF(E110,F110,"MD")>=15,1,0) -> 12 | I110: PT RPN | J110: PKWTT | K110: 21000003
A111: 5 | B111: PT RPN | C111: Muhammad Edwin Syahputra | D111: SEVP Riset, Inovasi, dan Sustainability | E111: 45658 | F111: 46022 | G111: =DATEDIF(E111,F111,"d")+1 -> 365 | H111: =DATEDIF(E111,F111,"M") + IF(DATEDIF(E111,F111,"MD")>=15,1,0) -> 12 | I111: PT RPN | J111: PKWTT | K111: 21000004
...

Sheet Kertas Kerja
B4: Penilaian Direktur, Region Head & SEVP 2025
B5: No | C5: Entitas Penugasan | D5: Nama | E5: Jabatan | F5: Nilai 2025 | G5: Keterangan | H5: Awal Menjabat | I5: Akhir Menjabat | J5: Hari | K5: Bulan | L5: SKOR SEMENTARA | M5: Jabatan Rangkap?
B6: 1 | C6: PTPN I - Supporting Co HO | D6: Teddy Yunirman Danas | E6: Direktur Utama | G6: Skor Direktur menyusul | H6: 45658 | I6: 46022 | J6: =I6-H6+1 -> 365 | K6: =ROUND(J6/365*12,0) -> 12 | L6: ='PTPN I DIR'!H18*K6/12 -> 81.73 | M6: {=IF(SUMPRODUCT(($D$6:$D$121=D6)*($H$6:$H$121<I6)*($I$6:$I$121>H6))>1,"Rangkap","")}
B7: 2 | C7: PTPN I - Supporting Co HO | D7: Fauzi Omar | E7: Direktur Operasional | G7: Skor Direktur menyusul | H7: 45658 | I7: 46022 | J7: 365 | K7: 12 | L7: ='PTPN I DIR'!H100*K7/12 -> 83.56 | M7: {=IF(SUMPRODUCT(($D$6:$D$121=D7)*($H$6:$H$121<I7)*($I$6:$I$121>H7))>1,"Rangkap","")}
B8: 3 | C8: PTPN I - Supporting Co HO | D8: Landi Rizaldi Mangaweang | E8: Direktur Pemasaran dan Aset | G8: Skor Direktur menyusul | H8: 45658 | I8: 46022 | J8: 365 | K8: 12 | L8: ='PTPN I DIR'!H114*K8/12 -> 81.41 | M8: {=IF(SUMPRODUCT(($D$6:$D$121=D8)*($H$6:$H$121<I8)*($I$6:$I$121>H8))>1,"Rangkap","")}
B9: 4 | C9: PTPN I - Supporting Co HO | D9: Doni P Gandamihardja | E9: Direktur Keuangan dan Manajemen Risiko | G9: Skor Direktur menyusul | H9: 45658 | I9: 46022 | J9: 365 | K9: 12 | L9: ='PTPN I DIR'!H78*K9/12 -> 84.38 | M9: {=IF(SUMPRODUCT(($D$6:$D$121=D9)*($H$6:$H$121<I9)*($I$6:$I$121>H9))>1,"Rangkap","")}
B10: 5 | C10: PTPN I - Supporting Co HO | D10: Siwi Peni | E10: Direktur SDM dan TI | G10: Skor Direktur menyusul | H10: 45658 | I10: 46022 | J10: 365 | K10: 12 | L10: ='PTPN I DIR'!H38*K10/12 -> 84.55 | M10: {=IF(SUMPRODUCT(($D$6:$D$121=D10)*($H$6:$H$121<I10)*($I$6:$I$121>H10))>1,"Rangkap","")}
B11: 6 | C11: PTPN I - Supporting Co HO | D11: Tio Handoko | E11: Direktur Hubungan Kelembagaan | G11: Skor Direktur menyusul | H11: 45658 | I11: 46022 | J11: 365 | K11: 12 | L11: ='PTPN I DIR'!H59*K11/12 -> 85.58 | M11: {=IF(SUMPRODUCT(($D$6:$D$121=D11)*($H$6:$H$121<I11)*($I$6:$I$121>H11))>1,"Rangkap","")}
B12: 7 | C12: PTPN I - Regional 1 | D12: Didik Prasetyo | E12: Region Head R1 | H12: 45658 | I12: 45972 | J12: 304 | K12: 10 | L12: =N1R1!M60*K12/12 -> 79.513327 | M12: {=IF(SUMPRODUCT(($D$6:$D$121=D12)*($H$6:$H$121<I12)*($I$6:$I$121>H12))>1,"Rangkap","")}
A13: Oke | B13: 8 | C13: PTPN I - Regional 1 | D13: Wispramono Budiman | E13: SEVP Business Support R1 | H13: 45658 | I13: 46022 | J13: 365 | K13: 12 | L13: =N1R1!Q60*K13/12 -> 96.051929 | M13: {=IF(SUMPRODUCT(($D$6:$D$121=D13)*($H$6:$H$121<I13)*($I$6:$I$121>H13))>1,"Rangkap","")} -> Rangkap
B14: 9 | C14: PTPN I - Regional 1 | D14: Wispramono Budiman | E14: Plt Region Head R1 | H14: 45962 | I14: 46022 | J14: 61 | K14: 2 | L14: 15.9 | M14: {=IF(SUMPRODUCT(($D$6:$D$121=D14)*($H$6:$H$121<I14)*($I$6:$I$121>H14))>1,"Rangkap","")} -> Rangkap
B15: 10 | C15: PTPN I - Regional 1 | D15: Ganda Wiatmaja | E15: SEVP Aset R1 | H15: 45662 | I15: 46022 | J15: 361 | K15: 12 | L15: =N1R1!Q60*K15/12 -> 96.051929 | M15: {=IF(SUMPRODUCT(($D$6:$D$121=D15)*($H$6:$H$121<I15)*($I$6:$I$121>H15))>1,"Rangkap","")}
B16: 11 | C16: PTPN I - Regional 2 | D16: Desmanto | E16: Region Head R2 | H16: 45658 | I16: 46022 | J16: 365 | K16: 12 | L16: =N1R2!M87*K16/12 -> 81.971293 | M16: {=IF(SUMPRODUCT(($D$6:$D$121=D16)*($H$6:$H$121<I16)*($I$6:$I$121>H16))>1,"Rangkap","")}
B17: 12 | C17: PTPN I - Regional 2 | D17: Iyan Heryanto | E17: SEVP Operation R2 | H17: 45658 | I17: 46022 | J17: 365 | K17: 12 | L17: =N1R2!O87*K17/12 -> 80.074079 | M17: {=IF(SUMPRODUCT(($D$6:$D$121=D17)*($H$6:$H$121<I17)*($I$6:$I$121>H17))>1,"Rangkap","")}
B18: 13 | C18: PTPN I - Regional 2 | D18: Okta Kurniawan | E18: SEVP Business Support R2 | H18: 45658 | I18: 46022 | J18: 365 | K18: 12 | L18: =N1R2!Q87*K18/12 -> 85.58976 | M18: {=IF(SUMPRODUCT(($D$6:$D$121=D18)*($H$6:$H$121<I18)*($I$6:$I$121>H18))>1,"Rangkap","")}
B19: 14 | C19: PTPN I - Regional 2 | D19: Pulung Rinandoro | E19: SEVP Aset R2 | H19: 45658 | I19: 46022 | J19: 365 | K19: 12 | L19: =N1R2!Q87*K19/12 -> 85.58976 | M19: {=IF(SUMPRODUCT(($D$6:$D$121=D19)*($H$6:$H$121<I19)*($I$6:$I$121>H19))>1,"Rangkap","")}
B20: 15 | C20: PTPN I - Regional 3 | D20: Tri Septiono | E20: Region Head R3 | H20: 45658 | I20: 46022 | J20: 365 | K20: 12 | L20: =N1R3!M90*K20/12 -> 93.716363 | M20: {=IF(SUMPRODUCT(($D$6:$D$121=D20)*($H$6:$H$121<I20)*($I$6:$I$121>H20))>1,"Rangkap","")}
B21: 16 | C21: PTPN I - Regional 3 | D21: Budiyono | E21: SEVP Operation R3 | H21: 45658 | I21: 46022 | J21: 365 | K21: 12 | L21: =N1R3!O90*K21/12 -> 91.091047 | M21: {=IF(SUMPRODUCT(($D$6:$D$121=D21)*($H$6:$H$121<I21)*($I$6:$I$121>H21))>1,"Rangkap","")}
B22: 17 | C22: PTPN I - Regional 4 | D22: Subagiyo | E22: Region Head R4 | H22: 45658 | I22: 45808 | J22: 151 | K22: 5 | L22: =N1R4!M67*K22/12 -> 32.506174 | M22: {=IF(SUMPRODUCT(($D$6:$D$121=D22)*($H$6:$H$121<I22)*($I$6:$I$121>H22))>1,"Rangkap","")}
A23: turun | B23: 18 | C23: PTPN I - Regional 4 | D23: Subagiyo | E23: SEVP Business Support R5 | H23: 45809 | I23: 46022 | J23: 214 | K23: 7 | L23: 44.5 | M23: {=IF(SUMPRODUCT(($D$6:$D$121=D23)*($H$6:$H$121<I23)*($I$6:$I$121>H23))>1,"Rangkap","")} -> Rangkap
B24: 19 | C24: PTPN I - Regional 4 | D24: Subagiyo | E24: Plt. Region Head R5 | H24: 45992 | I24: 46022 | J24: 31 | K24: 1 | L24: 6.5 | M24: {=IF(SUMPRODUCT(($D$6:$D$121=D24)*($H$6:$H$121<I24)*($I$6:$I$121>H24))>1,"Rangkap","")} -> Rangkap
B25: 20 | C25: PTPN I - Regional 5 | D25: Winarto | E25: Region Head R5 | H25: 45658 | I25: 45991 | J25: 334 | K25: 11 | L25: =N1R5!M91*K25/12 -> 86.355088 | M25: {=IF(SUMPRODUCT(($D$6:$D$121=D25)*($H$6:$H$121<I25)*($I$6:$I$121>H25))>1,"Rangkap","")}
B26: 21 | C26: PTPN I - Regional 5 | D26: Asep Sontani | E26: SEVP Operation R5 | H26: 45658 | I26: 46022 | J26: 365 | K26: 12 | L26: =N1R5!O91*K26/12 -> 91.818108 | M26: {=IF(SUMPRODUCT(($D$6:$D$121=D26)*($H$6:$H$121<I26)*($I$6:$I$121>H26))>1,"Rangkap","")}
B27: 22 | C27: PTPN I - Regional 5 | D27: Benny Sandjaya | E27: SEVP Business Support R5 | H27: 45658 | I27: 45808 | J27: 151 | K27: 5 | L27: =N1R5!Q91*K27/12 -> 40.013774 | M27: {=IF(SUMPRODUCT(($D$6:$D$121=D27)*($H$6:$H$121<I27)*($I$6:$I$121>H27))>1,"Rangkap","")}
B28: 23 | C28: PTPN I - Regional 7 | D28: Tuhu Bangun | E28: Regional Head R7 | H28: 45658 | I28: 46022 | J28: 365 | K28: 12 | L28: =N1R7!M84*K28/12 -> 82.927896 | M28: {=IF(SUMPRODUCT(($D$6:$D$121=D28)*($H$6:$H$121<I28)*($I$6:$I$121>H28))>1,"Rangkap","")}
B29: 24 | C29: PTPN I - Regional 7 | D29: Bambang Agustian | E29: SEVP Business Support R7 | H29: 45658 | I29: 45808 | J29: 151 | K29: 5 | L29: =N1R7!Q84*K29/12 -> 34.976627 | M29: {=IF(SUMPRODUCT(($D$6:$D$121=D29)*($H$6:$H$121<I29)*($I$6:$I$121>H29))>1,"Rangkap","")}
B30: 25 | C30: PTPN I - Regional 7 | D30: Wiyoso | E30: SEVP Operation R7 | H30: 45658 | I30: 46022 | J30: 365 | K30: 12 | L30: =N1R7!O84*K30/12 -> 82.078565 | M30: {=IF(SUMPRODUCT(($D$6:$D$121=D30)*($H$6:$H$121<I30)*($I$6:$I$121>H30))>1,"Rangkap","")}
A31: KPBN | B31: 26 | C31: PTPN I - Regional 7 | D31: Iskandar Dewantara | E31: SEVP Busines Support R7 | H31: 45809 | I31: 46022 | J31: 214 | K31: 7 | L31: =N1R7!Q84*K31/12 -> 48.967278 | M31: {=IF(SUMPRODUCT(($D$6:$D$121=D31)*($H$6:$H$121<I31)*($I$6:$I$121>H31))>1,"Rangkap","")} -> Rangkap
B32: 27 | C32: PTPN I - Regional 8 | D32: R Tulus Panduwidjaja | E32: Regional Head R8 | H32: 45658 | I32: 45808 | J32: 151 | K32: 5 | L32: =N1R8!M67*K32/12 -> 33.635416 | M32: {=IF(SUMPRODUCT(($D$6:$D$121=D32)*($H$6:$H$121<I32)*($I$6:$I$121>H32))>1,"Rangkap","")}
B33: 28 | C33: PTPN I - Regional 8 | D33: Maalun Lamau | E33: SEVP Business Support R8 | H33: 45658 | I33: 46022 | J33: 365 | K33: 12 | L33: =N1R8!Q67*K33/12 -> 80.258495 | M33: {=IF(SUMPRODUCT(($D$6:$D$121=D33)*($H$6:$H$121<I33)*($I$6:$I$121>H33))>1,"Rangkap","")} -> Rangkap
B34: 29 | D34: Maalun Lamau | E34: Plt. Region Head R8 | H34: 45658 | I34: 46022 | J34: =I34-H34+1 -> 365 | K34: =ROUND(J34/365*12,0) -> 12 | L34: =N1R8!M67*K34/12 -> 80.724997 | M34: {=IF(SUMPRODUCT(($D$6:$D$121=D34)*($H$6:$H$121<I34)*($I$6:$I$121>H34))>1,"Rangkap","")} -> Rangkap
B35: 30 | C35: PTPN I - Regional 8 | D35: Misran | E35: SEVP Operation R8 | H35: 45809 | I35: 46022 | J35: 214 | K35: 7 | L35: =N1R8!O67*K35/12 -> 47.361708 | M35: {=IF(SUMPRODUCT(($D$6:$D$121=D35)*($H$6:$H$121<I35)*($I$6:$I$121>H35))>1,"Rangkap","")}
B36: 31 | C36: PTPN IV - Palm Co HO | D36: Jatmiko Krisna Santosa | E36: Direktur Utama | G36: Skor Direktur menyusul | H36: 45658 | I36: 46022 | J36: 365 | K36: 12 | L36: ='PTPN IV DIR'!K26*K36/12 -> 89.8 | M36: {=IF(SUMPRODUCT(($D$6:$D$121=D36)*($H$6:$H$121<I36)*($I$6:$I$121>H36))>1,"Rangkap","")}
B37: 32 | C37: PTPN IV - Palm Co HO | D37: Rizal H Damanik | E37: Direktur Operasional | G37: Skor Direktur menyusul | H37: 45658 | I37: 45823 | J37: 166 | K37: 5 | L37: ='PTPN IV DIR'!K53*K37/12 -> 35.941667 | M37: {=IF(SUMPRODUCT(($D$6:$D$121=D37)*($H$6:$H$121<I37)*($I$6:$I$121>H37))>1,"Rangkap","")}
B38: 33 | C38: PTPN IV - Palm Co HO | D38: Ryanto Wisnuardhy | E38: Direktur Pemasaran dan Komersial | G38: Skor Direktur menyusul | H38: 45658 | I38: 45823 | J38: 166 | K38: 5 | L38: ='PTPN IV DIR'!K72*K38/12 -> 40.233333 | M38: {=IF(SUMPRODUCT(($D$6:$D$121=D38)*($H$6:$H$121<I38)*($I$6:$I$121>H38))>1,"Rangkap","")}
B39: 34 | C39: PTPN IV - Palm Co HO | D39: Hilda Savitri | E39: Direktur Keuangan dan Manajemen Risiko | G39: Skor Direktur menyusul | H39: 45658 | I39: 46022 | J39: 365 | K39: 12 | L39: ='PTPN IV DIR'!K114*K39/12 -> 93.89 | M39: {=IF(SUMPRODUCT(($D$6:$D$121=D39)*($H$6:$H$121<I39)*($I$6:$I$121>H39))>1,"Rangkap","")}
B40: 35 | C40: PTPN IV - Palm Co HO | D40: Suhendri | E40: Direktur SDM dan TI | G40: Skor Direktur menyusul | H40: 45658 | I40: 46022 | J40: 365 | K40: 12 | L40: ='PTPN IV DIR'!K136*K40/12 -> 87.43 | M40: {=IF(SUMPRODUCT(($D$6:$D$121=D40)*($H$6:$H$121<I40)*($I$6:$I$121>H40))>1,"Rangkap","")}
B41: 36 | C41: PTPN IV - Palm Co HO | D41: Irwan Perangin Angin | E41: Direktur Hubungan Kelembagaan | G41: Skor Direktur menyusul | H41: 45658 | I41: 45972 | J41: 315 | K41: 10 | L41: ='PTPN IV DIR'!K158*K41/12 -> 75.7 | M41: {=IF(SUMPRODUCT(($D$6:$D$121=D41)*($H$6:$H$121<I41)*($I$6:$I$121>H41))>1,"Rangkap","")}
B42: 37 | C42: PTPN IV - Palm Co HO | D42: Ugun Untaryo | E42: Direktur Strategic dan Sustainability | G42: Skor Direktur menyusul | H42: 45658 | I42: 46022 | J42: 365 | K42: 12 | L42: ='PTPN IV DIR'!K91*K42/12 -> 85.4 | M42: {=IF(SUMPRODUCT(($D$6:$D$121=D42)*($H$6:$H$121<I42)*($I$6:$I$121>H42))>1,"Rangkap","")}
B43: 38 | C43: PTPN IV - Palm Co HO | D43: Rediman Silalahi | E43: SEVP Operation HO | G43: SEVP level HO - sumber skor belum ada | H43: 45962 | I43: 46022 | J43: 61 | K43: 2 | M43: {=IF(SUMPRODUCT(($D$6:$D$121=D43)*($H$6:$H$121<I43)*($I$6:$I$121>H43))>1,"Rangkap","")}
B44: 39 | C44: PTPN IV - Regional 1 | D44: Rurianto | E44: Regional Head R1 | H44: 45658 | I44: 46022 | J44: 365 | K44: 12 | L44: =N4R1!R94*K44/12 -> 88.593044 | M44: {=IF(SUMPRODUCT(($D$6:$D$121=D44)*($H$6:$H$121<I44)*($I$6:$I$121>H44))>1,"Rangkap","")}
B45: 40 | C45: PTPN IV - Regional 1 | D45: Budi Susilo | E45: SEVP Operation I R1 | H45: 45658 | I45: 46022 | J45: 365 | K45: 12 | L45: =N4R1!T94*K45/12 -> 89.727552 | M45: {=IF(SUMPRODUCT(($D$6:$D$121=D45)*($H$6:$H$121<I45)*($I$6:$I$121>H45))>1,"Rangkap","")} -> Rangkap
B46: 41 | C46: PTPN IV - Regional 1 | D46: Joni Raja Siregar | E46: SEVP Operation II R1 | H46: 45658 | I46: 46022 | J46: 365 | K46: 12 | L46: =N4R1!T94*K46/12 -> 89.727552 | M46: {=IF(SUMPRODUCT(($D$6:$D$121=D46)*($H$6:$H$121<I46)*($I$6:$I$121>H46))>1,"Rangkap","")}
B47: 42 | C47: PTPN IV - Regional 1 | D47: Tengku Rinel | E47: SEVP Business Support R1 | H47: 45658 | I47: 45691 | J47: 34 | K47: 1 | L47: =N4R1!V94*K47/12 -> 7.2911143 | M47: {=IF(SUMPRODUCT(($D$6:$D$121=D47)*($H$6:$H$121<I47)*($I$6:$I$121>H47))>1,"Rangkap","")}
B48: 43 | C48: PTPN IV - Regional 1 | D48: Ahmad Diponegoro | E48: SEVP Business Support R1 | H48: 45809 | I48: 46022 | J48: 214 | K48: 7 | L48: =N4R1!V94*K48/12 -> 51.0378 | M48: {=IF(SUMPRODUCT(($D$6:$D$121=D48)*($H$6:$H$121<I48)*($I$6:$I$121>H48))>1,"Rangkap","")}
B49: 44 | C49: PTPN IV - Regional 1 | D49: Budi Susanto | E49: SEVP Business Support R1 | H49: 45658 | I49: 45727 | J49: 70 | K49: 2 | L49: =N4R1!V94*K49/12 -> 14.582229 | M49: {=IF(SUMPRODUCT(($D$6:$D$121=D49)*($H$6:$H$121<I49)*($I$6:$I$121>H49))>1,"Rangkap","")}
B50: 45 | C50: PTPN IV - Regional 2 | D50: Sudarma Bhakti Lessan | E50: Regional Head R2 | H50: 45658 | I50: 45728 | J50: 71 | K50: 2 | L50: =N4R2!R100*K50/12 -> 14.588147 | M50: {=IF(SUMPRODUCT(($D$6:$D$121=D50)*($H$6:$H$121<I50)*($I$6:$I$121>H50))>1,"Rangkap","")}
A51: salah | B51: 46 | C51: PTPN IV - Regional 2 | D51: Budi Susilo | E51: SEVP Operation I R2 | H51: 45658 | I51: 45992 | J51: 335 | K51: 11 | L51: =N4R2!T100*K51/12 -> 81.388101 | M51: {=IF(SUMPRODUCT(($D$6:$D$121=D51)*($H$6:$H$121<I51)*($I$6:$I$121>H51))>1,"Rangkap","")} -> Rangkap
B52: 47 | C52: PTPN IV - Regional 2 | D52: Dedy Gurning | E52: SEVP Operation II R2 | H52: 45658 | I52: 46022 | J52: 365 | K52: 12 | L52: =N4R2!T100*K52/12 -> 88.78702 | M52: {=IF(SUMPRODUCT(($D$6:$D$121=D52)*($H$6:$H$121<I52)*($I$6:$I$121>H52))>1,"Rangkap","")}
B53: 48 | C53: PTPN IV - Regional 2 | D53: Budi Susanto | E53: Regional Head R2 | H53: 45727 | I53: 46022 | J53: 296 | K53: 10 | L53: =N4R2!R100*K53/12 -> 72.940733 | M53: {=IF(SUMPRODUCT(($D$6:$D$121=D53)*($H$6:$H$121<I53)*($I$6:$I$121>H53))>1,"Rangkap","")}
B54: 50 | C54: PTPN IV - Regional 2 | D54: Arief Subhan Siregar | E54: SEVP Operation I R2 | H54: 45658 | I54: 45808 | J54: 151 | K54: 5 | L54: =N4R2!T100*K54/12 -> 36.994592 | M54: {=IF(SUMPRODUCT(($D$6:$D$121=D54)*($H$6:$H$121<I54)*($I$6:$I$121>H54))>1,"Rangkap","")}
B55: 51 | C55: PTPN IV - Regional 2 | D55: Arief Subhan Siregar | E55: SEVP Business Support R2 | H55: 45809 | I55: 46022 | J55: 214 | K55: 7 | L55: =N4R2!V100*K55/12 -> 49.854017 | M55: {=IF(SUMPRODUCT(($D$6:$D$121=D55)*($H$6:$H$121<I55)*($I$6:$I$121>H55))>1,"Rangkap","")}
B56: 52 | C56: PTPN IV - Regional 2 | D56: Mulianto | E56: SEVP Operation I | H56: 45809 | I56: 46022 | J56: 214 | K56: 7 | L56: =N4R2!T100*K56/12 -> 51.792428 | M56: {=IF(SUMPRODUCT(($D$6:$D$121=D56)*($H$6:$H$121<I56)*($I$6:$I$121>H56))>1,"Rangkap","")}
B57: 53 | C57: PTPN IV - Regional 3 | D57: Yudhi Cahyadi | E57: SEVP Operation R3 | H57: 45658 | I57: 45916 | J57: 259 | K57: 9 | L57: =N4R3!T108*K57/12 -> 67.679604 | M57: {=IF(SUMPRODUCT(($D$6:$D$121=D57)*($H$6:$H$121<I57)*($I$6:$I$121>H57))>1,"Rangkap","")}
B58: 55 | C58: PTPN IV - Regional 3 | D58: Bambang Budi Santoso | E58: SEVP Business Support | H58: 45692 | I58: 46022 | J58: 331 | K58: 11 | L58: =N4R3!V108*K58/12 -> 81.48587 | M58: {=IF(SUMPRODUCT(($D$6:$D$121=D58)*($H$6:$H$121<I58)*($I$6:$I$121>H58))>1,"Rangkap","")}
B59: 56 | C59: PTPN IV - Regional 3 | D59: Sori Pardomuan Ritonga | E59: SEVP Operation | H59: 45922 | I59: 46022 | J59: 101 | K59: 3 | L59: =N4R3!T108*K59/12 -> 22.559868 | M59: {=IF(SUMPRODUCT(($D$6:$D$121=D59)*($H$6:$H$121<I59)*($I$6:$I$121>H59))>1,"Rangkap","")}
B60: 57 | C60: PTPN IV - Regional 4 | D60: Khayamuddin Panjaitan | E60: Regional Head R4 | H60: 45658 | I60: 46022 | J60: 365 | K60: 12 | L60: =N4R4!R101*K60/12 -> 79.96698 | M60: {=IF(SUMPRODUCT(($D$6:$D$121=D60)*($H$6:$H$121<I60)*($I$6:$I$121>H60))>1,"Rangkap","")}
B61: 58 | C61: PTPN IV - Regional 4 | D61: Ospin Sembiring | E61: Regional Head R4 | H61: 45658 | I61: 45728 | J61: 71 | K61: 2 | L61: =N4R4!R101*K61/12 -> 13.32783 | M61: {=IF(SUMPRODUCT(($D$6:$D$121=D61)*($H$6:$H$121<I61)*($I$6:$I$121>H61))>1,"Rangkap","")}
B62: 59 | C62: PTPN IV - Regional 4 | D62: Ifri Handi Lubis | E62: SEVP Business Support R4 | H62: 45658 | I62: 45809 | J62: 152 | K62: 5 | L62: =N4R4!V101*K62/12 -> 32.100723 | M62: {=IF(SUMPRODUCT(($D$6:$D$121=D62)*($H$6:$H$121<I62)*($I$6:$I$121>H62))>1,"Rangkap","")}
B63: 60 | C63: PTPN IV - Regional 4 | D63: Achmedi Akbar | E63: SEVP Business Support R4 | H63: 45809 | I63: 46022 | J63: 214 | K63: 7 | L63: =N4R4!V101*K63/12 -> 44.941012 | M63: {=IF(SUMPRODUCT(($D$6:$D$121=D63)*($H$6:$H$121<I63)*($I$6:$I$121>H63))>1,"Rangkap","")}
B64: 62 | C64: PTPN IV - Regional 4 | D64: Bambang Agustian | E64: SEVP Operation | H64: 45809 | I64: 46022 | J64: 152 | K64: 5 | L64: =N4R4!T101*K64/12 -> 33.581491 | M64: {=IF(SUMPRODUCT(($D$6:$D$121=D64)*($H$6:$H$121<I64)*($I$6:$I$121>H64))>1,"Rangkap","")}
B65: 63 | C65: PTPN IV - Regional 5 | D65: Sudarma Bhakti Lessan | E65: Regional Head R5 | H65: 45728 | I65: 46022 | J65: 295 | K65: 10 | L65: =N4R5!R90*K65/12 -> 63.167441 | M65: {=IF(SUMPRODUCT(($D$6:$D$121=D65)*($H$6:$H$121<I65)*($I$6:$I$121>H65))>1,"Rangkap","")}
B66: 64 | C66: PTPN IV - Regional 5 | D66: Darmansyah Siregar | E66: SEVP Operation I R5 | H66: 45658 | I66: 45879 | J66: 222 | K66: 7 | L66: =N4R5!T90*K66/12 -> 44.123305 | M66: {=IF(SUMPRODUCT(($D$6:$D$121=D66)*($H$6:$H$121<I66)*($I$6:$I$121>H66))>1,"Rangkap","")}
B67: 65 | C67: PTPN IV - Regional 5 | D67: Darmansyah Siregar | E67: SEVP Operation II R5 | H67: 45880 | I67: 46022 | J67: 143 | K67: 5 | L67: =N4R5!T90*K67/12 -> 31.516646 | M67: {=IF(SUMPRODUCT(($D$6:$D$121=D67)*($H$6:$H$121<I67)*($I$6:$I$121>H67))>1,"Rangkap","")}
B68: 66 | C68: PTPN IV - Regional 5 | D68: Ihsan | E68: SEVP Operation II R5 | H68: 45658 | I68: 45879 | J68: 222 | K68: 7 | L68: =N4R5!T90*K68/12 -> 44.123305 | M68: {=IF(SUMPRODUCT(($D$6:$D$121=D68)*($H$6:$H$121<I68)*($I$6:$I$121>H68))>1,"Rangkap","")}
B69: 67 | C69: PTPN IV - Regional 5 | D69: Ihsan | E69: SEVP Operation I R5 | H69: 45880 | I69: 46022 | J69: 143 | K69: 5 | L69: =N4R5!T90*K69/12 -> 31.516646 | M69: {=IF(SUMPRODUCT(($D$6:$D$121=D69)*($H$6:$H$121<I69)*($I$6:$I$121>H69))>1,"Rangkap","")}
B70: 68 | C70: PTPN IV - Regional 5 | D70: Donny Amril | E70: SEVP Business Support R5 | H70: 45658 | I70: 46022 | J70: 365 | K70: 12 | L70: =N4R5!V90*K70/12 -> 74.484656 | M70: {=IF(SUMPRODUCT(($D$6:$D$121=D70)*($H$6:$H$121<I70)*($I$6:$I$121>H70))>1,"Rangkap","")}
B71: 69 | C71: PTPN IV - Regional 6 | D71: Syahriadi Siregar | E71: Region Head R6 Merangkap Business Support | H71: 45658 | I71: 45916 | J71: 259 | K71: 9 | L71: =N4R6!R83*K71/12 -> 62.634533 | M71: {=IF(SUMPRODUCT(($D$6:$D$121=D71)*($H$6:$H$121<I71)*($I$6:$I$121>H71))>1,"Rangkap","")}
B72: 70 | C72: PTPN IV - Regional 6 | D72: Ir Tengku Zein Ichwan | E72: SEVP Operation R6 | H72: 45778 | I72: 46022 | J72: 245 | K72: 8 | L72: =N4R6!T83*K72/12 -> 56.990515 | M72: {=IF(SUMPRODUCT(($D$6:$D$121=D72)*($H$6:$H$121<I72)*($I$6:$I$121>H72))>1,"Rangkap","")}
B73: 71 | C73: PTPN IV - Regional 6 | D73: Tengku Rinel | E73: SEVP Business Support R6 | H73: 45692 | I73: 45809 | J73: 118 | K73: 4 | L73: =N4R6!V83*K73/12 -> 26.47086 | M73: {=IF(SUMPRODUCT(($D$6:$D$121=D73)*($H$6:$H$121<I73)*($I$6:$I$121>H73))>1,"Rangkap","")}
B74: 72 | C74: PTPN IV - Regional 6 | D74: Ifri Handi Lubis | E74: SEVP Business Support | H74: 45809 | I74: 46022 | J74: 214 | K74: 7 | L74: =N4R6!V83*K74/12 -> 46.324004 | M74: {=IF(SUMPRODUCT(($D$6:$D$121=D74)*($H$6:$H$121<I74)*($I$6:$I$121>H74))>1,"Rangkap","")}
B75: 73 | C75: PTPN IV - Regional 6 | D75: Yudhi Cahyadi | E75: Region Head R6 | H75: 45917 | I75: 46022 | J75: 106 | K75: 3 | L75: =N4R6!R83*K75/12 -> 20.878178 | M75: {=IF(SUMPRODUCT(($D$6:$D$121=D75)*($H$6:$H$121<I75)*($I$6:$I$121>H75))>1,"Rangkap","")}
B76: 74 | C76: PTPN IV - Regional 7 | D76: Denny Ramadhan Nasution | E76: Regional Head R7 | H76: 45658 | I76: 46022 | J76: 365 | K76: 12 | L76: =N4R7!R72*K76/12 -> 77.3547 | M76: {=IF(SUMPRODUCT(($D$6:$D$121=D76)*($H$6:$H$121<I76)*($I$6:$I$121>H76))>1,"Rangkap","")}
B77: 75 | C77: PTPN IV - Regional 7 | D77: Oshutri Anwar | E77: SEVP Business Support R7 | H77: 45658 | I77: 46022 | J77: 365 | K77: 12 | L77: =N4R7!V72*K77/12 -> 77.399186 | M77: {=IF(SUMPRODUCT(($D$6:$D$121=D77)*($H$6:$H$121<I77)*($I$6:$I$121>H77))>1,"Rangkap","")}
B78: 76 | C78: PTPN IV - Regional 7 | D78: Rina Tanjung | E78: SEVP Operation R7 | H78: 45658 | I78: 46022 | J78: 365 | K78: 12 | L78: =N4R7!T72*K78/12 -> 77.278198 | M78: {=IF(SUMPRODUCT(($D$6:$D$121=D78)*($H$6:$H$121<I78)*($I$6:$I$121>H78))>1,"Rangkap","")}
B79: 77 | C79: PT SGN | D79: Mahmudi | E79: Direktur Utama | G79: Skor Direktur menyusul | H79: 45658 | I79: 46022 | J79: 365 | K79: 12 | M79: {=IF(SUMPRODUCT(($D$6:$D$121=D79)*($H$6:$H$121<I79)*($I$6:$I$121>H79))>1,"Rangkap","")}
B80: 78 | C80: PT SGN | D80: Dodik Ristiawan | E80: Direktur Operasional | G80: Skor Direktur menyusul | H80: 45658 | I80: 46022 | J80: 365 | K80: 12 | M80: {=IF(SUMPRODUCT(($D$6:$D$121=D80)*($H$6:$H$121<I80)*($I$6:$I$121>H80))>1,"Rangkap","")}
B81: 79 | C81: PT SGN | D81: Hariyanto | E81: Direktur Keuangan | G81: Skor Direktur menyusul | H81: 45658 | I81: 46022 | J81: 365 | K81: 12 | M81: {=IF(SUMPRODUCT(($D$6:$D$121=D81)*($H$6:$H$121<I81)*($I$6:$I$121>H81))>1,"Rangkap","")}
B82: 80 | C82: PT SGN | D82: Affan Safiq | E82: Direktur SDM dan TI | G82: Skor Direktur menyusul | H82: 45658 | I82: 46022 | J82: 365 | K82: 12 | M82: {=IF(SUMPRODUCT(($D$6:$D$121=D82)*($H$6:$H$121<I82)*($I$6:$I$121>H82))>1,"Rangkap","")}
B83: 81 | C83: PT SGN | D83: Aris Toharisman | E83: Direktur Hubungan Kelembagaan dan Manajemen Risiko | G83: Skor Direktur menyusul | H83: 45658 | I83: 45735 | J83: 78 | K83: 3 | M83: {=IF(SUMPRODUCT(($D$6:$D$121=D83)*($H$6:$H$121<I83)*($I$6:$I$121>H83))>1,"Rangkap","")}
B84: 82 | C84: PT SGN | D84: M Fakhrur Rozi | E84: Direktur Manajemen Risiko | G84: Skor Direktur menyusul | H84: 45840 | I84: 46022 | J84: 183 | K84: 6 | M84: {=IF(SUMPRODUCT(($D$6:$D$121=D84)*($H$6:$H$121<I84)*($I$6:$I$121>H84))>1,"Rangkap","")}
B85: 83 | C85: PT SGN | D85: Dimas Eko Prasetyo | E85: SEVP Operation I / SEVP Strategic Business | H85: 45658 | I85: 45840 | J85: 183 | K85: 6 | L85: ='PT SGN'!AQ29*K85/12 -> 40.437089 | M85: {=IF(SUMPRODUCT(($D$6:$D$121=D85)*($H$6:$H$121<I85)*($I$6:$I$121>H85))>1,"Rangkap","")}
B86: 84 | C86: PT SGN | D86: Dimas Eko Prasetyo | E86: Direktur Strategi & Sustainability | G86: Skor Direktur menyusul | H86: 45840 | I86: 46022 | J86: 183 | K86: 6 | M86: {=IF(SUMPRODUCT(($D$6:$D$121=D86)*($H$6:$H$121<I86)*($I$6:$I$121>H86))>1,"Rangkap","")}
B87: 85 | C87: PT SGN | D87: Imam Cipto Suyitno | E87: SEVP Operation II / SEVP Koordinator KSO | H87: 45658 | I87: 45991 | J87: 334 | K87: 11 | L87: ='PT SGN'!AQ29*K87/12 -> 74.134664 | M87: {=IF(SUMPRODUCT(($D$6:$D$121=D87)*($H$6:$H$121<I87)*($I$6:$I$121>H87))>1,"Rangkap","")}
B88: 86 | C88: PT SGN | D88: Putu Sukarmen | E88: SEVP Pengembangan | H88: 45869 | I88: 46022 | J88: 154 | K88: 5 | L88: ='PT SGN'!AQ29*K88/12 -> 33.697574 | M88: {=IF(SUMPRODUCT(($D$6:$D$121=D88)*($H$6:$H$121<I88)*($I$6:$I$121>H88))>1,"Rangkap","")}
B89: 87 | C89: PT SGN | D89: R Tulus Panduwidjaja | E89: SEVP Business Support | H89: 45809 | I89: 46022 | J89: 214 | K89: 7 | L89: ='PT SGN'!AT29*K89/12 -> 38.762634 | M89: {=IF(SUMPRODUCT(($D$6:$D$121=D89)*($H$6:$H$121<I89)*($I$6:$I$121>H89))>1,"Rangkap","")}
B90: 88 | C90: PT SGN | D90: Febri Ari Marpaung | E90: SEVP Operasional KSO | H90: 45658 | I90: 45992 | J90: 335 | K90: 11 | L90: ='PT SGN'!AQ29*K90/12 -> 74.134664 | M90: {=IF(SUMPRODUCT(($D$6:$D$121=D90)*($H$6:$H$121<I90)*($I$6:$I$121>H90))>1,"Rangkap","")}
B91: 89 | C91: PT SGN | D91: Febri Ari Marpaung | E91: SEVP Koordinator KSO | H91: 45992 | I91: 46022 | J91: 31 | K91: 1 | L91: ='PT SGN'!AQ29*K91/12 -> 6.7395149 | M91: {=IF(SUMPRODUCT(($D$6:$D$121=D91)*($H$6:$H$121<I91)*($I$6:$I$121>H91))>1,"Rangkap","")}
B92: 90 | C92: PT RPN | D92: Iman Yani Harahap | E92: Direktur | H92: 45658 | I92: 46022 | J92: 365 | K92: 12 | L92: =RPN!R33*K92/12 -> 88.099317 | M92: {=IF(SUMPRODUCT(($D$6:$D$121=D92)*($H$6:$H$121<I92)*($I$6:$I$121>H92))>1,"Rangkap","")}
B93: 91 | C93: PT RPN | D93: Tjahjono Herawan | E93: SEVP Operation I | H93: 45658 | I93: 46022 | J93: 365 | K93: 12 | L93: =RPN!Y33*K93/12 -> 87.009253 | M93: {=IF(SUMPRODUCT(($D$6:$D$121=D93)*($H$6:$H$121<I93)*($I$6:$I$121>H93))>1,"Rangkap","")}
B94: 92 | C94: PT RPN | D94: Misnawi | E94: SEVP Operation II | H94: 45658 | I94: 46022 | J94: 365 | K94: 12 | L94: =RPN!Y33*K94/12 -> 87.009253 | M94: {=IF(SUMPRODUCT(($D$6:$D$121=D94)*($H$6:$H$121<I94)*($I$6:$I$121>H94))>1,"Rangkap","")}
B95: 93 | C95: PT RPN | D95: Edy Suprianto | E95: SEVP Business Support | H95: 45658 | I95: 46022 | J95: 365 | K95: 12 | L95: =RPN!AB33*K95/12 -> 87.643837 | M95: {=IF(SUMPRODUCT(($D$6:$D$121=D95)*($H$6:$H$121<I95)*($I$6:$I$121>H95))>1,"Rangkap","")}
B96: 94 | C96: PT RPN | D96: Muhammad Edwin Syahputra | E96: SEVP Riset, Inovasi, dan Sustainability | H96: 45658 | I96: 46022 | J96: 365 | K96: 12 | L96: =RPN!Y33*K96/12 -> 87.009253 | M96: {=IF(SUMPRODUCT(($D$6:$D$121=D96)*($H$6:$H$121<I96)*($I$6:$I$121>H96))>1,"Rangkap","")}
B97: 95 | C97: PT LPPAN | D97: Pranoto Hadi Raharjo | E97: Direktur | H97: 45658 | I97: 46022 | J97: 365 | K97: 12 | L97: =LPP!Q30*K97/12 -> 101.12832 | M97: {=IF(SUMPRODUCT(($D$6:$D$121=D97)*($H$6:$H$121<I97)*($I$6:$I$121>H97))>1,"Rangkap","")}
B98: 96 | C98: PT LPPAN | D98: Pugar Indriawan | E98: SEVP Operation | H98: 45658 | I98: 46022 | J98: 365 | K98: 12 | L98: =LPP!X30*K98/12 -> 104.94083 | M98: {=IF(SUMPRODUCT(($D$6:$D$121=D98)*($H$6:$H$121<I98)*($I$6:$I$121>H98))>1,"Rangkap","")}
B99: 97 | C99: PT LPPAN | D99: Sosiawan Hary Kustanto | E99: SEVP Business Support | H99: 45658 | I99: 46022 | J99: 365 | K99: 12 | L99: =LPP!AA30*K99/12 -> 97.775816 | M99: {=IF(SUMPRODUCT(($D$6:$D$121=D99)*($H$6:$H$121<I99)*($I$6:$I$121>H99))>1,"Rangkap","")}
A100: not found | B100: 98 | C100: PT KINRA | D100: Arif Budiman | E100: Direktur | H100: 45994 | I100: 46022 | J100: 29 | K100: 1 | L100: =KINRA!T35*K100/12 -> 7.4811241 | M100: {=IF(SUMPRODUCT(($D$6:$D$121=D100)*($H$6:$H$121<I100)*($I$6:$I$121>H100))>1,"Rangkap","")} -> Rangkap
B101: 99 | C101: PT KINRA | D101: VT Moses Situmorang | E101: Direktur | H101: 45658 | I101: 45994 | J101: 337 | K101: 11 | L101: =KINRA!T35*K101/12 -> 82.292366 | M101: {=IF(SUMPRODUCT(($D$6:$D$121=D101)*($H$6:$H$121<I101)*($I$6:$I$121>H101))>1,"Rangkap","")}
B102: 100 | C102: PT KINRA | D102: Alwin Abdi | E102: SEVP Business Support | H102: 45658 | I102: 46022 | J102: 365 | K102: 12 | L102: =KINRA!AD35*K102/12 -> 86.492949 | M102: {=IF(SUMPRODUCT(($D$6:$D$121=D102)*($H$6:$H$121<I102)*($I$6:$I$121>H102))>1,"Rangkap","")}
B103: 101 | C103: PT KINRA | D103: Kennedy Nasib P. Sibarani | E103: SEVP Operation | H103: 45658 | I103: 46022 | J103: 365 | K103: 12 | L103: =KINRA!AA35*K103/12 -> 84.408548 | M103: {=IF(SUMPRODUCT(($D$6:$D$121=D103)*($H$6:$H$121<I103)*($I$6:$I$121>H103))>1,"Rangkap","")}
...

Sheet PTPN III (Persero)
A1: Key Performance Indicator PT Perkebunan Nusantara III (Persero)
A2: s.d. Desember 2025
V3: Cascade Penilaian Region Head & SEVP
A4: No. | B4: Key Performance Indicator | C4: ESG/C | D4: 88 PS | E4: Satuan | F4: Target 2025 | G4: Target s.d. Desember | H4: Realisasi s.d. Desember | I4: Polaritas | J4: Bobot | L4: Realisasi vs Target s.d. Desember | N4: Realisasi vs Target 2025 | P4: Target 2025 | Q4: Realisasi 2025 | R4: Bobot KPI | S4: % Capaian Realisasi | T4: Skor Realisasi KPI | V4: Region Head | Y4: SEVP Operation / Koordinator KSO / Operasional KSO / Aset | AB4: SEVP Business Support / Business Strategy
J5: Sub | K5: Total | L5: Sub | M5: Total | N5: Sub | O5: Total | V5: Bobot | W5: % Capaian | X5: Skor | Y5: Bobot | Z5: % Capaian | AA5: Skor | AB5: Bobot | AC5: % Capaian | AD5: Skor
A6: A. Nilai Ekonomi dan Sosial Untuk Indonesia | V6: =V7+V11+V15 -> 50 | W6: =IFERROR(X6/V6,0) -> 0.89834112 | X6: =X7+X11+X15 -> 44.917056 | Y6: =Y7+Y11+Y15 -> 50 | Z6: =IFERROR(AA6/Y6,0) -> 0.90772431 | AA6: =AA7+AA11+AA15 -> 45.386215 | AB6: =AB7+AB11+AB15 -> 50 | AC6: =IFERROR(AD6/AB6,0) -> 0.86950976 | AD6: =AD7+AD11+AD15 -> 43.475488
A7: A.1 Finansial | V7: =SUM(V8:V10) -> 20 | W7: =IFERROR(X7/V7,0) -> 0.825 | X7: =SUM(X8:X10) -> 16.5 | Y7: =SUM(Y8:Y10) -> 10 | Z7: =IFERROR(AA7/Y7,0) -> 0.77 | AA7: =SUM(AA8:AA10) -> 7.7 | AB7: =SUM(AB8:AB10) -> 30 | AC7: =IFERROR(AD7/AB7,0) -> 0.80666667 | AD7: =SUM(AD8:AD10) -> 24.2
A8: 1 | B8: EBITDA Margin | C8: C | E8: % | F8: 22.89 | G8: 22.89 | H8: 26.94 | I8: Maximize | J8: 8 | K8: =J8+J9+J10 -> 18 | L8: =IFERROR(MIN(1.1*J8,(H8/G8)*J8),0) -> 8.8 | M8: =SUM(L8:L10) -> 14.3 | N8: =IFERROR(MIN(1.1*J8,(H8/F8)*J8),0) -> 8.8 | O8: =SUM(N8:N10) -> 14.3 | P8: =F8 -> 22.89 | Q8: =H8 -> 26.94 | R8: =J8 -> 8 | S8: =IFERROR(IF(I8="Minimize",F8/H8,IF(F8<=0,IF(H8>=F8,1.1,0),H8/F8)),0) -> 1.1769332 | T8: =MIN(1.1*R8,S8*R8) -> 8.8 | V8: 9 | W8: =S8 -> 1.1769332 | X8: =MIN(1.1*V8,W8*V8) -> 9.9 | Y8: 4 | Z8: =S8 -> 1.1769332 | AA8: =MIN(1.1*Y8,Z8*Y8) -> 4.4 | AB8: 14 | AC8: =S8 -> 1.1769332 | AD8: =MIN(1.1*AB8,AC8*AB8) -> 15.4
A9: 2 | B9: ROIC >= WACC | C9: C | E9: % | F9: -1.34 | G9: -1.34 | H9: 0.44 | I9: Maximize | J9: 5 | L9: 5.5 | N9: 5.5 | P9: =F9 -> -1.34 | Q9: =H9 -> 0.44 | R9: =J9 -> 5 | S9: =IFERROR(IF(I9="Minimize",F9/H9,IF(F9<=0,IF(H9>=F9,1.1,0),H9/F9)),0) -> 1.1 | T9: =MIN(1.1*R9,S9*R9) -> 5.5 | V9: 6 | W9: =S9 -> 1.1 | X9: =MIN(1.1*V9,W9*V9) -> 6.6 | Y9: 3 | Z9: =S9 -> 1.1 | AA9: =MIN(1.1*Y9,Z9*Y9) -> 3.3 | AB9: 8 | AC9: =S9 -> 1.1 | AD9: =MIN(1.1*AB9,AC9*AB9) -> 8.8
A10: 3 | B10: Penyampaian LAI Tahun 2024 | C10: G | E10: Waktu | F10: 15/04/2025 | G10: 15/04/2025 | H10: 45861 | I10: Minimize | J10: 5 | L10: 0 | N10: =IFERROR(MIN(1.1*L10,(H10/J10)*L10),0) -> 0 | P10: =F10 -> 15/04/2025 | Q10: =H10 -> 45861 | R10: =J10 -> 5 | S10: =IFERROR(T10/R10,0) -> 0 | T10: =R10*IF(H10<DATE(2025,4,1),1.1,IF(H10<=DATE(2025,4,15),1,IF(H10<=DATE(2025,5,31),0.8,IF(H10<=DATE(2025,6,15),0.4,IF(H10<=DATE(2025,6,30),0.2,0))))) -> 0 | V10: 5 | W10: =S10 -> 0 | X10: =MIN(1.1*V10,W10*V10) -> 0 | Y10: 3 | Z10: =S10 -> 0 | AA10: =MIN(1.1*Y10,Z10*Y10) -> 0 | AB10: 8 | AC10: =S10 -> 0 | AD10: =MIN(1.1*AB10,AC10*AB10) -> 0
A11: A.2. Operasional | V11: =SUM(V12:V14) -> 20 | W11: =IFERROR(X11/V11,0) -> 0.91473527 | X11: =SUM(X12:X14) -> 18.294705 | Y11: =SUM(Y12:Y14) -> 30 | Z11: =IFERROR(AA11/Y11,0) -> 0.91879549 | AA11: =SUM(AA12:AA14) -> 27.563865 | AB11: =SUM(AB12:AB14) -> 10 | AC11: =IFERROR(AD11/AB11,0) -> 0.91531373 | AD11: =SUM(AD12:AD14) -> 9.1531373
A12: 4 | B12: Produktivitas CPO | C12: C | E12: Ton/Ha | F12: 5.43 | G12: 5.43 | H12: 4.8 | I12: Maximize | J12: 7 | K12: =SUM(J12+J13+J14) -> 21 | L12: =IFERROR(MIN(1.1*J12,(H12/G12)*J12),0) -> 6.1878453 | M12: =SUM(L12+L13+L14) -> 19.294705 | N12: =IFERROR(MIN(1.1*J12,(H12/F12)*J12),0) -> 6.1878453 | O12: =SUM(N12+N13+N14) -> 19.294705 | P12: =F12 -> 5.43 | Q12: =H12 -> 4.8 | R12: =J12 -> 7 | S12: =IFERROR(IF(I12="Minimize",F12/H12,IF(F12<=0,IF(H12>=F12,1.1,0),H12/F12)),0) -> 0.8839779 | T12: =MIN(1.1*R12,S12*R12) -> 6.1878453 | V12: 7 | W12: =S12 -> 0.8839779 | X12: =MIN(1.1*V12,W12*V12) -> 6.1878453 | Y12: 10 | Z12: =S12 -> 0.8839779 | AA12: =MIN(1.1*Y12,Z12*Y12) -> 8.839779 | AB12: 4 | AC12: =S12 -> 0.8839779 | AD12: =MIN(1.1*AB12,AC12*AB12) -> 3.5359116
A13: 5 | B13: Pencapaian Produksi Gula Untuk Mendukung Swasembada | C13: C | E13: Ton | F13: 1011621 | G13: 1011621 | H13: 882546.84 | I13: Maximize | J13: 7 | L13: =IFERROR(MIN(1.1*J13,(H13/G13)*J13),0) -> 6.1068601 | N13: =IFERROR(MIN(1.1*J13,(H13/F13)*J13),0) -> 6.1068601 | P13: =F13 -> 1011621 | Q13: =H13 -> 882546.84 | R13: =J13 -> 7 | S13: =IFERROR(IF(I13="Minimize",F13/H13,IF(F13<=0,IF(H13>=F13,1.1,0),H13/F13)),0) -> 0.87240858 | T13: =MIN(1.1*R13,S13*R13) -> 6.1068601 | V13: 7 | W13: =S13 -> 0.87240858 | X13: =MIN(1.1*V13,W13*V13) -> 6.1068601 | Y13: 10 | Z13: =S13 -> 0.87240858 | AA13: =MIN(1.1*Y13,Z13*Y13) -> 8.7240858 | AB13: 3 | AC13: =S13 -> 0.87240858 | AD13: =MIN(1.1*AB13,AC13*AB13) -> 2.6172257
A14: 6 | B14: Sinergi BUMN Untuk Mendukung Swasembada Gula | C14: C | E14: % | F14: 100 | G14: 100 | H14: 100 | I14: Maximize | J14: 7 | L14: =IFERROR(MIN(1.1*J14,(H14/G14)*J14),0) -> 7 | N14: =IFERROR(MIN(1.1*J14,(H14/F14)*J14),0) -> 7 | P14: =F14 -> 100 | Q14: =H14 -> 100 | R14: =J14 -> 7 | S14: =IFERROR(IF(I14="Minimize",F14/H14,IF(F14<=0,IF(H14>=F14,1.1,0),H14/F14)),0) -> 1 | T14: =MIN(1.1*R14,S14*R14) -> 7 | V14: 6 | W14: =S14 -> 1 | X14: =MIN(1.1*V14,W14*V14) -> 6 | Y14: 10 | Z14: =S14 -> 1 | AA14: =MIN(1.1*Y14,Z14*Y14) -> 10 | AB14: 3 | AC14: =S14 -> 1 | AD14: =MIN(1.1*AB14,AC14*AB14) -> 3
A15: A.3. Sosial | V15: =SUM(V16:V17) -> 10 | W15: =IFERROR(X15/V15,0) -> 1.012235 | X15: =SUM(X16:X17) -> 10.12235 | Y15: =SUM(Y16:Y17) -> 10 | Z15: =IFERROR(AA15/Y15,0) -> 1.012235 | AA15: =SUM(AA16:AA17) -> 10.12235 | AB15: =SUM(AB16:AB17) -> 10 | AC15: =IFERROR(AD15/AB15,0) -> 1.012235 | AD15: =SUM(AD16:AD17) -> 10.12235
A16: 7 | B16: Perolehan Bahan Baku P-3 Kelapa Sawit | C16: S | E16: Ton | F16: 3191756 | G16: 3191756 | H16: 3259110 | I16: Maximize | J16: 7 | K16: =SUM(J16:J17) -> 15 | L16: =IFERROR(MIN(1.1*J16,(H16/G16)*J16),0) -> 7.1477174 | M16: =SUM(L16:L17) -> 15.174658 | N16: =IFERROR(MIN(1.1*J16,(H16/F16)*J16),0) -> 7.1477174 | O16: =SUM(N16:N17) -> 15.174658 | P16: =F16 -> 3191756 | Q16: =H16 -> 3259110 | R16: =J16 -> 7 | S16: =IFERROR(IF(I16="Minimize",F16/H16,IF(F16<=0,IF(H16>=F16,1.1,0),H16/F16)),0) -> 1.0211025 | T16: =MIN(1.1*R16,S16*R16) -> 7.1477174 | V16: 5 | W16: =S16 -> 1.0211025 | X16: =MIN(1.1*V16,W16*V16) -> 5.1055125 | Y16: 5 | Z16: =S16 -> 1.0211025 | AA16: =MIN(1.1*Y16,Z16*Y16) -> 5.1055125 | AB16: 5 | AC16: =S16 -> 1.0211025 | AD16: =MIN(1.1*AB16,AC16*AB16) -> 5.1055125
A17: 8 | B17: Peremajaan Sawit Rakyat Sebagai Komitmen PSN | C17: S | E17: Ha | F17: 22568 | G17: 22568 | H17: 22644 | I17: Maximize | J17: 8 | L17: =IFERROR(MIN(1.1*J17,(H17/G17)*J17),0) -> 8.0269408 | N17: =IFERROR(MIN(1.1*J17,(H17/F17)*J17),0) -> 8.0269408 | P17: =F17 -> 22568 | Q17: =H17 -> 22644 | R17: =J17 -> 8 | S17: =IFERROR(IF(I17="Minimize",F17/H17,IF(F17<=0,IF(H17>=F17,1.1,0),H17/F17)),0) -> 1.0033676 | T17: =MIN(1.1*R17,S17*R17) -> 8.0269408 | V17: 5 | W17: =S17 -> 1.0033676 | X17: =MIN(1.1*V17,W17*V17) -> 5.016838 | Y17: 5 | Z17: =S17 -> 1.0033676 | AA17: =MIN(1.1*Y17,Z17*Y17) -> 5.016838 | AB17: 5 | AC17: =S17 -> 1.0033676 | AD17: =MIN(1.1*AB17,AC17*AB17) -> 5.016838
A18: B. Inovasi Model Bisnis | V18: =SUM(V19:V21) -> 15 | W18: =IFERROR(X18/V18,0) -> 0.86583629 | X18: =SUM(X19:X21) -> 12.987544 | Y18: =SUM(Y19:Y21) -> 15 | Z18: =IFERROR(AA18/Y18,0) -> 0.86583629 | AA18: =SUM(AA19:AA21) -> 12.987544 | AB18: =SUM(AB19:AB21) -> 15 | AC18: =IFERROR(AD18/AB18,0) -> 0.86583629 | AD18: =SUM(AD19:AD21) -> 12.987544
A19: 1 | B19: Sertifikasi RSPO PKS | C19: E | E19: Unit | F19: 68 | G19: 68 | H19: 67 | I19: Maximize | J19: 5 | K19: =J19+J20+J21 -> 15 | L19: =IFERROR(MIN(1.1*J19,(H19/G19)*J19),0) -> 4.9264706 | M19: =SUM(L19:L21) -> 12.987544 | N19: =IFERROR(MIN(1.1*J19,(H19/F19)*J19),0) -> 4.9264706 | O19: =SUM(N19:N21) -> 12.987544 | P19: =F19 -> 68 | Q19: =H19 -> 67 | R19: =J19 -> 5 | S19: =IFERROR(IF(I19="Minimize",F19/H19,IF(F19<=0,IF(H19>=F19,1.1,0),H19/F19)),0) -> 0.98529412 | T19: =MIN(1.1*R19,S19*R19) -> 4.9264706 | V19: 5 | W19: =S19 -> 0.98529412 | X19: =MIN(1.1*V19,W19*V19) -> 4.9264706 | Y19: 5 | Z19: =S19 -> 0.98529412 | AA19: =MIN(1.1*Y19,Z19*Y19) -> 4.9264706 | AB19: 5 | AC19: =S19 -> 0.98529412 | AD19: =MIN(1.1*AB19,AC19*AB19) -> 4.9264706
A20: 2 | B20: Sertifikasi RSPO Kebun | C20: E | E20: Unit | F20: 149 | G20: 149 | H20: 124 | I20: Maximize | J20: 5 | L20: =IFERROR(MIN(1.1*J20,(H20/G20)*J20),0) -> 4.1610738 | N20: =IFERROR(MIN(1.1*J20,(H20/F20)*J20),0) -> 4.1610738 | P20: =F20 -> 149 | Q20: =H20 -> 124 | R20: =J20 -> 5 | S20: =IFERROR(IF(I20="Minimize",F20/H20,IF(F20<=0,IF(H20>=F20,1.1,0),H20/F20)),0) -> 0.83221477 | T20: =MIN(1.1*R20,S20*R20) -> 4.1610738 | V20: 5 | W20: =S20 -> 0.83221477 | X20: =MIN(1.1*V20,W20*V20) -> 4.1610738 | Y20: 5 | Z20: =S20 -> 0.83221477 | AA20: =MIN(1.1*Y20,Z20*Y20) -> 4.1610738 | AB20: 5 | AC20: =S20 -> 0.83221477 | AD20: =MIN(1.1*AB20,AC20*AB20) -> 4.1610738
A21: 3 | B21: Implementasi Post Merger Integration | C21: C | E21: % | F21: 100 | G21: 100 | H21: 78 | I21: Maximize | J21: 5 | L21: =IFERROR(MIN(1.1*J21,(H21/G21)*J21),0) -> 3.9 | N21: =IFERROR(MIN(1.1*J21,(H21/F21)*J21),0) -> 3.9 | P21: =F21 -> 100 | Q21: =H21 -> 78 | R21: =J21 -> 5 | S21: =IFERROR(IF(I21="Minimize",F21/H21,IF(F21<=0,IF(H21>=F21,1.1,0),H21/F21)),0) -> 0.78 | T21: =MIN(1.1*R21,S21*R21) -> 3.9 | V21: 5 | W21: =S21 -> 0.78 | X21: =MIN(1.1*V21,W21*V21) -> 3.9 | Y21: 5 | Z21: =S21 -> 0.78 | AA21: =MIN(1.1*Y21,Z21*Y21) -> 3.9 | AB21: 5 | AC21: =S21 -> 0.78 | AD21: =MIN(1.1*AB21,AC21*AB21) -> 3.9
A22: C. Kepemimpinan Teknologi | V22: =V23 -> 10 | W22: =IFERROR(X22/V22,0) -> 1 | X22: =X23 -> 10 | Y22: =Y23 -> 10 | Z22: =IFERROR(AA22/Y22,0) -> 1 | AA22: =AA23 -> 10 | AB22: =AB23 -> 10 | AC22: =IFERROR(AD22/AB22,0) -> 1 | AD22: =AD23 -> 10
A23: 1 | B23: Implementasi Use Case Dalam RSTI 2025 - 2029 | C23: C | E23: % | F23: 100 | G23: 100 | H23: 100 | I23: Maximize | J23: 8 | K23: =J23 -> 8 | L23: =IFERROR(MIN(1.1*J23,(H23/G23)*J23),0) -> 8 | M23: =SUM(L23) -> 8 | N23: =IFERROR(MIN(1.1*J23,(H23/F23)*J23),0) -> 8 | O23: =SUM(N23) -> 8 | P23: =F23 -> 100 | Q23: =H23 -> 100 | R23: =J23 -> 8 | S23: =IFERROR(IF(I23="Minimize",F23/H23,IF(F23<=0,IF(H23>=F23,1.1,0),H23/F23)),0) -> 1 | T23: =MIN(1.1*R23,S23*R23) -> 8 | V23: 10 | W23: =S23 -> 1 | X23: =MIN(1.1*V23,W23*V23) -> 10 | Y23: 10 | Z23: =S23 -> 1 | AA23: =MIN(1.1*Y23,Z23*Y23) -> 10 | AB23: 10 | AC23: =S23 -> 1 | AD23: =MIN(1.1*AB23,AC23*AB23) -> 10
A24: D. Peningkatan Investasi | V24: =SUM(V25:V26) -> 15 | W24: =IFERROR(X24/V24,0) -> 0.87846248 | X24: =SUM(X25:X26) -> 13.176937 | Y24: =SUM(Y25:Y26) -> 15 | Z24: =IFERROR(AA24/Y24,0) -> 0.87846248 | AA24: =SUM(AA25:AA26) -> 13.176937 | AB24: =SUM(AB25:AB26) -> 15 | AC24: =IFERROR(AD24/AB24,0) -> 0.87846248 | AD24: =SUM(AD25:AD26) -> 13.176937
A25: 1 | B25: Replanting & Konversi | C25: C | E25: Ha | F25: 41842 | G25: 41842 | H25: 38288.5 | I25: Maximize | J25: 8 | K25: =J25+J26 -> 15 | L25: =IFERROR(MIN(1.1*J25,(H25/G25)*J25),0) -> 7.320587 | M25: =SUM(L25:L26) -> 13.176937 | N25: =IFERROR(MIN(1.1*J25,(H25/F25)*J25),0) -> 7.320587 | O25: =SUM(N25:N26) -> 13.176937 | P25: =F25 -> 41842 | Q25: =H25 -> 38288.5 | R25: =J25 -> 8 | S25: =IFERROR(IF(I25="Minimize",F25/H25,IF(F25<=0,IF(H25>=F25,1.1,0),H25/F25)),0) -> 0.91507337 | T25: =MIN(1.1*R25,S25*R25) -> 7.320587 | V25: 8 | W25: =S25 -> 0.91507337 | X25: =MIN(1.1*V25,W25*V25) -> 7.320587 | Y25: 8 | Z25: =S25 -> 0.91507337 | AA25: =MIN(1.1*Y25,Z25*Y25) -> 7.320587 | AB25: 8 | AC25: =S25 -> 0.91507337 | AD25: =MIN(1.1*AB25,AC25*AB25) -> 7.320587
A26: 2 | B26: Realisasi PMN | C26: S | E26: % | F26: 97.32 | G26: 97.32 | H26: 81.42 | I26: Maximize | J26: 7 | L26: =IFERROR(MIN(1.1*J26,(H26/G26)*J26),0) -> 5.8563502 | N26: =IFERROR(MIN(1.1*J26,(H26/F26)*J26),0) -> 5.8563502 | P26: =F26 -> 97.32 | Q26: =H26 -> 81.42 | R26: =J26 -> 7 | S26: =IFERROR(IF(I26="Minimize",F26/H26,IF(F26<=0,IF(H26>=F26,1.1,0),H26/F26)),0) -> 0.83662145 | T26: =MIN(1.1*R26,S26*R26) -> 5.8563502 | V26: 7 | W26: =S26 -> 0.83662145 | X26: =MIN(1.1*V26,W26*V26) -> 5.8563502 | Y26: 7 | Z26: =S26 -> 0.83662145 | AA26: =MIN(1.1*Y26,Z26*Y26) -> 5.8563502 | AB26: 7 | AC26: =S26 -> 0.83662145 | AD26: =MIN(1.1*AB26,AC26*AB26) -> 5.8563502
A27: E. Pengembangan Talenta | V27: =V28 -> 10 | W27: =IFERROR(X27/V27,0) -> 0.946 | X27: =X28 -> 9.46 | Y27: =Y28 -> 10 | Z27: =IFERROR(AA27/Y27,0) -> 0.946 | AA27: =AA28 -> 9.46 | AB27: =AB28 -> 10 | AC27: =IFERROR(AD27/AB27,0) -> 0.946 | AD27: =AD28 -> 9.46
A28: 1 | B28: Human Capital Transformation | C28: S | E28: % | F28: 100 | G28: 100 | H28: 94.6 | I28: Maximize | J28: 8 | K28: =J28 -> 8 | L28: =IFERROR(MIN(1.1*J28,(H28/G28)*J28),0) -> 7.568 | M28: =SUM(L28) -> 7.568 | N28: =IFERROR(MIN(1.1*J28,(H28/F28)*J28),0) -> 7.568 | O28: =SUM(N28) -> 7.568 | P28: =F28 -> 100 | Q28: =H28 -> 94.6 | R28: =J28 -> 8 | S28: =IFERROR(IF(I28="Minimize",F28/H28,IF(F28<=0,IF(H28>=F28,1.1,0),H28/F28)),0) -> 0.946 | T28: =MIN(1.1*R28,S28*R28) -> 7.568 | V28: 10 | W28: =S28 -> 0.946 | X28: =MIN(1.1*V28,W28*V28) -> 9.46 | Y28: 10 | Z28: =S28 -> 0.946 | AA28: =MIN(1.1*Y28,Z28*Y28) -> 9.46 | AB28: 10 | AC28: =S28 -> 0.946 | AD28: =MIN(1.1*AB28,AC28*AB28) -> 9.46
B29: TOTAL | K29: =SUM(K8,K12,K16,K19,K23,K25,K28) -> 100 | M29: =SUM(M8,M12,M16,M19,M23,M25,M28) -> 90.501845 | O29: =SUM(O8,O12,O16,O19,O23,O25,O28) -> 90.501845 | R29: =SUM(R8:R28) -> 100 | S29: =IFERROR(T29/R29,0) -> 0.90501845 | T29: =SUM(T8:T28) -> 90.501845 | V29: =V7+V11+V15+V18+V22+V24+V27 -> 100 | W29: =IFERROR(X29/V29,0) -> 0.90541537 | X29: =X7+X11+X15+X18+X22+X24+X27 -> 90.541537 | Y29: =Y7+Y11+Y15+Y18+Y22+Y24+Y27 -> 100 | Z29: =IFERROR(AA29/Y29,0) -> 0.91010697 | AA29: =AA7+AA11+AA15+AA18+AA22+AA24+AA27 -> 91.010697 | AB29: =AB7+AB11+AB15+AB18+AB22+AB24+AB27 -> 100 | AC29: =IFERROR(AD29/AB29,0) -> 0.89099969 | AD29: =AD7+AD11+AD15+AD18+AD22+AD24+AD27 -> 89.099969

Sheet PTPN IV
A1: Key Performance Indicator PT Perkebunan Nusantara IV
A2: s.d. Desember2025
A4: No. | B4: Key Performance Indicator | C4: ESG/C | D4: 88 PS | E4: Satuan | F4: Target 2025 | G4: Target s.d. Desember | H4: Realisasi s.d. Desember | I4: Polaritas | J4: Bobot | L4: Realisasi vs Target s.d. Desember | N4: Realisasi vs Target 2025 | P4: Target 2025 | Q4: Realisasi 2025 | R4: Bobot KPI | S4: % Capaian Realisasi | T4: Skor Realisasi KPI | V4: Region Head | Y4: SEVP Operation / Koordinator KSO / Operasional KSO / Aset | AB4: SEVP Business Support / Business Strategy
J5: Sub | K5: Total | L5: Sub | M5: Total | N5: Sub | O5: Total | V5: Bobot | W5: % Capaian | X5: Skor | Y5: Bobot | Z5: % Capaian | AA5: Skor | AB5: Bobot | AC5: % Capaian | AD5: Skor
A6: A. Nilai Ekonomi dan Sosial Untuk Indonesia
A7: A.1 Finansial
A8: 1 | B8: EBITDA Margin | C8: C | E8: % | F8: 21.92 | G8: 21.92 | H8: 26.15 | I8: Maximize | J8: 8 | K8: =J8+J9+J10 -> 18 | L8: =IFERROR(MIN(1.1*J8,(H8/G8)*J8),0) -> 8.8 | M8: =L8+L9+L10 -> 14.3 | N8: =IFERROR(MIN(1.1*J8,(H8/F8)*J8),0) -> 8.8 | O8: =N8+N9+N10 -> 14.3 | P8: =F8 -> 21.92 | Q8: =H8 -> 26.15 | R8: =J8 -> 8 | S8: =IFERROR(MAX(0,IF(I8="Minimize",F8/H8,IF(F8>0,H8/F8,IF(H8>0,1.1,F8/H8)))),0) -> 1.1929745 | T8: =MIN(1.1*R8,S8*R8) -> 8.8 | V8: 9 | W8: =S8 -> 1.1929745 | X8: =MIN(1.1*V8,W8*V8) -> 9.9 | Y8: 4 | Z8: =S8 -> 1.1929745 | AA8: =MIN(1.1*Y8,Z8*Y8) -> 4.4 | AB8: 14 | AC8: =S8 -> 1.1929745 | AD8: =MIN(1.1*AB8,AC8*AB8) -> 15.4
A9: 2 | B9: ROIC >= WACC | C9: C | E9: % | F9: 3.8187418 | G9: 3.8187418 | H9: 9.72 | I9: Maximize | J9: 5 | L9: =IFERROR(MIN(1.1*J9,(H9/G9)*J9),0) -> 5.5 | N9: =IFERROR(MIN(1.1*J9,(H9/F9)*J9),0) -> 5.5 | P9: =F9 -> 3.8187418 | Q9: =H9 -> 9.72 | R9: =J9 -> 5 | S9: =IFERROR(MAX(0,IF(I9="Minimize",F9/H9,IF(F9>0,H9/F9,IF(H9>0,1.1,F9/H9)))),0) -> 2.545341 | T9: =MIN(1.1*R9,S9*R9) -> 5.5 | V9: 6 | W9: =S9 -> 2.545341 | X9: =MIN(1.1*V9,W9*V9) -> 6.6 | Y9: 3 | Z9: =S9 -> 2.545341 | AA9: =MIN(1.1*Y9,Z9*Y9) -> 3.3 | AB9: 8 | AC9: =S9 -> 2.545341 | AD9: =MIN(1.1*AB9,AC9*AB9) -> 8.8
A10: 3 | B10: Penyampaian LAI Tahun 2025 | C10: G | E10: Waktu | F10: 45747 | G10: 45748 | H10: 45748 | I10: Minimize | J10: 5 | L10: =IFERROR(MIN(1.1*J10,(F10/D10)*J10),0) -> 0 | N10: =IFERROR(MIN(1.1*L10,(H10/F10)*L10),0) -> 0 | P10: =F10 -> 45747 | Q10: =H10 -> 45748 | R10: =J10 -> 5 | S10: =IFERROR(T10/R10,0) -> 1 | T10: =R10*IF(H10<DATE(2025,4,1),1.1,IF(H10<=DATE(2025,4,15),1,IF(H10<=DATE(2025,5,31),0.8,IF(H10<=DATE(2025,6,15),0.4,IF(H10<=DATE(2025,6,30),0.2,0))))) -> 5 | V10: 5 | W10: =S10 -> 1 | X10: =MIN(1.1*V10,W10*V10) -> 5 | Y10: 3 | Z10: =S10 -> 1 | AA10: =MIN(1.1*Y10,Z10*Y10) -> 3 | AB10: 8 | AC10: =S10 -> 1 | AD10: =MIN(1.1*AB10,AC10*AB10) -> 8
A11: A.2. Operasional
A12: 4 | B12: Cash Cost Kelapa Sawit | C12: C | E12: Rp/Kg | F12: 4630.8 | G12: 4630.8 | H12: 4405 | I12: Minimize | J12: 10 | K12: =SUM(J12:J13) -> 20 | L12: =IFERROR(MIN(1.1*J12,(G12/H12)*J12),0) -> 10.512599 | M12: =SUM(L12,L13) -> 19.353841 | N12: =IFERROR(MIN(1.1*J12,(F12/H12)*J12),0) -> 10.512599 | O12: =SUM(N12,N13) -> 19.353841 | P12: =F12 -> 4630.8 | Q12: =H12 -> 4405 | R12: =J12 -> 10 | S12: =IFERROR(MAX(0,IF(I12="Minimize",F12/H12,IF(F12>0,H12/F12,IF(H12>0,1.1,F12/H12)))),0) -> 1.0512599 | T12: =MIN(1.1*R12,S12*R12) -> 10.512599 | V12: 10 | W12: =S12 -> 1.0512599 | X12: =MIN(1.1*V12,W12*V12) -> 10.512599 | Y12: 15 | Z12: =S12 -> 1.0512599 | AA12: =MIN(1.1*Y12,Z12*Y12) -> 15.768899 | AB12: 5 | AC12: =S12 -> 1.0512599 | AD12: =MIN(1.1*AB12,AC12*AB12) -> 5.2562997
A13: 5 | B13: Produktivitas CPO | C13: C | E13: Ton/Ha | F13: 5.4291019 | G13: 5.4291019 | H13: 4.8 | I13: Maximize | J13: 10 | L13: =IFERROR(MIN(1.1*J13,(H13/G13)*J13),0) -> 8.8412413 | N13: =IFERROR(MIN(1.1*J13,(H13/F13)*J13),0) -> 8.8412413 | P13: =F13 -> 5.4291019 | Q13: =H13 -> 4.8 | R13: =J13 -> 10 | S13: =IFERROR(MAX(0,IF(I13="Minimize",F13/H13,IF(F13>0,H13/F13,IF(H13>0,1.1,F13/H13)))),0) -> 0.88412413 | T13: =MIN(1.1*R13,S13*R13) -> 8.8412413 | V13: 10 | W13: =S13 -> 0.88412413 | X13: =MIN(1.1*V13,W13*V13) -> 8.8412413 | Y13: 15 | Z13: =S13 -> 0.88412413 | AA13: =MIN(1.1*Y13,Z13*Y13) -> 13.261862 | AB13: 5 | AC13: =S13 -> 0.88412413 | AD13: =MIN(1.1*AB13,AC13*AB13) -> 4.4206207
A14: A.3. Sosial
A15: 6 | B15: Perolehan Bahan Baku P-3 Kelapa Sawit | C15: S | E15: Ton | F15: 3191757 | G15: 3191757 | H15: 3259110 | I15: Maximize | J15: 8 | K15: =SUM(J15:J16) -> 16 | L15: =IFERROR(MIN(1.1*J15,(H15/G15)*J15),0) -> 8.1688175 | M15: =SUM(L15,L16) -> 16.388598 | N15: =IFERROR(MIN(1.1*J15,(H15/F15)*J15),0) -> 8.1688175 | O15: =SUM(N15,N16) -> 16.388598 | P15: =F15 -> 3191757 | Q15: =H15 -> 3259110 | R15: =J15 -> 8 | S15: =IFERROR(MAX(0,IF(I15="Minimize",F15/H15,IF(F15>0,H15/F15,IF(H15>0,1.1,F15/H15)))),0) -> 1.0211022 | T15: =MIN(1.1*R15,S15*R15) -> 8.1688175 | V15: 5 | W15: =S15 -> 1.0211022 | X15: =MIN(1.1*V15,W15*V15) -> 5.1055109 | Y15: 5 | Z15: =S15 -> 1.0211022 | AA15: =MIN(1.1*Y15,Z15*Y15) -> 5.1055109 | AB15: 5 | AC15: =S15 -> 1.0211022 | AD15: =MIN(1.1*AB15,AC15*AB15) -> 5.1055109
A16: 7 | B16: Peremajaan Sawit Rakyat Sebagai Komitmen PSN | C16: S | E16: Ha | F16: 22568 | G16: 22568 | H16: 23188 | I16: Maximize | J16: 8 | L16: =IFERROR(MIN(1.1*J16,(H16/G16)*J16),0) -> 8.2197802 | N16: =IFERROR(MIN(1.1*J16,(H16/F16)*J16),0) -> 8.2197802 | P16: =F16 -> 22568 | Q16: =H16 -> 23188 | R16: =J16 -> 8 | S16: =IFERROR(MAX(0,IF(I16="Minimize",F16/H16,IF(F16>0,H16/F16,IF(H16>0,1.1,F16/H16)))),0) -> 1.0274725 | T16: =MIN(1.1*R16,S16*R16) -> 8.2197802 | V16: 5 | W16: =S16 -> 1.0274725 | X16: =MIN(1.1*V16,W16*V16) -> 5.1373626 | Y16: 5 | Z16: =S16 -> 1.0274725 | AA16: =MIN(1.1*Y16,Z16*Y16) -> 5.1373626 | AB16: 5 | AC16: =S16 -> 1.0274725 | AD16: =MIN(1.1*AB16,AC16*AB16) -> 5.1373626
A17: B. Inovasi Model Bisnis
A18: 1 | B18: Sertifikasi RSPO | C18: E | E18: Unit | F18: 217 | G18: 217 | H18: 191 | I18: Maximize | J18: 4 | K18: =SUM(J18:J21) -> 15 | L18: =IFERROR(MIN(1.1*J18,(H18/G18)*J18),0) -> 3.5207373 | M18: =SUM(L18:L21) -> 14.920737 | N18: =IFERROR(MIN(1.1*J18,(H18/F18)*J18),0) -> 3.5207373 | O18: =SUM(N18:N21) -> 14.920737 | P18: =F18 -> 217 | Q18: =H18 -> 191 | R18: =J18 -> 4 | S18: =IFERROR(MAX(0,IF(I18="Minimize",F18/H18,IF(F18>0,H18/F18,IF(H18>0,1.1,F18/H18)))),0) -> 0.88018433 | T18: =MIN(1.1*R18,S18*R18) -> 3.5207373 | V18: 4 | W18: =S18 -> 0.88018433 | X18: =MIN(1.1*V18,W18*V18) -> 3.5207373 | Y18: 4 | Z18: =S18 -> 0.88018433 | AA18: =MIN(1.1*Y18,Z18*Y18) -> 3.5207373 | AB18: 4 | AC18: =S18 -> 0.88018433 | AD18: =MIN(1.1*AB18,AC18*AB18) -> 3.5207373
A19: 2 | B19: Total Revenue dari Pemasaran Produk | C19: C | E19: Rp Miliar | F19: 41404 | G19: 41404 | H19: 46387 | I19: Maximize | J19: 4 | L19: =IFERROR(MIN(1.1*J19,(H19/G19)*J19),0) -> 4.4 | N19: =IFERROR(MIN(1.1*J19,(H19/F19)*J19),0) -> 4.4 | P19: =F19 -> 41404 | Q19: =H19 -> 46387 | R19: =J19 -> 4 | S19: =IFERROR(MAX(0,IF(I19="Minimize",F19/H19,IF(F19>0,H19/F19,IF(H19>0,1.1,F19/H19)))),0) -> 1.1203507 | T19: =MIN(1.1*R19,S19*R19) -> 4.4 | V19: 4 | W19: =S19 -> 1.1203507 | X19: =MIN(1.1*V19,W19*V19) -> 4.4 | Y19: 4 | Z19: =S19 -> 1.1203507 | AA19: =MIN(1.1*Y19,Z19*Y19) -> 4.4 | AB19: 4 | AC19: =S19 -> 1.1203507 | AD19: =MIN(1.1*AB19,AC19*AB19) -> 4.4
A20: 3 | B20: Pengukuran Nilai Emisi Karbon | C20: E | E20: % | F20: 100 | G20: 100 | H20: 100 | I20: Maximize | J20: 3 | L20: =IFERROR(MIN(1.1*J20,(H20/G20)*J20),0) -> 3 | N20: =IFERROR(MIN(1.1*J20,(H20/F20)*J20),0) -> 3 | P20: =F20 -> 100 | Q20: =H20 -> 100 | R20: =J20 -> 3 | S20: =IFERROR(MAX(0,IF(I20="Minimize",F20/H20,IF(F20>0,H20/F20,IF(H20>0,1.1,F20/H20)))),0) -> 1 | T20: =MIN(1.1*R20,S20*R20) -> 3 | V20: 3 | W20: =S20 -> 1 | X20: =MIN(1.1*V20,W20*V20) -> 3 | Y20: 3 | Z20: =S20 -> 1 | AA20: =MIN(1.1*Y20,Z20*Y20) -> 3 | AB20: 3 | AC20: =S20 -> 1 | AD20: =MIN(1.1*AB20,AC20*AB20) -> 3
A21: 4 | B21: Implementasi Post Merger Integration | C21: C | E21: % | F21: 100 | G21: 100 | H21: 100 | I21: Maximize | J21: 4 | L21: =IFERROR(MIN(1.1*J21,(H21/G21)*J21),0) -> 4 | N21: =IFERROR(MIN(1.1*J21,(H21/F21)*J21),0) -> 4 | P21: =F21 -> 100 | Q21: =H21 -> 100 | R21: =J21 -> 4 | S21: =IFERROR(MAX(0,IF(I21="Minimize",F21/H21,IF(F21>0,H21/F21,IF(H21>0,1.1,F21/H21)))),0) -> 1 | T21: =MIN(1.1*R21,S21*R21) -> 4 | V21: 4 | W21: =S21 -> 1 | X21: =MIN(1.1*V21,W21*V21) -> 4 | Y21: 4 | Z21: =S21 -> 1 | AA21: =MIN(1.1*Y21,Z21*Y21) -> 4 | AB21: 4 | AC21: =S21 -> 1 | AD21: =MIN(1.1*AB21,AC21*AB21) -> 4
A22: C. Kepemimpinan Teknologi
A23: 1 | B23: Implementasi RSTI 2025 | C23: C | E23: % | F23: 100 | G23: 100 | H23: 100 | I23: Maximize | J23: 8 | K23: =J23 -> 8 | L23: =IFERROR(MIN(1.1*J23,(H23/G23)*J23),0) -> 8 | M23: =SUM(L23) -> 8 | N23: =IFERROR(MIN(1.1*J23,(H23/F23)*J23),0) -> 8 | O23: =SUM(N23) -> 8 | P23: =F23 -> 100 | Q23: =H23 -> 100 | R23: =J23 -> 8 | S23: =IFERROR(MAX(0,IF(I23="Minimize",F23/H23,IF(F23>0,H23/F23,IF(H23>0,1.1,F23/H23)))),0) -> 1 | T23: =MIN(1.1*R23,S23*R23) -> 8 | V23: 10 | W23: =S23 -> 1 | X23: =MIN(1.1*V23,W23*V23) -> 10 | Y23: 10 | Z23: =S23 -> 1 | AA23: =MIN(1.1*Y23,Z23*Y23) -> 10 | AB23: 10 | AC23: =S23 -> 1 | AD23: =MIN(1.1*AB23,AC23*AB23) -> 10
A24: D. Peningkatan Investasi
A25: 1 | B25: Replanting & Konversi | C25: C | E25: Ha | F25: 21443.16 | G25: 21443.16 | H25: 20397.99 | I25: Maximize | J25: 8 | K25: =SUM(J25:J26) -> 15 | L25: =IFERROR(MIN(1.1*J25,(H25/G25)*J25),0) -> 7.6100687 | M25: =SUM(L25:L26) -> 7.6100687 | N25: =IFERROR(MIN(1.1*J25,(H25/F25)*J25),0) -> 7.6100687 | O25: =SUM(N25:N26) -> 7.6100687 | P25: =F25 -> 21443.16 | Q25: =H25 -> 20397.99 | R25: =J25 -> 8 | S25: =IFERROR(MAX(0,IF(I25="Minimize",F25/H25,IF(F25>0,H25/F25,IF(H25>0,1.1,F25/H25)))),0) -> 0.95125858 | T25: =MIN(1.1*R25,S25*R25) -> 7.6100687 | V25: 8 | W25: =S25 -> 0.95125858 | X25: =MIN(1.1*V25,W25*V25) -> 7.6100687 | Y25: 8 | Z25: =S25 -> 0.95125858 | AA25: =MIN(1.1*Y25,Z25*Y25) -> 7.6100687 | AB25: 8 | AC25: =S25 -> 0.95125858 | AD25: =MIN(1.1*AB25,AC25*AB25) -> 7.6100687
A26: 2 | B26: Pembangunan Pabrik Pengolahan Inti Sawit | C26: C | E26: Waktu | F26: Triwulan II | G26: Triwulan II | H26: 0 | I26: Maximize | J26: 7 | L26: =IFERROR(MIN(1.1*J26,(H26/G26)*J26),0) -> 0 | N26: =IFERROR(MIN(1.1*J26,(H25/F26)*J26),0) -> 0 | P26: =F26 -> Triwulan II | Q26: =H26 -> 0 | R26: =J26 -> 7 | V26: 7 | W26: =S26 -> 0 | X26: =MIN(1.1*V26,W26*V26) -> 0 | Y26: 7 | Z26: =S26 -> 0 | AA26: =MIN(1.1*Y26,Z26*Y26) -> 0 | AB26: 7 | AC26: =S26 -> 0 | AD26: =MIN(1.1*AB26,AC26*AB26) -> 0
A27: E. Pengembangan Talenta
A28: 1 | B28: Human Capital Transformation | C28: S | E28: % | F28: 100 | G28: 100 | H28: 116.68 | I28: Maximize | J28: 8 | K28: =J28 -> 8 | L28: =IFERROR(MIN(1.1*J28,(H28/G28)*J28),0) -> 8.8 | M28: =SUM(L28) -> 8.8 | N28: =IFERROR(MIN(1.1*J28,(H28/F28)*J28),0) -> 8.8 | O28: =SUM(N28) -> 8.8 | P28: =F28 -> 100 | Q28: =H28 -> 116.68 | R28: =J28 -> 8 | S28: =IFERROR(MAX(0,IF(I28="Minimize",F28/H28,IF(F28>0,H28/F28,IF(H28>0,1.1,F28/H28)))),0) -> 1.1668 | T28: =MIN(1.1*R28,S28*R28) -> 8.8 | V28: 10 | W28: =S28 -> 1.1668 | X28: =MIN(1.1*V28,W28*V28) -> 11 | Y28: 10 | Z28: =S28 -> 1.1668 | AA28: =MIN(1.1*Y28,Z28*Y28) -> 11 | AB28: 10 | AC28: =S28 -> 1.1668 | AD28: =MIN(1.1*AB28,AC28*AB28) -> 11
B29: TOTAL | K29: =SUM(K8,K12,K15,K18,K23,K25,K28) -> 100 | M29: =SUM(M8,M12,M15,M18,M23,M25,M28) -> 89.373244 | O29: =SUM(O8:O28) -> 89.373244 | R29: =SUM(R5:R28) -> 100 | S29: =IFERROR(T29/R29,0) -> 0.94373244 | T29: =SUM(T5:T28) -> 94.373244 | V29: =SUM(V8:V28) -> 100 | W29: =IFERROR(X29/V29,0) -> 0.9462752 | X29: =SUM(X8:X28) -> 94.62752 | Y29: =SUM(Y8:Y28) -> 100 | Z29: =IFERROR(AA29/Y29,0) -> 0.9350444 | AA29: =SUM(AA8:AA28) -> 93.50444 | AB29: =SUM(AB8:AB28) -> 100 | AC29: =IFERROR(AD29/AB29,0) -> 0.956506 | AD29: =SUM(AD8:AD28) -> 95.6506

Sheet PTPN IV DIR
A1: KOLEGIAL
A2: No | B2: Key Performance Indicator | C2: Satuan | D2: Target | E2: Polaritas | F2: Bobot | G2: Total Bobot | H2: Realisasi | I2: Capaian | J2: Skor | K2: Total Skor | M2: Target 2025 | N2: Realisasi 2025 | O2: Bobot KPI | P2: % Capaian Realisasi | Q2: Skor Realisasi KPI
A3: A | B3: Nilai Ekonomi dan Sosial Untuk Indonesia
A4: A.1 | B4: Finansial
A5: 1 | B5: EBITDA Margin | C5: % | D5: 21.92 | E5: Maximize | F5: 8 | G5: 18 | H5: 26.15 | I5: 1.193 | J5: 8.8 | K5: 14.3 | M5: =D5 -> 21.92 | N5: =H5 -> 26.15 | O5: =F5 -> 8 | P5: =I5 -> 1.193 | Q5: =MAX(0,MIN(1.1*O5,P5*O5)) -> 8.8
A6: 2 | B6: ROIC >= WACC | C6: % | D6: 3.82 | E6: Maximize | F6: 5 | H6: 9.72 | I6: 2.5453 | J6: 5.5 | M6: =D6 -> 3.82 | N6: =H6 -> 9.72 | O6: =F6 -> 5 | P6: =I6 -> 2.5453 | Q6: =MAX(0,MIN(1.1*O6,P6*O6)) -> 5.5
A7: 3 | B7: Penyampaian LAI Tahun 2025 | C7: Waktu | D7: 31/03/2025 | E7: Minimize | F7: 5 | H7: 0 | I7: 0 | J7: 0 | M7: =D7 -> 31/03/2025 | N7: =H7 -> 0 | O7: =F7 -> 5 | P7: =I7 -> 0 | Q7: =MAX(0,MIN(1.1*O7,P7*O7)) -> 0
A8: A.2 | B8: Operasional
A9: 4 | B9: Cash Cost Kelapa Sawit | C9: Rp/Kg | D9: 4630.8 | E9: Minimize | F9: 10 | G9: 20 | H9: 4405 | I9: 1.0513 | J9: 10.51 | K9: 19.35 | M9: =D9 -> 4630.8 | N9: =H9 -> 4405 | O9: =F9 -> 10 | P9: =I9 -> 1.0513 | Q9: =MAX(0,MIN(1.1*O9,P9*O9)) -> 10.513
A10: 5 | B10: Produktivitas CPO | C10: Ton/Ha | D10: 5.43 | E10: Maximize | F10: 10 | H10: 4.8 | I10: 0.8841 | J10: 8.84 | M10: =D10 -> 5.43 | N10: =H10 -> 4.8 | O10: =F10 -> 10 | P10: =I10 -> 0.8841 | Q10: =MAX(0,MIN(1.1*O10,P10*O10)) -> 8.841
A11: A.3 | B11: Sosial
A12: 6 | B12: Perolehan Bahan Baku P-3 Kelapa Sawit | C12: Ton | D12: 3191757 | E12: Maximize | F12: 8 | G12: 16 | H12: 3259110 | I12: 1.0211 | J12: 8.17 | K12: 16.39 | M12: =D12 -> 3191757 | N12: =H12 -> 3259110 | O12: =F12 -> 8 | P12: =I12 -> 1.0211 | Q12: =MAX(0,MIN(1.1*O12,P12*O12)) -> 8.1688
A13: 7 | B13: Peremajaan Sawit Rakyat Sebagai Komitmen PSN | C13: Ha | D13: 22568 | E13: Maximize | F13: 8 | H13: 23188 | I13: 1.0275 | J13: 8.22 | M13: =D13 -> 22568 | N13: =H13 -> 23188 | O13: =F13 -> 8 | P13: =I13 -> 1.0275 | Q13: =MAX(0,MIN(1.1*O13,P13*O13)) -> 8.22
A14: B | B14: Inovasi Model Bisnis
A15: 1 | B15: Sertifikasi RSPO | C15: Unit | D15: 217 | E15: Maximize | F15: 4 | G15: 15 | H15: 191 | I15: 0.8802 | J15: 3.52 | K15: 14.92 | M15: =D15 -> 217 | N15: =H15 -> 191 | O15: =F15 -> 4 | P15: =I15 -> 0.8802 | Q15: =MAX(0,MIN(1.1*O15,P15*O15)) -> 3.5208
A16: 2 | B16: Total Revenue dari Pemasaran Produk | C16: Rp Miliar | D16: 41404 | E16: Maximize | F16: 4 | H16: 46387 | I16: 1.1203 | J16: 4.4 | M16: =D16 -> 41404 | N16: =H16 -> 46387 | O16: =F16 -> 4 | P16: =I16 -> 1.1203 | Q16: =MAX(0,MIN(1.1*O16,P16*O16)) -> 4.4
A17: 3 | B17: Pengukuran Nilai Emisi Karbon | C17: % | D17: 100 | E17: Maximize | F17: 3 | H17: 100 | I17: 1 | J17: 3 | M17: =D17 -> 100 | N17: =H17 -> 100 | O17: =F17 -> 3 | P17: =I17 -> 1 | Q17: =MAX(0,MIN(1.1*O17,P17*O17)) -> 3
A18: 4 | B18: Implementasi Post Merger Integration | C18: % | D18: 100 | E18: Maximize | F18: 4 | H18: 100 | I18: 1 | J18: 4 | M18: =D18 -> 100 | N18: =H18 -> 100 | O18: =F18 -> 4 | P18: =I18 -> 1 | Q18: =MAX(0,MIN(1.1*O18,P18*O18)) -> 4
A19: C | B19: Kepemimpinan Teknologi
A20: 1 | B20: Implementasi RSTI 2025 | C20: % | D20: 100 | E20: Maximize | F20: 8 | G20: 8 | H20: 110 | I20: 1.1 | J20: 8.8 | K20: 8.8 | M20: =D20 -> 100 | N20: =H20 -> 110 | O20: =F20 -> 8 | P20: =I20 -> 1.1 | Q20: =MAX(0,MIN(1.1*O20,P20*O20)) -> 8.8
A21: D | B21: Peningkatan Investasi
A22: 1 | B22: Replanting & Konversi | C22: Ha | D22: 21443.16 | E22: Maximize | F22: 8 | G22: 15 | H22: 20397.99 | I22: 0.9513 | J22: 7.61 | K22: 7.61 | M22: =D22 -> 21443.16 | N22: =H22 -> 20397.99 | O22: =F22 -> 8 | P22: =I22 -> 0.9513 | Q22: =MAX(0,MIN(1.1*O22,P22*O22)) -> 7.6104
A23: 2 | B23: Pembangunan Pabrik Pengolahan Inti Sawit | C23: Waktu | D23: Triwulan II | E23: Maximize | F23: 7 | H23: 0 | I23: 0 | J23: 0 | K23: 0 | M23: =D23 -> Triwulan II | N23: =H23 -> 0 | O23: =F23 -> 7 | P23: =I23 -> 0 | Q23: =MAX(0,MIN(1.1*O23,P23*O23)) -> 0
A24: E | B24: Pengembangan Talenta
A25: 1 | B25: Human Capital Transformation | C25: % | D25: 100 | E25: Maximize | F25: 8 | G25: 8 | H25: 105.41 | I25: 1.0541 | J25: 8.43 | K25: 8.43 | M25: =D25 -> 100 | N25: =H25 -> 105.41 | O25: =F25 -> 8 | P25: =I25 -> 1.0541 | Q25: =MAX(0,MIN(1.1*O25,P25*O25)) -> 8.4328
A26: TOTAL | F26: 100 | G26: 100 | K26: 89.8 | O26: =SUM(O5:O25) -> 100 | P26: =IFERROR(Q26/O26,0) -> 0.898068 | Q26: =SUM(Q5:Q25) -> 89.8068
A29: DIR. OPERASIONAL
A30: No | B30: Key Performance Indicator | C30: Satuan | D30: Target | E30: Polaritas | F30: Bobot | G30: Total Bobot | H30: Realisasi | I30: Capaian | J30: Skor | K30: Total Skor | M30: Target 2025 | N30: Realisasi 2025 | O30: Bobot KPI | P30: % Capaian Realisasi | Q30: Skor Realisasi KPI
A31: A | B31: KPI Bersama
A32: 1 | B32: EBITDA Margin | C32: % | D32: 21.92 | E32: Maximize | F32: 20 | G32: 40 | H32: 26.15 | I32: 1.193 | J32: 22 | K32: 33 | M32: =D32 -> 21.92 | N32: =H32 -> 26.15 | O32: =F32 -> 20 | P32: =I32 -> 1.193 | Q32: =MAX(0,MIN(1.1*O32,P32*O32)) -> 22
A33: 2 | B33: ROIC >= WACC | C33: % | D33: 3.82 | E33: Maximize | F33: 10 | H33: 9.72 | I33: 2.5445 | J33: 11 | M33: =D33 -> 3.82 | N33: =H33 -> 9.72 | O33: =F33 -> 10 | P33: =I33 -> 2.5445 | Q33: =MAX(0,MIN(1.1*O33,P33*O33)) -> 11
A34: 3 | B34: Penyampaian LAI Tahun 2024 | C34: Waktu | D34: 31/03/2025 | E34: Minimize | F34: 10 | H34: 0 | I34: 0 | J34: 0 | M34: =D34 -> 31/03/2025 | N34: =H34 -> 0 | O34: =F34 -> 10 | P34: =I34 -> 0 | Q34: =MAX(0,MIN(1.1*O34,P34*O34)) -> 0
A35: B | B35: KPI Direktorat
A36: 1 | B36: Cash Cost
B37: - Cash Cost Kelapa Sawit | C37: Rp/Kg | D37: 4630.8 | E37: Minimize | F37: 4 | G37: 16 | H37: 4405 | I37: 1.0513 | J37: 4.21 | K37: 14.34 | M37: =D37 -> 4630.8 | N37: =H37 -> 4405 | O37: =F37 -> 4 | P37: =I37 -> 1.0513 | Q37: =MAX(0,MIN(1.1*O37,P37*O37)) -> 4.2052
B38: - Cash Cost Karet | C38: Rp/Kg | D38: 15786.19 | E38: Minimize | F38: 4 | H38: 21357 | I38: 0.7392 | J38: 2.96 | M38: =D38 -> 15786.19 | N38: =H38 -> 21357 | O38: =F38 -> 4 | P38: =I38 -> 0.7392 | Q38: =MAX(0,MIN(1.1*O38,P38*O38)) -> 2.9568
B39: - Cash Cost Teh | C39: Rp/Kg | D39: 16584.7 | E39: Minimize | F39: 4 | H39: 18206 | I39: 0.9109 | J39: 3.64 | M39: =D39 -> 16584.7 | N39: =H39 -> 18206 | O39: =F39 -> 4 | P39: =I39 -> 0.9109 | Q39: =MAX(0,MIN(1.1*O39,P39*O39)) -> 3.6436
B40: - Cash Cost Kopi | C40: Rp/Kg | D40: 68842.65 | E40: Minimize | F40: 4 | H40: 78065 | I40: 0.8819 | J40: 3.53 | M40: =D40 -> 68842.65 | N40: =H40 -> 78065 | O40: =F40 -> 4 | P40: =I40 -> 0.8819 | Q40: =MAX(0,MIN(1.1*O40,P40*O40)) -> 3.5276
A41: 2 | B41: Produktivitas
B42: - Produktivitas CPO | C42: Ton/Ha | D42: 5.43 | E42: Maximize | F42: 4 | G42: 34 | H42: 4.8 | I42: 0.884 | J42: 3.54 | K42: 38.92 | M42: =D42 -> 5.43 | N42: =H42 -> 4.8 | O42: =F42 -> 4 | P42: =I42 -> 0.884 | Q42: =MAX(0,MIN(1.1*O42,P42*O42)) -> 3.536
B43: - Produktivitas Karet Kering | C43: Ton/Ha | D43: 1.3 | E43: Maximize | F43: 4 | H43: 0.84 | I43: 0.6772 | J43: 2.71 | M43: =D43 -> 1.3 | N43: =H43 -> 0.84 | O43: =F43 -> 4 | P43: =I43 -> 0.6772 | Q43: =MAX(0,MIN(1.1*O43,P43*O43)) -> 2.7088
B44: - Produktivitas Teh Kering | C44: Ton/Ha | D44: 2.95 | E44: Maximize | F44: 4 | H44: 2.28 | I44: 0.7719 | J44: 3.09 | M44: =D44 -> 2.95 | N44: =H44 -> 2.28 | O44: =F44 -> 4 | P44: =I44 -> 0.7719 | Q44: =MAX(0,MIN(1.1*O44,P44*O44)) -> 3.0876
B45: - Produktivitas Kopi | C45: Ton/Ha | D45: 0.49 | E45: Maximize | F45: 4 | H45: 0.38 | I45: 0.7642 | J45: 3.06 | M45: =D45 -> 0.49 | N45: =H45 -> 0.38 | O45: =F45 -> 4 | P45: =I45 -> 0.7642 | Q45: =MAX(0,MIN(1.1*O45,P45*O45)) -> 3.0568
A46: 3 | B46: Pengukuran Nilai Emisi Karbon | C46: % | D46: 100 | E46: Maximize | F46: 4 | H46: 100 | I46: 1 | J46: 4 | M46: =D46 -> 100 | N46: =H46 -> 100 | O46: =F46 -> 4 | P46: =I46 -> 1 | Q46: =MAX(0,MIN(1.1*O46,P46*O46)) -> 4
A47: 4 | B47: Implementasi RSTI 2025 | C47: % | D47: 100 | E47: Maximize | F47: 4 | H47: 110 | I47: 1.1 | J47: 4.4 | M47: =D47 -> 100 | N47: =H47 -> 110 | O47: =F47 -> 4 | P47: =I47 -> 1.1 | Q47: =MAX(0,MIN(1.1*O47,P47*O47)) -> 4.4
A48: 5 | B48: Replanting & Konversi | C48: Ha | D48: 21443.16 | E48: Maximize | F48: 4 | H48: 20397.99 | I48: 0.9513 | J48: 3.81 | M48: =D48 -> 21443.16 | N48: =H48 -> 20397.99 | O48: =F48 -> 4 | P48: =I48 -> 0.9513 | Q48: =MAX(0,MIN(1.1*O48,P48*O48)) -> 3.8052
A49: 6 | B49: Human Capital Transformation | C49: Ton/Orang | D49: 39.47 | E49: Maximize | F49: 4 | H49: 44 | I49: 1.1148 | J49: 4.4 | M49: =D49 -> 39.47 | N49: =H49 -> 44 | O49: =F49 -> 4 | P49: =I49 -> 1.1148 | Q49: =MAX(0,MIN(1.1*O49,P49*O49)) -> 4.4
A50: 7 | B50: Value Impact Operational Excellence-CPO | C50: Rp. Miliar | D50: 4189 | E50: Maximize | F50: 4 | H50: 1162 | I50: 0.2774 | J50: 1.11 | M50: =D50 -> 4189 | N50: =H50 -> 1162 | O50: =F50 -> 4 | P50: =I50 -> 0.2774 | Q50: =MAX(0,MIN(1.1*O50,P50*O50)) -> 1.1096
A51: 8 | B51: Value Impact Operational Excellence-PKO | C51: Rp. Miliar | D51: 257 | E51: Maximize | F51: 4 | H51: 310 | I51: 1.2062 | J51: 4.4 | M51: =D51 -> 257 | N51: =H51 -> 310 | O51: =F51 -> 4 | P51: =I51 -> 1.2062 | Q51: =MAX(0,MIN(1.1*O51,P51*O51)) -> 4.4
A52: 9 | B52: Value Impact Cash Cost Optimization | C52: Rp. Miliar | D52: 290.76 | E52: Maximize | F52: 4 | H52: 2000 | I52: 6.8785 | J52: 4.4 | M52: =D52 -> 290.76 | N52: =H52 -> 2000 | O52: =F52 -> 4 | P52: =I52 -> 6.8785 | Q52: =MAX(0,MIN(1.1*O52,P52*O52)) -> 4.4
A53: TOTAL | G53: 100 | K53: 86.26 | O53: =SUM(O32:O52) -> 100 | P53: =IFERROR(Q53/O53,0) -> 0.862372 | Q53: =SUM(Q32:Q52) -> 86.2372
A56: DIR. PEMASARAN
A57: No | B57: Key Performance Indicator | C57: Satuan | D57: Target | E57: Polaritas | F57: Bobot | G57: Total Bobot | H57: Realisasi | I57: Capaian | J57: Skor | K57: Total Skor | M57: Target 2025 | N57: Realisasi 2025 | O57: Bobot KPI | P57: % Capaian Realisasi | Q57: Skor Realisasi KPI
A58: A | B58: KPI Bersama
A59: 1 | B59: EBITDA Margin | C59: % | D59: 21.92 | E59: Maximize | F59: 20 | G59: 40 | H59: 26.15 | I59: 1.193 | J59: 22 | K59: 33 | M59: =D59 -> 21.92 | N59: =H59 -> 26.15 | O59: =F59 -> 20 | P59: =I59 -> 1.193 | Q59: =MAX(0,MIN(1.1*O59,P59*O59)) -> 22
A60: 2 | B60: ROIC >= WACC | C60: % | D60: 3.82 | E60: Maximize | F60: 10 | H60: 9.72 | I60: 2.5445 | J60: 11 | M60: =D60 -> 3.82 | N60: =H60 -> 9.72 | O60: =F60 -> 10 | P60: =I60 -> 2.5445 | Q60: =MAX(0,MIN(1.1*O60,P60*O60)) -> 11
A61: 3 | B61: Penyampaian LAI Tahun 2024 | C61: Waktu | D61: 31/03/2025 | E61: Minimize | F61: 10 | H61: 0 | I61: 0 | J61: 0 | M61: =D61 -> 31/03/2025 | N61: =H61 -> 0 | O61: =F61 -> 10 | P61: =I61 -> 0 | Q61: =MAX(0,MIN(1.1*O61,P61*O61)) -> 0
A62: B | B62: KPI Direktorat
A63: 1 | B63: Capaian Nilai Penjualan Produk Komoditi Kelapa Sawit, Karet,Kopi dan Teh | C63: Rp. Miliar | D63: 41388 | E63: Maximize | F63: 8 | G63: 60 | H63: 45990.6 | I63: 1.1112 | J63: 8.8 | K63: 63.56 | M63: =D63 -> 41388 | N63: =H63 -> 45990.6 | O63: =F63 -> 8 | P63: =I63 -> 1.1112 | Q63: =MAX(0,MIN(1.1*O63,P63*O63)) -> 8.8
A64: 2 | B64: Capaian nilai penjualan produk retail Teh | C64: Rp. Miliar | D64: 15.81 | E64: Maximize | F64: 7 | H64: 13.47 | I64: 0.852 | J64: 5.96 | M64: =D64 -> 15.81 | N64: =H64 -> 13.47 | O64: =F64 -> 7 | P64: =I64 -> 0.852 | Q64: =MAX(0,MIN(1.1*O64,P64*O64)) -> 5.964
A65: 3 | B65: Implementasi RSTI 2025 | C65: % | D65: 100 | E65: Maximize | F65: 6 | H65: 110 | I65: 1.1 | J65: 6.6 | M65: =D65 -> 100 | N65: =H65 -> 110 | O65: =F65 -> 6 | P65: =I65 -> 1.1 | Q65: =MAX(0,MIN(1.1*O65,P65*O65)) -> 6.6
A66: 4 | B66: Peningkatan OTIF penyerahan produk kepada Buyer | C66: % | D66: 85 | E66: Maximize | F66: 6 | H66: 92.16 | I66: 1.0842 | J66: 6.51 | M66: =D66 -> 85 | N66: =H66 -> 92.16 | O66: =F66 -> 6 | P66: =I66 -> 1.0842 | Q66: =MAX(0,MIN(1.1*O66,P66*O66)) -> 6.5052
A67: 5 | B67: Efesiensi Nilai SPPBJ dibandingkan HPS | C67: % | D67: 3 | E67: Maximize | F67: 6 | H67: 4.84 | I67: 1.6133 | J67: 6.6 | M67: =D67 -> 3 | N67: =H67 -> 4.84 | O67: =F67 -> 6 | P67: =I67 -> 1.6133 | Q67: =MAX(0,MIN(1.1*O67,P67*O67)) -> 6.6
A68: 6 | B68: Penggunaan Produk Dalam Negeri (PDN) PTPN Group | C68: Rp Triliun | D68: 93 | E68: Maximize | F68: 6 | H68: 10.27 | I68: 1.1043 | J68: 6.6 | M68: =D68 -> 93 | N68: =H68 -> 10.27 | O68: =F68 -> 6 | P68: =I68 -> 1.1043 | Q68: =MAX(0,MIN(1.1*O68,P68*O68)) -> 6.6
A69: 7 | B69: Transaksi Pengadaan Barang/Jasa dengan Penyedia UMKM melalui PaDi UMKM | C69: Rp. Miliar | D69: 90 | E69: Maximize | F69: 7 | H69: 224.78 | I69: 2.4976 | J69: 7.7 | M69: =D69 -> 90 | N69: =H69 -> 224.78 | O69: =F69 -> 7 | P69: =I69 -> 2.4976 | Q69: =MAX(0,MIN(1.1*O69,P69*O69)) -> 7.7
A70: 8 | B70: Value Impact Revenue Enhancement | C70: Rp. Miliar | D70: 190.8 | E70: Maximize | F70: 7 | H70: 228 | I70: 1.195 | J70: 7.7 | M70: =D70 -> 190.8 | N70: =H70 -> 228 | O70: =F70 -> 7 | P70: =I70 -> 1.195 | Q70: =MAX(0,MIN(1.1*O70,P70*O70)) -> 7.7
A71: 9 | B71: Value Impact Procurement Excellence | C71: Rp. Miliar | D71: 222.2 | E71: Maximize | F71: 7 | H71: 225.16 | I71: 1.0133 | J71: 7.09 | M71: =D71 -> 222.2 | N71: =H71 -> 225.16 | O71: =F71 -> 7 | P71: =I71 -> 1.0133 | Q71: =MAX(0,MIN(1.1*O71,P71*O71)) -> 7.0931
A72: TOTAL | F72: 100 | G72: 100 | K72: 96.56 | O72: =SUM(O59:O71) -> 100 | P72: =IFERROR(Q72/O72,0) -> 0.965623 | Q72: =SUM(Q59:Q71) -> 96.5623
A75: DIR. STRATEGY
A76: No | B76: Key Performance Indicator | C76: Satuan | D76: Target | E76: Polaritas | F76: Bobot | G76: Total Bobot | H76: Realisasi | I76: Capaian | J76: Skor | K76: Total Skor | M76: Target 2025 | N76: Realisasi 2025 | O76: Bobot KPI | P76: % Capaian Realisasi | Q76: Skor Realisasi KPI
A77: A. | B77: KPI Bersama
A78: 1 | B78: EBITDA Margin | C78: % | D78: 21.92 | E78: Maximize | F78: 20 | G78: 40 | H78: 26.15 | I78: 1.193 | J78: 22 | K78: 33 | M78: =D78 -> 21.92 | N78: =H78 -> 26.15 | O78: =F78 -> 20 | P78: =I78 -> 1.193 | Q78: =MAX(0,MIN(1.1*O78,P78*O78)) -> 22
A79: 2 | B79: ROIC >= WACC | C79: % | D79: 3.82 | E79: Maximize | F79: 10 | H79: 9.72 | I79: 2.5453 | J79: 11 | M79: =D79 -> 3.82 | N79: =H79 -> 9.72 | O79: =F79 -> 10 | P79: =I79 -> 2.5453 | Q79: =MAX(0,MIN(1.1*O79,P79*O79)) -> 11
A80: 3 | B80: Penyampaian LAI Tahun 2024 | C80: Waktu | D80: 31/03/2025 | E80: Minimize | F80: 10 | H80: 0 | I80: 0 | J80: 0 | M80: =D80 -> 31/03/2025 | N80: =H80 -> 0 | O80: =F80 -> 10 | P80: =I80 -> 0 | Q80: =MAX(0,MIN(1.1*O80,P80*O80)) -> 0
A81: B | B81: KPI Direktorat
A82: 1 | B82: Sertifikasi RSPO | C82: Unit | D82: 217 | E82: Maximize | F82: 6 | G82: 60 | H82: 191 | I82: 0.8802 | J82: 5.28 | K82: 52.4 | M82: =D82 -> 217 | N82: =H82 -> 191 | O82: =F82 -> 6 | P82: =I82 -> 0.8802 | Q82: =MAX(0,MIN(1.1*O82,P82*O82)) -> 5.2812
A83: 2 | B83: Pengukuran Nilai Emisi Karbon | C83: % | D83: 100 | E83: Maximize | F83: 6 | H83: 100 | I83: 1 | J83: 6 | M83: =D83 -> 100 | N83: =H83 -> 100 | O83: =F83 -> 6 | P83: =I83 -> 1 | Q83: =MAX(0,MIN(1.1*O83,P83*O83)) -> 6
A84: 3 | B84: Pembangunan Pabrik Pengolahan Inti Sawit | C84: Waktu | D84: TW II | E84: Maximize | F84: 7 | H84: 0 | I84: 0 | J84: 0 | M84: =D84 -> TW II | N84: =H84 -> 0 | O84: =F84 -> 7 | P84: =I84 -> 0 | Q84: =MAX(0,MIN(1.1*O84,P84*O84)) -> 0
A85: 4 | B85: Pelaksanaan Jumlah Proyek riset Pengembangan dan Riset On Farm/Off Farm/Produk baru | C85: Jumlah | D85: 5 | E85: Maximize | F85: 6 | H85: 5 | I85: 1 | J85: 6 | M85: =D85 -> 5 | N85: =H85 -> 5 | O85: =F85 -> 6 | P85: =I85 -> 1 | Q85: =MAX(0,MIN(1.1*O85,P85*O85)) -> 6
A86: 5 | B86: Pelaksanaan Jumlah Proyek riset Pengembangan dan Riset On Farm/Off Farm/Produk yang didukung | C86: Jumlah | D86: 10 | E86: Maximize | F86: 6 | H86: 11 | I86: 1.1 | J86: 6.6 | M86: =D86 -> 10 | N86: =H86 -> 11 | O86: =F86 -> 6 | P86: =I86 -> 1.1 | Q86: =MAX(0,MIN(1.1*O86,P86*O86)) -> 6.6
A87: 6 | B87: Implementasi Program Penyehatan Anak Perusahaan PTPN IV | C87: % | D87: 100 | E87: Maximize | F87: 7 | H87: 100 | I87: 1 | J87: 7 | M87: =D87 -> 100 | N87: =H87 -> 100 | O87: =F87 -> 7 | P87: =I87 -> 1 | Q87: =MAX(0,MIN(1.1*O87,P87*O87)) -> 7
A88: 7 | B88: Pengembangan Energi Baru Terbarukan (EBT) | C88: % | D88: 100 | E88: Maximize | F88: 7 | H88: 100 | I88: 1 | J88: 7 | M88: =D88 -> 100 | N88: =H88 -> 100 | O88: =F88 -> 7 | P88: =I88 -> 1 | Q88: =MAX(0,MIN(1.1*O88,P88*O88)) -> 7
A89: 8 | B89: Optimalisasi Aset | C89: Rp. Miliar | D89: 40.98 | E89: Maximize | F89: 7 | H89: 61.3 | I89: 1.4959 | J89: 7.7 | M89: =D89 -> 40.98 | N89: =H89 -> 61.3 | O89: =F89 -> 7 | P89: =I89 -> 1.4959 | Q89: =MAX(0,MIN(1.1*O89,P89*O89)) -> 7.7
A90: 9 | B90: Value Impact Business Turnaround | C90: Rp. Miliar | D90: 184.7 | E90: Maximize | F90: 8 | H90: 157.4 | I90: 0.8522 | J90: 6.82 | M90: =D90 -> 184.7 | N90: =H90 -> 157.4 | O90: =F90 -> 8 | P90: =I90 -> 0.8522 | Q90: =MAX(0,MIN(1.1*O90,P90*O90)) -> 6.8176
A91: TOTAL | F91: 100 | G91: 100 | K91: 85.4 | O91: =SUM(O78:O90) -> 100 | P91: =IFERROR(Q91/O91,0) -> 0.853988 | Q91: =SUM(Q78:Q90) -> 85.3988
A94: DIR. KEUANGAN
A95: No | B95: Key Performance Indicator | C95: Satuan | D95: Target | E95: Polaritas | F95: Bobot | G95: Total Bobot | H95: Realisasi | I95: Capaian | J95: Skor | K95: Total Skor | M95: Target 2025 | N95: Realisasi 2025 | O95: Bobot KPI | P95: % Capaian Realisasi | Q95: Skor Realisasi KPI
A96: A | B96: KPI Bersama
A97: 1 | B97: EBITDA Margin | C97: % | D97: 21.92 | E97: Maximize | F97: 20 | G97: 40 | H97: 26.15 | I97: 1.193 | J97: 22 | K97: 33 | M97: =D97 -> 21.92 | N97: =H97 -> 26.15 | O97: =F97 -> 20 | P97: =I97 -> 1.193 | Q97: =MAX(0,MIN(1.1*O97,P97*O97)) -> 22
A98: 2 | B98: ROIC >= WACC | C98: % | D98: 3.82 | E98: Maximize | F98: 10 | H98: 9.72 | I98: 2.5445 | J98: 11 | M98: =D98 -> 3.82 | N98: =H98 -> 9.72 | O98: =F98 -> 10 | P98: =I98 -> 2.5445 | Q98: =MAX(0,MIN(1.1*O98,P98*O98)) -> 11
A99: 3 | B99: Penyampaian LAI Tahun 2024 | C99: Waktu | D99: 31/03/2025 | E99: Minimize | F99: 10 | H99: 0 | I99: 0 | J99: 0 | M99: =D99 -> 31/03/2025 | N99: =H99 -> 0 | O99: =F99 -> 10 | P99: =I99 -> 0 | Q99: =MAX(0,MIN(1.1*O99,P99*O99)) -> 0
A100: B | B100: KPI Direktorat
A101: 1 | B101: Cash Cost
B102: - Cash Cost Kelapa Sawit | C102: Rp/Kg | D102: 4630.8 | E102: Minimize | F102: 5 | G102: 60 | H102: 4405 | I102: 1.0513 | J102: 5.26 | K102: 60.89 | M102: =D102 -> 4630.8 | N102: =H102 -> 4405 | O102: =F102 -> 5 | P102: =I102 -> 1.0513 | Q102: =MAX(0,MIN(1.1*O102,P102*O102)) -> 5.2565
B103: - Cash Cost Karet | C103: Rp/Kg | D103: 15786.19 | E103: Minimize | F103: 4 | H103: 21357 | I103: 0.7392 | J103: 2.96 | M103: =D103 -> 15786.19 | N103: =H103 -> 21357 | O103: =F103 -> 4 | P103: =I103 -> 0.7392 | Q103: =MAX(0,MIN(1.1*O103,P103*O103)) -> 2.9568
B104: - Cash Cost Teh | C104: Rp/Kg | D104: 16584.7 | E104: Minimize | F104: 4 | H104: 18206 | I104: 0.9109 | J104: 3.64 | M104: =D104 -> 16584.7 | N104: =H104 -> 18206 | O104: =F104 -> 4 | P104: =I104 -> 0.9109 | Q104: =MAX(0,MIN(1.1*O104,P104*O104)) -> 3.6436
B105: - Cash Cost Kopi | C105: Rp/Kg | D105: 68842.65 | E105: Minimize | F105: 4 | H105: 78065 | I105: 0.8819 | J105: 3.53 | M105: =D105 -> 68842.65 | N105: =H105 -> 78065 | O105: =F105 -> 4 | P105: =I105 -> 0.8819 | Q105: =MAX(0,MIN(1.1*O105,P105*O105)) -> 3.5276
A106: 2 | B106: Implementasi Post Merger Integration | C106: % | D106: 10000 | E106: Maximize | F106: 4 | H106: 100 | I106: 1 | J106: 4 | M106: =D106 -> 10000 | N106: =H106 -> 100 | O106: =F106 -> 4 | P106: =I106 -> 1 | Q106: =MAX(0,MIN(1.1*O106,P106*O106)) -> 4
A107: 3 | B107: Rancangan RKAP tahun 2026 | C107: Waktu | D107: 31/10/2025 | E107: Minimize | F107: 5 | H107: 29/10/2025 | I107: 1 | J107: 5.5 | M107: =D107 -> 31/10/2025 | N107: =H107 -> 29/10/2025 | O107: =F107 -> 5 | P107: =I107 -> 1 | Q107: =MAX(0,MIN(1.1*O107,P107*O107)) -> 5
A108: 4 | B108: Laporan Manajemen | C108: Waktu | D108: Tgl 15/bulan berjalan | E108: Minimize | F108: 5 | H108: 10 | I108: 1.5 | J108: 5.5 | M108: =D108 -> Tgl 15/bulan berjalan | N108: =H108 -> 10 | O108: =F108 -> 5 | P108: =I108 -> 1.5 | Q108: =MAX(0,MIN(1.1*O108,P108*O108)) -> 5.5
...

Sheet PT SGN
A1: Key Performance Indicator PT Sinergi Gula Nusantara
A2: s.d. Desember2025
A4: No. | B4: Key Performance Indicator | C4: ESG / C | D4: 88PS | E4: Satuan | F4: Target 2025 | G4: Target s.d. Desember | H4: Realisasi s.d. Desember | I4: Polaritas | J4: Bobot | L4: Realisasi vs Target s.d. Desember | N4: Realisasi vs Target 2025 | AF4: Target 2025 | AG4: Realisasi 2025 | AH4: Bobot KPI | AI4: % Capaian Realisasi | AJ4: Skor Realisasi KPI | AL4: Region Head | AO4: SEVP Operation / Koordinator KSO / Operasional KSO / Aset | AR4: SEVP Business Support / Business Strategy
J5: Sub | K5: Total | L5: Sub | M5: Total | N5: Sub | O5: Total | Q5: SEVP BS dan Pengembangan | V5: SEVP OPS dan KSO | AA5: SEVP KSO | AL5: Bobot | AM5: % Capaian | AN5: Skor | AO5: Bobot | AP5: % Capaian | AQ5: Skor | AR5: Bobot | AS5: % Capaian | AT5: Skor
A6: A. Nilai Ekonomi dan Sosial Untuk Indonesia | Q6: Bobot | V6: Bobot | AA6: Bobot
A7: A.1 Finansial | Q7: Sub | R7: Total | V7: Sub | W7: Total | AA7: Sub | AB7: Total
A8: 1 | B8: EBITDA Margin | C8: C | E8: % | F8: 26.95 | G8: 26.95 | H8: 6.54 | I8: Maximize | J8: 8 | K8: 18 | L8: 1.94 | M8: =SUM(L8:L10) -> 1.94 | N8: 1.94 | O8: =SUM(N8:N10) -> 1.94 | P8: =H8/G8 -> 0.24267161 | Q8: 10 | R8: =SUM(Q8:Q17) -> 50 | S8: =MAX(0,MIN($P8,110%)) -> 0.24267161 | T8: =Q8*S8 -> 2.4267161 | V8: =10/3 -> 3.3333333 | W8: =SUM(V8:V17) -> 50 | X8: =MAX(0,MIN($P8,110%)) -> 0.24267161 | Y8: =V8*X8 -> 0.80890538 | AF8: =F8 -> 26.95 | AG8: =H8 -> 6.54 | AH8: =J8 -> 8 | AI8: =IFERROR(MAX(0,IF(I8="Minimize",F8/H8,IF(F8>0,H8/F8,IF(H8>0,1.1,F8/H8)))),0) -> 0.24267161 | AJ8: =MIN(1.1*AH8,AI8*AH8) -> 1.9413729 | AL8: 9 | AM8: =AI8 -> 0.24267161 | AN8: =MIN(1.1*AL8,AM8*AL8) -> 2.1840445 | AO8: 4 | AP8: =AI8 -> 0.24267161 | AQ8: =MIN(1.1*AO8,AP8*AO8) -> 0.97068646 | AR8: 14 | AS8: =AI8 -> 0.24267161 | AT8: =MIN(1.1*AR8,AS8*AR8) -> 3.3974026
A9: 2 | B9: ROIC >= WACC | C9: C | E9: % | F9: 11 | G9: 0.11 | H9: -10.73 | I9: Maximize | J9: 5 | L9: 0 | N9: 0 | P9: 0 | Q9: 10 | S9: =MAX(0,MIN($P9,110%)) -> 0 | T9: =Q9*S9 -> 0 | V9: =10/3 -> 3.3333333 | X9: =MAX(0,MIN($P9,110%)) -> 0 | Y9: =V9*X9 -> 0 | AF9: =F9 -> 11 | AG9: =H9 -> -10.73 | AH9: =J9 -> 5 | AI9: =IFERROR(MAX(0,IF(I9="Minimize",F9/H9,IF(F9>0,H9/F9,IF(H9>0,1.1,F9/H9)))),0) -> 0 | AJ9: =MIN(1.1*AH9,AI9*AH9) -> 0 | AL9: 6 | AM9: =AI9 -> 0 | AN9: =MIN(1.1*AL9,AM9*AL9) -> 0 | AO9: 3 | AP9: =AI9 -> 0 | AQ9: =MIN(1.1*AO9,AP9*AO9) -> 0 | AR9: 8 | AS9: =AI9 -> 0 | AT9: =MIN(1.1*AR9,AS9*AR9) -> 0
A10: 3 | B10: Penyampaian LAI Tahun 2024 | C10: G | E10: Waktu | F10: 31/03/25 | G10: 31/03/25 | H10: 23/07/2025 kenapa ditulis 31/03? | I10: Minimize | J10: 5 | L10: 0 | N10: 0 | P10: 0 | Q10: 10 | S10: =MAX(0,MIN($P10,110%)) -> 0 | T10: =Q10*S10 -> 0 | V10: =10/3 -> 3.3333333 | X10: =MAX(0,MIN($P10,110%)) -> 0 | Y10: =V10*X10 -> 0 | AF10: =F10 -> 31/03/25 | AG10: =H10 -> 23/07/2025 kenapa ditulis 31/03? | AH10: =J10 -> 5 | AL10: 5 | AM10: =AI10 -> 0 | AN10: =MIN(1.1*AL10,AM10*AL10) -> 0 | AO10: 3 | AP10: =AI10 -> 0 | AQ10: =MIN(1.1*AO10,AP10*AO10) -> 0 | AR10: 8 | AS10: =AI10 -> 0 | AT10: =MIN(1.1*AR10,AS10*AR10) -> 0
A11: A.2. Operasional
A12: 4 | B12: Cash Cost Gula | C12: C | E12: Rp/Kg | F12: 10858 | G12: 10858 | H12: 16414 | I12: Minimize | J12: 7 | K12: 31 | L12: 4.63 | M12: 26.12 | N12: 4.63 | O12: 26.12 | P12: =H12/G12 -> 1.5116964 | Q12: 2.5 | S12: =MAX(0,MIN($P12,110%)) -> 1.1 | T12: =Q12*S12 -> 2.75 | V12: =30/4 -> 7.5 | X12: =MAX(0,MIN($P12,110%)) -> 1.1 | Y12: =V12*X12 -> 8.25 | AF12: =F12 -> 10858 | AG12: =H12 -> 16414 | AH12: =J12 -> 7 | AI12: =IFERROR(MAX(0,IF(I12="Minimize",F12/H12,IF(F12>0,H12/F12,IF(H12>0,1.1,F12/H12)))),0) -> 0.66150847 | AJ12: =MIN(1.1*AH12,AI12*AH12) -> 4.6305593 | AL12: 5 | AM12: =AI12 -> 0.66150847 | AN12: =MIN(1.1*AL12,AM12*AL12) -> 3.3075423 | AO12: 7 | AP12: =AI12 -> 0.66150847 | AQ12: =MIN(1.1*AO12,AP12*AO12) -> 4.6305593 | AR12: 3 | AS12: =AI12 -> 0.66150847 | AT12: =MIN(1.1*AR12,AS12*AR12) -> 1.9845254
A13: 5 | B13: Produktivitas Gula | C13: C | E13: Ton/Ha | F13: 5.4 | G13: 5.4 | H13: 4.15 | I13: Maximize | J13: 7 | L13: 5.38 | N13: 5.38 | P13: =H13/G13 -> 0.76851852 | Q13: 2.5 | S13: =MAX(0,MIN($P13,110%)) -> 0.76851852 | T13: =Q13*S13 -> 1.9212963 | V13: =30/4 -> 7.5 | X13: =MAX(0,MIN($P13,110%)) -> 0.76851852 | Y13: =V13*X13 -> 5.7638889 | AF13: =F13 -> 5.4 | AG13: =H13 -> 4.15 | AH13: =J13 -> 7 | AI13: =IFERROR(MAX(0,IF(I13="Minimize",F13/H13,IF(F13>0,H13/F13,IF(H13>0,1.1,F13/H13)))),0) -> 0.76851852 | AJ13: =MIN(1.1*AH13,AI13*AH13) -> 5.3796296 | AL13: 5 | AM13: =AI13 -> 0.76851852 | AN13: =MIN(1.1*AL13,AM13*AL13) -> 3.8425926 | AO13: 7 | AP13: =AI13 -> 0.76851852 | AQ13: =MIN(1.1*AO13,AP13*AO13) -> 5.3796296 | AR13: 2 | AS13: =AI13 -> 0.76851852 | AT13: =MIN(1.1*AR13,AS13*AR13) -> 1.537037
A14: 6 | B14: Pencapaian Produksi Gula Untuk Mendukung Swasembada | C14: C | E14: Ton | F14: 1.011.622 | G14: 1011622 | H14: 882546.85 | I14: Maximize | J14: 7 | L14: 6.11 | N14: 6.11 | P14: =H14/G14 -> 0.87240773 | Q14: 2.5 | S14: =MAX(0,MIN($P14,110%)) -> 0.87240773 | T14: =Q14*S14 -> 2.1810193 | V14: =30/4 -> 7.5 | X14: =MAX(0,MIN($P14,110%)) -> 0.87240773 | Y14: =V14*X14 -> 6.543058 | AF14: =F14 -> 1.011.622 | AG14: =H14 -> 882546.85 | AH14: =J14 -> 7 | AI14: =IFERROR(MAX(0,IF(I14="Minimize",G14/H14,IF(G14>0,H14/G14,IF(H14>0,1.1,G14/H14)))),0) -> 0.87240773 | AJ14: =MIN(1.1*AH14,AI14*AH14) -> 6.1068541 | AL14: 4 | AM14: =AI14 -> 0.87240773 | AN14: =MIN(1.1*AL14,AM14*AL14) -> 3.4896309 | AO14: 7 | AP14: =AI14 -> 0.87240773 | AQ14: =MIN(1.1*AO14,AP14*AO14) -> 6.1068541 | AR14: 2 | AS14: =AI14 -> 0.87240773 | AT14: =MIN(1.1*AR14,AS14*AR14) -> 1.7448155
A15: 7 | B15: Sinergi BUMN untuk mendukung Swasembada Gula | C15: C | E15: % | F15: 100 | G15: 100 | H15: 100 | I15: Maximize | J15: 10 | L15: 10 | N15: 10 | P15: =H15/G15 -> 1 | Q15: 2.5 | S15: =MAX(0,MIN($P15,110%)) -> 1 | T15: =Q15*S15 -> 2.5 | V15: =30/4 -> 7.5 | X15: =MAX(0,MIN($P15,110%)) -> 1 | Y15: =V15*X15 -> 7.5 | AF15: =F15 -> 100 | AG15: =H15 -> 100 | AH15: =J15 -> 10 | AI15: =IFERROR(MAX(0,IF(I15="Minimize",F15/H15,IF(F15>0,H15/F15,IF(H15>0,1.1,F15/H15)))),0) -> 1 | AJ15: =MIN(1.1*AH15,AI15*AH15) -> 10 | AL15: 6 | AM15: =AI15 -> 1 | AN15: =MIN(1.1*AL15,AM15*AL15) -> 6 | AO15: 9 | AP15: =AI15 -> 1 | AQ15: =MIN(1.1*AO15,AP15*AO15) -> 9 | AR15: 3 | AS15: =AI15 -> 1 | AT15: =MIN(1.1*AR15,AS15*AR15) -> 3
A16: A.3. Sosial
A17: 8 | B17: Perolehan Bahan Baku P-3 Tebu | C17: S | E17: Ton | F17: 9.138.943 | G17: 9138943 | H17: 10846468 | I17: Maximize | J17: 5 | K17: 5 | L17: 5.5 | M17: 5.5 | N17: 5.5 | O17: 5.5 | P17: =H17/G17 -> 1.1868405 | Q17: 10 | S17: =MAX(0,MIN($P17,110%)) -> 1.1 | T17: =Q17*S17 -> 11 | V17: 10 | X17: =MAX(0,MIN($P17,110%)) -> 1.1 | Y17: =V17*X17 -> 11 | AF17: =F17 -> 9.138.943 | AG17: =H17 -> 10846468 | AH17: =J17 -> 5 | AI17: =IFERROR(MAX(0,IF(I17="Minimize",G17/H17,IF(G17>0,H17/G17,IF(H17>0,1.1,G17/H17)))),0) -> 1.1868405 | AJ17: =MIN(1.1*AH17,AI17*AH17) -> 5.5 | AL17: 10 | AM17: =AI17 -> 1.1868405 | AN17: =MIN(1.1*AL17,AM17*AL17) -> 11 | AO17: 10 | AP17: =AI17 -> 1.1868405 | AQ17: =MIN(1.1*AO17,AP17*AO17) -> 11 | AR17: 10 | AS17: =AI17 -> 1.1868405 | AT17: =MIN(1.1*AR17,AS17*AR17) -> 11
A18: B. Inovasi Model Bisnis
A19: 1 | B19: Implementasi Post Merger Integration | C19: C | E19: % | F19: 100 | G19: 100 | H19: 50 | I19: Maximize | J19: 5 | K19: 15 | L19: 2.5 | M19: 11.08 | N19: 2.5 | O19: 11.08 | P19: =H19/G19 -> 0.5 | Q19: 5 | R19: =SUM(Q19:Q21) -> 15 | S19: =MAX(0,MIN($P19,110%)) -> 0.5 | T19: =Q19*S19 -> 2.5 | V19: 5 | W19: =SUM(V19:V21) -> 15 | X19: =MAX(0,MIN($P19,110%)) -> 0.5 | Y19: =V19*X19 -> 2.5 | AF19: =F19 -> 100 | AG19: =H19 -> 50 | AH19: =J19 -> 5 | AI19: =IFERROR(MAX(0,IF(I19="Minimize",F19/H19,IF(F19>0,H19/F19,IF(H19>0,1.1,F19/H19)))),0) -> 0.5 | AJ19: =MIN(1.1*AH19,AI19*AH19) -> 2.5 | AL19: 5 | AM19: =AI19 -> 0.5 | AN19: =MIN(1.1*AL19,AM19*AL19) -> 2.5 | AO19: 5 | AP19: =AI19 -> 0.5 | AQ19: =MIN(1.1*AO19,AP19*AO19) -> 2.5 | AR19: 5 | AS19: =AI19 -> 0.5 | AT19: =MIN(1.1*AR19,AS19*AR19) -> 2.5
A20: 2 | B20: Total Revenue dari Pemasaran Produk | C20: C | E20: Rp Miliar | F20: 6737 | G20: 6737 | H20: 4824.59 | I20: Maximize | J20: 5 | L20: 3.58 | N20: 3.58 | P20: =H20/G20 -> 0.71613329 | Q20: 5 | S20: =MAX(0,MIN($P20,110%)) -> 0.71613329 | T20: =Q20*S20 -> 3.5806665 | V20: 5 | X20: =MAX(0,MIN($P20,110%)) -> 0.71613329 | Y20: =V20*X20 -> 3.5806665 | AF20: =F20 -> 6737 | AG20: =H20 -> 4824.59 | AH20: =J20 -> 5 | AI20: =IFERROR(MAX(0,IF(I20="Minimize",F20/H20,IF(F20>0,H20/F20,IF(H20>0,1.1,F20/H20)))),0) -> 0.71613329 | AJ20: =MIN(1.1*AH20,AI20*AH20) -> 3.5806665 | AL20: 5 | AM20: =AI20 -> 0.71613329 | AN20: =MIN(1.1*AL20,AM20*AL20) -> 3.5806665 | AO20: 5 | AP20: =AI20 -> 0.71613329 | AQ20: =MIN(1.1*AO20,AP20*AO20) -> 3.5806665 | AR20: 5 | AS20: =AI20 -> 0.71613329 | AT20: =MIN(1.1*AR20,AS20*AR20) -> 3.5806665
A21: 3 | B21: Pengukuran Nilai Emisi Karbon | C21: E | E21: % | F21: 100 | G21: 100 | H21: 100 | I21: Maximize | J21: 5 | L21: 5 | N21: 5 | P21: =H21/G21 -> 1 | Q21: 5 | S21: =MAX(0,MIN($P21,110%)) -> 1 | T21: =Q21*S21 -> 5 | V21: 5 | X21: =MAX(0,MIN($P21,110%)) -> 1 | Y21: =V21*X21 -> 5 | AF21: =F21 -> 100 | AG21: =H21 -> 100 | AH21: =J21 -> 5 | AI21: =IFERROR(MAX(0,IF(I21="Minimize",F21/H21,IF(F21>0,H21/F21,IF(H21>0,1.1,F21/H21)))),0) -> 1 | AJ21: =MIN(1.1*AH21,AI21*AH21) -> 5 | AL21: 5 | AM21: =AI21 -> 1 | AN21: =MIN(1.1*AL21,AM21*AL21) -> 5 | AO21: 5 | AP21: =AI21 -> 1 | AQ21: =MIN(1.1*AO21,AP21*AO21) -> 5 | AR21: 5 | AS21: =AI21 -> 1 | AT21: =MIN(1.1*AR21,AS21*AR21) -> 5
A22: C. Kepemimpinan Teknologi
A23: 1 | B23: Implementasi Use Case RSTI 2025 - 2029 | C23: C | E23: % | F23: 100 | G23: 100 | H23: 100 | I23: Maximize | J23: 8 | K23: 8 | L23: 8 | M23: 8 | N23: 8 | O23: 8 | P23: =H23/G23 -> 1 | Q23: 10 | R23: =Q23 -> 10 | S23: =MAX(0,MIN($P23,110%)) -> 1 | T23: =Q23*S23 -> 10 | V23: 10 | W23: =V23 -> 10 | X23: =MAX(0,MIN($P23,110%)) -> 1 | Y23: =V23*X23 -> 10 | AF23: =F23 -> 100 | AG23: =H23 -> 100 | AH23: =J23 -> 8 | AI23: =IFERROR(MAX(0,IF(I23="Minimize",F23/H23,IF(F23>0,H23/F23,IF(H23>0,1.1,F23/H23)))),0) -> 1 | AJ23: =MIN(1.1*AH23,AI23*AH23) -> 8 | AL23: 10 | AM23: =AI23 -> 1 | AN23: =MIN(1.1*AL23,AM23*AL23) -> 10 | AO23: 10 | AP23: =AI23 -> 1 | AQ23: =MIN(1.1*AO23,AP23*AO23) -> 10 | AR23: 10 | AS23: =AI23 -> 1 | AT23: =MIN(1.1*AR23,AS23*AR23) -> 10
A24: D. Peningkatan Investasi
A25: 1 | B25: Capex – Mesin & Non Mesin Serta Perlengkapan Pabrik | C25: C | E25: Rp Miliar | F25: 640 | G25: 640 | H25: 502.86 | I25: Minimize | J25: 7 | K25: 15 | L25: 7.7 | M25: 14.3 | N25: 7.7 | O25: 14.3 | P25: =H25/G25 -> 0.78571875 | Q25: =15/2 -> 7.5 | R25: =SUM(Q25:Q26) -> 15 | S25: =MAX(0,MIN($P25,110%)) -> 0.78571875 | T25: =Q25*S25 -> 5.8928906 | V25: =15/2 -> 7.5 | W25: =SUM(V25:V26) -> 15 | X25: =MAX(0,MIN($P25,110%)) -> 0.78571875 | Y25: =V25*X25 -> 5.8928906 | AF25: =F25 -> 640 | AG25: =H25 -> 502.86 | AH25: =J25 -> 7 | AI25: =IFERROR(MAX(0,IF(I25="Minimize",F25/H25,IF(F25>0,H25/F25,IF(H25>0,1.1,F25/H25)))),0) -> 1.27272 | AJ25: =MIN(1.1*AH25,AI25*AH25) -> 7.7 | AL25: 7 | AM25: =AI25 -> 1.27272 | AN25: =MIN(1.1*AL25,AM25*AL25) -> 7.7 | AO25: 7 | AP25: =AI25 -> 1.27272 | AQ25: =MIN(1.1*AO25,AP25*AO25) -> 7.7 | AR25: 7 | AS25: =AI25 -> 1.27272 | AT25: =MIN(1.1*AR25,AS25*AR25) -> 7.7
A26: 2 | B26: Replanting & Konversi | C26: C | E26: Ha | F26: 17643 | G26: 17643 | H26: 14548.38 | I26: Maximize | J26: 8 | L26: 6.6 | N26: 6.6 | P26: =H26/G26 -> 0.82459786 | Q26: =15/2 -> 7.5 | S26: =MAX(0,MIN($P26,110%)) -> 0.82459786 | T26: =Q26*S26 -> 6.1844839 | V26: =15/2 -> 7.5 | X26: =MAX(0,MIN($P26,110%)) -> 0.82459786 | Y26: =V26*X26 -> 6.1844839 | AF26: =F26 -> 17643 | AG26: =H26 -> 14548.38 | AH26: =J26 -> 8 | AI26: =IFERROR(MAX(0,IF(I26="Minimize",F26/H26,IF(F26>0,H26/F26,IF(H26>0,1.1,F26/H26)))),0) -> 0.82459786 | AJ26: =MIN(1.1*AH26,AI26*AH26) -> 6.5967829 | AL26: 8 | AM26: =AI26 -> 0.82459786 | AN26: =MIN(1.1*AL26,AM26*AL26) -> 6.5967829 | AO26: 8 | AP26: =AI26 -> 0.82459786 | AQ26: =MIN(1.1*AO26,AP26*AO26) -> 6.5967829 | AR26: 8 | AS26: =AI26 -> 0.82459786 | AT26: =MIN(1.1*AR26,AS26*AR26) -> 6.5967829
A27: E. Pengembangan Talenta
A28: 1 | B28: Human Capital Transformation | C28: S | E28: % | F28: 100 | G28: 100 | H28: 84.09 | I28: Maximize | J28: 8 | K28: 8 | L28: 6.73 | M28: 6.73 | N28: 6.73 | O28: 6.73 | P28: =H28/G28 -> 0.8409 | Q28: 10 | R28: =Q28 -> 10 | S28: =MAX(0,MIN($P28,110%)) -> 0.8409 | T28: =Q28*S28 -> 8.409 | V28: 10 | W28: =V28 -> 10 | X28: =MAX(0,MIN($P28,110%)) -> 0.8409 | Y28: =V28*X28 -> 8.409 | AF28: =F28 -> 100 | AG28: =H28 -> 84.09 | AH28: =J28 -> 8 | AI28: =IFERROR(MAX(0,IF(I28="Minimize",F28/H28,IF(F28>0,H28/F28,IF(H28>0,1.1,F28/H28)))),0) -> 0.8409 | AJ28: =MIN(1.1*AH28,AI28*AH28) -> 6.7272 | AL28: 10 | AM28: =AI28 -> 0.8409 | AN28: =MIN(1.1*AL28,AM28*AL28) -> 8.409 | AO28: 10 | AP28: =AI28 -> 0.8409 | AQ28: =MIN(1.1*AO28,AP28*AO28) -> 8.409 | AR28: 10 | AS28: =AI28 -> 0.8409 | AT28: =MIN(1.1*AR28,AS28*AR28) -> 8.409
B29: TOTAL | K29: 100 | M29: =SUM(M8:M28) -> 73.67 | O29: =SUM(O8:O28) -> 73.67 | R29: =SUM(R8:R28) -> 100 | T29: =SUM(T8:T28) -> 64.346073 | W29: =SUM(W8:W28) -> 100 | Y29: =SUM(Y8:Y28) -> 81.432893 | AH29: =SUM(AH5:AH28) -> 100 | AI29: =IFERROR(AJ29/AH29,0) -> 0.73663065 | AJ29: =SUM(AJ5:AJ28) -> 73.663065 | AL29: =SUM(AL8:AL28) -> 100 | AM29: =IFERROR(AN29/AL29,0) -> 0.7361026 | AN29: =SUM(AN8:AN28) -> 73.61026 | AO29: =SUM(AO8:AO28) -> 100 | AP29: =IFERROR(AQ29/AO29,0) -> 0.80874179 | AQ29: =SUM(AQ8:AQ28) -> 80.874179 | AR29: =SUM(AR8:AR28) -> 100 | AS29: =IFERROR(AT29/AR29,0) -> 0.6645023 | AT29: =SUM(AT8:AT28) -> 66.45023
N33: 10 | O33: 30
N34: 30 | O34: 10
N35: 10 | O35: 10 | P35: 50
P36: 15
P37: 10
P38: 15
P39: 10

Sheet PTPN I DIR
A1: KOLEGIAL
A2: No | B2: Key Performance Indicator | C2: Satuan | D2: Target | E2: Realisasi | F2: Polaritas | G2: Bobot | H2: Skor
A3: 1 | B3: EBITDA Margin | C3: % | D3: 24.72 | E3: 29.79 | F3: Maximize | G3: 10 | H3: 11
A4: 2 | B4: ROIC >= WACC | C4: % | D4: -1.53 | E4: -2.64 | F4: Maximize | G4: 7 | H4: 4.06
A5: 3 | B5: Penyampaian LAI Tahun 2024 | C5: Waktu | D5: 31 Maret 2025 | E5: 8 Juni 2025 | F5: Minimize | G5: 6 | H5: 0
A6: 4 | B6: Cash Cost Komoditi Karet | C6: Rp/Kg | D6: 18900 | E6: 21389.19 | F6: Minimize | G6: 12 | H6: 10.6
A7: 5 | B7: Produktivitas Komoditi Karet | C7: Ton/Ha | D7: 1.44 | E7: 1.21 | F7: Maximize | G7: 12 | H7: 10.08
A8: 6 | B8: Realisasi Program TJSL BUMN | C8: % | D8: 100 | E8: 95 | F8: Maximize | G8: 7 | H8: 6.65
A9: 7 | B9: Implementasi Post Merger Integration | C9: % | D9: 100 | E9: 90.28 | F9: Maximize | G9: 3 | H9: 2.71
A10: 8 | B10: Total Revenue dari Pemasaran Produk | C10: Rp Miliar | D10: 4048.4 | E10: 3856.98 | F10: Maximize | G10: 5 | H10: 4.76
A11: 9 | B11: Total Revenue dari Agrowisata | C11: Rp Miliar | D11: 215.8 | E11: 155.73 | F11: Maximize | G11: 4 | H11: 2.89
A12: 10 | B12: Implementasi ESG | C12: % | D12: 100 | E12: 100 | F12: Maximize | G12: 3 | H12: 3
A13: 11 | B13: Implementasi RSTI 2025 - 2029 | C13: % | D13: 100 | E13: 100 | F13: Maximize | G13: 8 | H13: 8
A14: 12 | B14: Realisasi PMN | C14: % | D14: 96.6 | E14: 81.78 | F14: Maximize | G14: 4 | H14: 3.39
A15: 13 | B15: Monetisasi/Pelepasan Aset Non-Inti | C15: Rp Miliar | D15: 1566 | E15: 489.39 | F15: Maximize | G15: 7 | H15: 2.19
A16: 14 | B16: Replanting & Perluasan | C16: Ha | D16: 3300.86 | E16: 3700.03 | F16: Maximize | G16: 4 | H16: 4.4
A17: 15 | B17: Human Capital Transformation | C17: % | D17: 100 | E17: 99.94 | F17: Maximize | G17: 8 | H17: 8
B18: TOTAL | G18: 100 | H18: =SUM(H3:H17) -> 81.73
A20: DIR. SDM DAN TI
A21: No | B21: Key Performance Indicator | C21: Satuan | D21: Target | E21: Realisasi | F21: Polaritas | G21: Bobot | H21: Skor
A22: 1 | B22: EBITDA Margin | C22: % | D22: 24.72 | E22: 29.79 | F22: Maximize | G22: 8 | H22: 8.8
A23: 2 | B23: ROIC >= WACC | C23: % | D23: -1.53 | E23: -2.64 | F23: Maximize | G23: 8 | H23: 4.64
A24: 3 | B24: Penyampaian LAI Tahun 2024 | C24: Waktu | D24: 31 Maret 2025 | E24: 8 Juni 2025 | F24: Minimize | G24: 8 | H24: 0
A25: 4 | B25: Implementasi Integrated Management System | C25: % | D25: 100 | E25: 100 | F25: Maximize | G25: 8 | H25: 8
A26: 5 | B26: Penggunaan Produk Dalam Negeri (PDN) | C26: Rp Miliar | D26: 1522.7 | E26: 1042.38 | F26: Maximize | G26: 6 | H26: 4.11
A27: 6 | B27: Efisiensi Nilai SPPBJ dibandingkan HPS | C27: % | D27: 3 | E27: 3.38 | F27: Maximize | G27: 6 | H27: 6.6
A28: 7 | B28: Pemenuhan Mitigasi Risiko | C28: % | D28: 100 | E28: 102.44 | F28: Maximize | G28: 6 | H28: 6.15
A29: 8 | B29: Implementasi RSTI 2025 - 2029 | C29: % | D29: 100 | E29: 100 | F29: Maximize | G29: 7 | H29: 7
A30: 9 | B30: Realisasi PMN | C30: % | D30: 96.6 | E30: 81.78 | F30: Maximize | G30: 8 | H30: 6.77
A31: 10 | B31: Human Capital Transformation | C31: % | D31: 100 | E31: 99.94 | F31: Maximize | G31: 5 | H31: 5
A32: 11 | B32: Competency Level Index (CLI) | C32: % | D32: 100 | E32: 100 | F32: Maximize | G32: 5 | H32: 5
A33: 12 | B33: AKHLAK Maturity Index | C33: % | D33: 100 | E33: 100 | F33: Maximize | G33: 5 | H33: 5
A34: 13 | B34: Employee Engagement Index | C34: % | D34: 100 | E34: 100 | F34: Maximize | G34: 5 | H34: 5
A35: 14 | B35: Implementasi Roadmap Penyehatan Dana Pensiun | C35: % | D35: 100 | E35: 39.51 | F35: Maximize | G35: 5 | H35: 1.98
A36: 15 | B36: Pelaksanaan IT Maturity Assessment | C36: % | D36: 100 | E36: 100 | F36: Maximize | G36: 5 | H36: 5
A37: 16 | B37: Transaksi Pengadaan UMKM (PaDi UMKM) | C37: Rp Miliar | D37: 21.55 | E37: 34 | F37: Maximize | G37: 5 | H37: 5.5
B38: TOTAL | G38: 100 | H38: =SUM(H22:H37) -> 84.55
A40: DIR. HUBUNGAN KELEMBAGAAN
A41: No | B41: Key Performance Indicator | C41: Satuan | D41: Target | E41: Realisasi | F41: Polaritas | G41: Bobot | H41: Skor
A42: 1 | B42: EBITDA Margin | C42: % | D42: 24.72 | E42: 29.79 | F42: Maximize | G42: 8 | H42: 8.8
A43: 2 | B43: ROIC >= WACC | C43: % | D43: -1.53 | E43: -2.64 | F43: Maximize | G43: 8 | H43: 4.64
A44: 3 | B44: Penyampaian LAI Tahun 2024 | C44: Waktu | D44: 31 Maret 2025 | E44: 8 Juni 2025 | F44: Minimize | G44: 8 | H44: 0
A45: 4 | B45: Realisasi Program TJSL BUMN | C45: % | D45: 100 | E45: 95 | F45: Maximize | G45: 5 | H45: 4.75
A46: 5 | B46: Implementasi Post Merger Integration | C46: % | D46: 100 | E46: 90.28 | F46: Maximize | G46: 5 | H46: 4.51
A47: 6 | B47: Implementasi Integrated Management System | C47: % | D47: 100 | E47: 100 | F47: Maximize | G47: 8 | H47: 8
A48: 7 | B48: Pemenuhan Mitigasi Risiko | C48: % | D48: 100 | E48: 98.04 | F48: Maximize | G48: 5 | H48: 4.9
A49: 8 | B49: Implementasi ESG | C49: % | D49: 100 | E49: 100 | F49: Minimize | G49: 5 | H49: 5
A50: 9 | B50: Penerbitan SSPD Nihil | C50: % | D50: 75 | E50: 53.19 | F50: Maximize | G50: 5 | H50: 3.55
A51: 10 | B51: Sertifikasi Aset Tanah | C51: % | D51: 100 | E51: 83 | F51: Maximize | G51: 5 | H51: 4.15
A52: 11 | B52: Recovery Aset | C52: Ha | D52: 1425 | E52: 2044.68 | F52: Maximize | G52: 5 | H52: 5.5
A53: 12 | B53: Pengurusan Perizinan Berusaha Pasca Integrasi | C53: % | D53: 100 | E53: 324 | F53: Maximize | G53: 5 | H53: 5.5
A54: 13 | B54: Realisasi PMN | C54: % | D54: 96.6 | E54: 81.78 | F54: Maximize | G54: 8 | H54: 6.77
A55: 14 | B55: Peningkatan Kompetensi Profesi | C55: % | D55: 100 | E55: 100 | F55: Maximize | G55: 5 | H55: 5
A56: 15 | B56: Rasio Pemenuhan Kualifikasi Organ Pengelola Risiko | C56: % | D56: 100 | E56: 144.59 | F56: Maximize | G56: 5 | H56: 5.5
... A58: 17 | B58: Survei Kepuasan Stakeholder | C58: % | D58: 80 | E58: 79.87 | F58: Maximize | G58: 5 | H58: 4.99
B59: TOTAL | G59: 100 | H59: =SUM(H42:H58) -> 85.58
A61: DIR. KEUANGAN DAN MANAJEMEN RISIKO
A62: No | B62: Key Performance Indicator | C62: Satuan | D62: Target | E62: Realisasi | F62: Polaritas | G62: Bobot | H62: Skor
A63: 1 | B63: EBITDA Margin | C63: % | D63: 24.72 | E63: 29.79 | F63: Maximize | G63: 8 | H63: 8.8
A64: 2 | B64: ROIC >= WACC | C64: % | D64: -1.53 | E64: -2.64 | F64: Maximize | G64: 8 | H64: 4.64
A65: 3 | B65: Penyampaian LAI Tahun 2024 | C65: Waktu | D65: 31 Maret 2025 | E65: 8 Juni 2025 | F65: Minimize | G65: 8 | H65: 0
A66: 4 | B66: Debt Service Coverage Ratio | C66: % | D66: 1.23 | E66: 0.69 | F66: Maximize | G66: 6 | H66: 3.35
A67: 5 | B67: Rancangan RKAP Tahun 2026 | C67: Waktu | D67: 31 Oktober 2025 | E67: 31 Oktober 2025 | F67: Minimize | G67: 6 | H67: 6
A68: 6 | B68: Cash Flow From Operational | C68: Rp Miliar | D68: 116.67 | E68: 917515 | F68: Maximize | G68: 6 | H68: 6.6
A69: 7 | B69: Implementasi Post Merger Integration | C69: % | D69: 100 | E69: 90.28 | F69: Maximize | G69: 6 | H69: 5.42
A70: 8 | B70: Implementasi Integrated Management System | C70: % | D70: 100 | E70: 100 | F70: Maximize | G70: 8 | H70: 8
A71: 9 | B71: Implementasi Business Turnaround | C71: % | D71: 100 | E71: 100 | F71: Maximize | G71: 6 | H71: 6
A72: 10 | B72: Pemenuhan Mitigasi Risiko | C72: % | D72: 100 | E72: 100 | F72: Maximize | G72: 6 | H72: 6
A73: 11 | B73: Optimalisasi Dividen Anak Perusahaan | C73: Rp Miliar | D73: 180 | E73: 428.12 | F73: Maximize | G73: 6 | H73: 6.6
A74: 12 | B74: Realisasi PMN | C74: % | D74: 96.6 | E74: 81.78 | F74: Maximize | G74: 8 | H74: 6.77
A75: 13 | B75: Penyehatan Anak Perusahaan Non PTPN | C75: Jumlah AP | D75: 2 | E75: 5 | F75: Maximize | G75: 6 | H75: 6.6
A76: 14 | B76: Pelaporan Dana IP PEN | C76: Waktu | D76: Tgl 20 bulan berikutnya | E76: Tgl 20 bulan berikutnya | F76: Minimize | G76: 6 | H76: 6
A77: 15 | B77: Penyelesaian Proses Debt Reprofilling | C77: % | D77: 100 | E77: 60 | F77: Maximize | G77: 6 | H77: 3.6
B78: TOTAL | G78: 100 | H78: =SUM(H63:H77) -> 84.38
A80: DIR. OPERASIONAL
A81: No | B81: Key Performance Indicator | C81: Satuan | D81: Target | E81: Realisasi | F81: Polaritas | G81: Bobot | H81: Skor
A82: 1 | B82: EBITDA Margin | C82: % | D82: 24.72 | E82: 29.79 | F82: Maximize | G82: 8 | H82: 8.8
A83: 2 | B83: ROIC >= WACC | C83: % | D83: -1.53 | E83: -2.64 | F83: Maximize | G83: 8 | H83: 4.64
A84: 3 | B84: Penyampaian LAI Tahun 2024 | C84: Waktu | D84: 31 Maret 2025 | E84: 8 Juni 2025 | F84: Minimize | G84: 8 | H84: 0
A85: 4a | B85: Cash Cost Karet | C85: Rp/Kg | D85: 18900.34 | E85: 21389.19 | F85: Minimize | G85: 7 | H85: 6.19
A86: 4b | B86: Cash Cost Teh | C86: Rp/Kg | D86: 22054.65 | E86: 20026.18 | F86: Minimize | G86: 4 | H86: 4.4
A87: 4c | B87: Cash Cost Kopi | C87: Rp/Kg | D87: 41800 | E87: 48053.1 | F87: Minimize | G87: 3 | H87: 2.61
A88: 5a | B88: Produktivitas Karet | C88: Ton/Ha | D88: 1.44 | E88: 1.21 | F88: Maximize | G88: 7 | H88: 5.88
A89: 5b | B89: Produktivitas Teh | C89: Ton/Ha | D89: 2.27 | E89: 2 | F89: Maximize | G89: 4 | H89: 3.52
A90: 5c | B90: Produktivitas Kopi | C90: Ton/Ha | D90: 0.5 | E90: 0.25 | F90: Maximize | G90: 3 | H90: 1.5
A91: 6 | B91: Kualitas Karet Mutu Tinggi (RSS 1) | C91: % | D91: 97.65 | E91: 97.65 | F91: Maximize | G91: 6 | H91: 5.98
A92: 7a | B92: Kualitas Teh Mutu Tinggi - Orthodox | C92: % | D92: 62.4 | E92: 48.78 | F92: Maximize | G92: 4 | H92: 3.13
A93: 7b | B93: Kualitas Teh Mutu Tinggi - CTC | C93: % | D93: 69 | E93: 59.93 | F93: Maximize | G93: 2 | H93: 1.74
A94: 8 | B94: Pemenuhan Kompensasi KSO Sawit dan Tebu | C94: % | D94: 100 | E94: 100 | F94: Maximize | G94: 6 | H94: 6
A95: 9 | B95: Implementasi Integrated Management System | C95: % | D95: 100 | E95: 100 | F95: Maximize | G95: 8 | H95: 8
A96: 10 | B96: Implementasi Pilot Project Kebun Teh | C96: % | D96: 100 | E96: 100 | F96: Maximize | G96: 5 | H96: 5
A97: 11 | B97: Pemenuhan Mitigasi Risiko | C97: % | D97: 100 | E97: 100 | F97: Maximize | G97: 5 | H97: 5
A98: 12 | B98: Realisasi PMN | C98: % | D98: 96.6 | E98: 81.78 | F98: Maximize | G98: 8 | H98: 6.77
A99: 13 | B99: Replanting & Perluasan | C99: Ha | D99: 3300.86 | E99: 3700.03 | F99: Maximize | G99: 4 | H99: 4.4
B100: TOTAL | G100: 100 | H100: =SUM(H82:H99) -> 83.56
A102: DIR. PEMASARAN DAN ASET MANAJEMEN
A103: No | B103: Key Performance Indicator | C103: Satuan | D103: Target | E103: Realisasi | F103: Polaritas | G103: Bobot | H103: Skor
A104: 1 | B104: EBITDA Margin | C104: % | D104: 24.72 | E104: 29.79 | F104: Maximize | G104: 8 | H104: 8.8
A105: 2 | B105: ROIC >= WACC | C105: % | D105: -1.53 | E105: -2.64 | F105: Maximize | G105: 8 | H105: 4.64
A106: 3 | B106: Penyampaian LAI Tahun 2024 | C106: Waktu | D106: 31 Maret 2025 | E106: 8 Juni 2025 | F106: Minimize | G106: 8 | H106: 0
...

Sheet PTPN I
A1: Key Performance Indicator PT Perkebunan Nusantara I
A2: s.d. Desember 2025
A4: No. | B4: Key Performance Indicator | C4: ESG / C | D4: 88 PS | E4: Satuan | F4: Target 2025 | G4: Target s.d. Desember | H4: Realisasi s.d. Desember | I4: Polaritas | J4: Bobot | L4: Realisasi vs Target s.d. Desember | N4: Realisasi vs Target 2025 | P4: Keterangan | Q4: Target 2025 | R4: Realisasi 2025 | S4: Bobot KPI | T4: % Capaian Realisasi | U4: Skor Realisasi KPI | W4: Region Head | Z4: SEVP Operation / Koordinator KSO / Operasional KSO / Aset | AC4: SEVP Business Support / Business Strategy
J5: Sub | K5: Total | L5: Sub | M5: Total | N5: Sub | O5: Total | W5: Bobot | X5: % Capaian | Y5: Skor | Z5: Bobot | AA5: % Capaian | AB5: Skor | AC5: Bobot | AD5: % Capaian | AE5: Skor
A6: A. Nilai Ekonomi dan Sosial Untuk Indonesia
A7: A.1 Finansial
A8: 1 | B8: EBITDA Margin | C8: C | E8: % | F8: 24.72 | G8: 24.72 | H8: 29.79 | I8: Maximize | J8: 10 | K8: =SUM(J8:J10) -> 23 | L8: =IFERROR((MIN(1.1,(H8/G8)))*J8,0) -> 11 | M8: =SUM(L8:L10) -> 18.7 | N8: =IFERROR((MIN(1.1,(H8/F8)))*J8,0) -> 11 | O8: =SUM(N8:N10) -> 15.056818 | P8: Realisasi EBITDA Margin tercapai 32% (EBITDA Operasional Rp1.229 Milyar, Penjualan Rp3.840,6 Milyar), lebih tinggi dari target RKAP s.d Juni 13,06% dan target RKAP 2025 24,72% | Q8: =F8 -> 24.72 | R8: =H8 -> 29.79 | S8: =J8 -> 10 | T8: =IFERROR(IF(I8="Minimize",F8/H8,IF(F8>0,H8/F8,IF(H8>0,1.1,F8/H8))),0) -> 1.2050971 | U8: =MIN(1.1*S8,T8*S8) -> 11 | W8: 9 | X8: =T8 -> 1.2050971 | Y8: =MIN(1.1*W8,X8*W8) -> 9.9 | Z8: 4 | AA8: =T8 -> 1.2050971 | AB8: =MIN(1.1*Z8,AA8*Z8) -> 4.4 | AC8: 13 | AD8: =T8 -> 1.2050971 | AE8: =MIN(1.1*AC8,AD8*AC8) -> 14.3
A9: 2 | B9: ROIC >= WACC | C9: C | E9: % | F9: -1.53 | G9: -1.53 | H9: -2.64 | I9: Maximize | J9: 7 | L9: =IFERROR(MIN(1.1*J9,(S9/T9)*J9),0) -> 7.7 | N9: =IFERROR((MIN(1.1,(F9/H9)))*J9,0) -> 4.0568182 | P9: Realisasi ROIC WACC -1,28%, lebih baik dari target RKAP s.d Juni -2,95% dan target RKAP 2025 -1,53% | Q9: =F9 -> -1.53 | R9: =H9 -> -2.64 | S9: =J9 -> 7 | T9: =IFERROR(IF(I9="Minimize",F9/H9,IF(F9>0,H9/F9,IF(H9>0,1.1,F9/H9))),0) -> 0.57954545 | U9: =MIN(1.1*S9,T9*S9) -> 4.0568182 | W9: 6 | X9: =T9 -> 0.57954545 | Y9: =MIN(1.1*W9,X9*W9) -> 3.4772727 | Z9: 3 | AA9: =T9 -> 0.57954545 | AB9: =MIN(1.1*Z9,AA9*Z9) -> 1.7386364 | AC9: 9 | AD9: =T9 -> 0.57954545 | AE9: =MIN(1.1*AC9,AD9*AC9) -> 5.2159091
A10: 3 | B10: Penyampaian LAI Tahun 2024 | C10: G | E10: Waktu | F10: 45747 | G10: 45874 | H10: 45875 | I10: Minimize | J10: 6 | L10: =IFERROR(MIN(1.1*J10,(#REF!/H10)*J10),0) -> 0 | N10: =IFERROR(MIN(1.1*L10,(H10/J10)*L10),0) -> 0 | P10: Proses Audit masih berjalan, estimasi penyelesaian pada minggu ke dua bulan Juni 2025 | Q10: =F10 -> 45747 | R10: =H10 -> 45875 | S10: =J10 -> 6 | T10: =IFERROR(U10/S10,0) -> 0 | U10: =S10*IF(H10<DATE(2025,4,1),1.1,IF(H10<=DATE(2025,4,15),1,IF(H10<=DATE(2025,5,31),0.8,IF(H10<=DATE(2025,6,15),0.4,IF(H10<=DATE(2025,6,30),0.2,0))))) -> 0 | W10: 5 | X10: =T10 -> 0 | Y10: =MIN(1.1*W10,X10*W10) -> 0 | Z10: 3 | AA10: =T10 -> 0 | AB10: =MIN(1.1*Z10,AA10*Z10) -> 0 | AC10: 8 | AD10: =T10 -> 0 | AE10: =MIN(1.1*AC10,AD10*AC10) -> 0
A11: A.2. Operasional
A12: 4 | B12: Cash Cost Komoditi Karet | C12: C | E12: Rp/Kg | F12: 18900.335 | G12: 18900.335 | H12: 21389.19 | I12: Minimize | J12: 12 | K12: =SUM(J12:J13) -> 24 | L12: =IFERROR(MIN(1.1*J12,(G12/H12)*J12),0) -> 10.603675 | M12: =SUM(L12:L13) -> 20.687009 | N12: =IFERROR((MIN(1.1,(F12/H12)))*J12,0) -> 10.603675 | O12: =SUM(N12:N13) -> 20.687009 | P12: Realisasi Cash Cost Karet Rp 20.114,-/Kg, lebih baik 108% dari target RKAP s.d Juni Rp 21.637,-/Kg, namun masih 106% melampaui target RKAP 2025 Rp 18.900,-/Kg | Q12: =F12 -> 18900.335 | R12: =H12 -> 21389.19 | S12: =J12 -> 12 | T12: =IFERROR(IF(I12="Minimize",F12/H12,IF(F12>0,H12/F12,IF(H12>0,1.1,F12/H12))),0) -> 0.88363961 | U12: =MIN(1.1*S12,T12*S12) -> 10.603675 | W12: 10 | X12: =T12 -> 0.88363961 | Y12: =MIN(1.1*W12,X12*W12) -> 8.8363961 | Z12: 15 | AA12: =T12 -> 0.88363961 | AB12: =MIN(1.1*Z12,AA12*Z12) -> 13.254594 | AC12: 5 | AD12: =T12 -> 0.88363961 | AE12: =MIN(1.1*AC12,AD12*AC12) -> 4.418198
A13: 5 | B13: Produktivitas Komoditi Karet | C13: C | E13: Ton/Ha | F13: 1.44 | G13: 1.44 | H13: 1.21 | I13: Maximize | J13: 12 | L13: =IFERROR((MIN(1.1,(H13/G13)))*J13,0) -> 10.083333 | N13: =IFERROR((MIN(1.1,(H13/F13)))*J13,0) -> 10.083333 | P13: Realisasi Protas Karet 0,540 Ton/Ha, atau tercapai hanya 95% dari target Juni 0,567 Ton/Ha dan baru tercapai 37% dari target RKAP 2025 1,44 Ton/Ha | Q13: =F13 -> 1.44 | R13: =H13 -> 1.21 | S13: =J13 -> 12 | T13: =IFERROR(IF(I13="Minimize",F13/H13,IF(F13>0,H13/F13,IF(H13>0,1.1,F13/H13))),0) -> 0.84027778 | U13: =MIN(1.1*S13,T13*S13) -> 10.083333 | W13: 10 | X13: =T13 -> 0.84027778 | Y13: =MIN(1.1*W13,X13*W13) -> 8.4027778 | Z13: 15 | AA13: =T13 -> 0.84027778 | AB13: =MIN(1.1*Z13,AA13*Z13) -> 12.604167 | AC13: 5 | AD13: =T13 -> 0.84027778 | AE13: =MIN(1.1*AC13,AD13*AC13) -> 4.2013889
A14: A.3. Sosial
A15: 6 | B15: Realisasi Program TJSL BUMN | C15: S | E15: % | F15: 100 | G15: 100 | H15: 95 | I15: Maximize | J15: 7 | K15: =SUM(J15) -> 7 | L15: =IFERROR((MIN(1.1,(H15/G15)))*J15,0) -> 6.65 | M15: =SUM(L15) -> 6.65 | N15: =IFERROR((MIN(1.1,(H15/F15)))*J15,0) -> 6.65 | O15: =SUM(N15) -> 6.65 | P15: Realisasi KPI TJSL Juni 2025 : 1. Aspek Fokus pada Dampak, yaitu pengukuran dampak 3 (tiga) program TJSL dengan metode Social Return on Investment (SROI), minimal 1 (satu) diantaranya adalah program Creating Shared Values (CSV) (0%) 2. Aspek Peningkatan Tata Kelola, terdiri dari: a. Kecukupan Standard Operating Procedure (SOP) Pelaksanaan Program TJSL BUMN (10%) b. Peningkatan Kompetensi SDM 1) Perusahaan memiliki minimal 1 (satu) pegawai yang bersertifikasi di bidang Sustainability 2) Seluruh karyawan pengelola TJSL mendapatkan pelatihan terkait kompetensi TJSL (10%) 3. Aspek Pemanfaatan Teknologi Informasi, yaitu pemenuhan pengisian data sistem informasi TJSL Kementerian BUMN (4%) 4. Aspek Peningkatan Kolaborasi, yaitu pelaksanaan kolaborasi program TJSL antar BUMN dan Pihak Lain (10%) 5. Aspek Peningkatan Engagement Karyawan, yaitu pelaksanaan kegiatan sosial kemasyarakatan oleh seluruh karyawan BUMN (1,83%) | Q15: =F15 -> 100 | R15: =H15 -> 95 | S15: =J15 -> 7 | T15: =IFERROR(IF(I15="Minimize",F15/H15,IF(F15>0,H15/F15,IF(H15>0,1.1,F15/H15))),0) -> 0.95 | U15: =MIN(1.1*S15,T15*S15) -> 6.65 | W15: 10 | X15: =T15 -> 0.95 | Y15: =MIN(1.1*W15,X15*W15) -> 9.5 | Z15: 10 | AA15: =T15 -> 0.95 | AB15: =MIN(1.1*Z15,AA15*Z15) -> 9.5 | AC15: 10 | AD15: =T15 -> 0.95 | AE15: =MIN(1.1*AC15,AD15*AC15) -> 9.5
A16: B. Inovasi Model Bisnis
A17: 1 | B17: Implementasi Post Merger Integration dan Implementasi Integrated Management System | C17: C | E17: % | F17: 100 | G17: 100 | H17: 90.28 | I17: Maximize | J17: 3 | K17: =SUM(J17:J20) -> 15 | L17: =IFERROR((MIN(1.1,(H17/G17)))*J17,0) -> 2.7084 | M17: =SUM(L17:L20) -> 13.363618 | N17: =IFERROR((MIN(1.1,(H17/F17)))*J17,0) -> 2.7084 | O17: =SUM(N17:N20) -> 13.363618 | P17: Realisasi Implementasi Post Merger Integration dan Implementasi Integrated Management System sebesar 77% yang terdiri dari : Perubahan Struktur Permodalan atas Integrasi PTPN (Bobot 30%, Progress 26%), Laporan Penilaian Saham sudah final, menunggu arahan Holding -Proses BPHTB 0% (Bobot 30%, Progress 29%), tercapai 98 SK dari target 125 SK. -Pelepasan Saham di PT SGN (Bobot 30%, Progress 21%), Kajian dan Tanggapan Dekom sudah selesai, untuk persetujuan RUPS menunggu arahan lebih lanjut dari Holding. -Implementasi Integrated Management System (Bobot 10%, Progress 14% (Tahap penyusunan pedoman dan pertanyaan audit, rencana audit IMS di Semester II 2025) | Q17: =F17 -> 100 | R17: =H17 -> 90.28 | S17: =J17 -> 3 | T17: =IFERROR(IF(I17="Minimize",F17/H17,IF(F17>0,H17/F17,IF(H17>0,1.1,F17/H17))),0) -> 0.9028 | U17: =MIN(1.1*S17,T17*S17) -> 2.7084 | W17: 3 | X17: =T17 -> 0.9028 | Y17: =MIN(1.1*W17,X17*W17) -> 2.7084 | Z17: 3 | AA17: =T17 -> 0.9028 | AB17: =MIN(1.1*Z17,AA17*Z17) -> 2.7084 | AC17: 3 | AD17: =T17 -> 0.9028 | AE17: =MIN(1.1*AC17,AD17*AC17) -> 2.7084
A18: 2 | B18: Total Revenue dari Pemasaran Produk | C18: C | E18: Rp Miliar | F18: 4048.3955 | G18: 4048.3955 | H18: 3856.98 | I18: Maximize | J18: 5 | L18: =IFERROR((MIN(1.1,(H18/G18)))*J18,0) -> 4.7635909 | N18: =IFERROR((MIN(1.1,(H18/F18)))*J18,0) -> 4.7635909 | P18:  Realisasi Pemasaran Produk Komoditi Rp 1.534,1 Milyar. Karet tercapai Rp 1.297,6 Milyar, tercapai lebih tinggi yaitu 104% dari target RKAP s.d Juni sebesar Rp 1.246,7 Milyar. Kopi tercapai Rp 44,5 Milyar dari target RKAP sd Juni Rp 41 juta. Teh tercapai Rp 191,9 Milyar atau hanya tercapai 65% dari target RKAP s.d Juni Rp 289 Milyar.  Realisasi Pemasaran Produk Retail Rp 24,21 Milyar, lebih rendah dari RKAP sd Juni sebesar Rp 45,7 Milyar atau tercapai sebesar 53%. | Q18: =F18 -> 4048.3955 | R18: =H18 -> 3856.98 | S18: =J18 -> 5 | T18: =IFERROR(IF(I18="Minimize",F18/H18,IF(F18>0,H18/F18,IF(H18>0,1.1,F18/H18))),0) -> 0.95271818 | U18: =MIN(1.1*S18,T18*S18) -> 4.7635909 | W18: 5 | X18: =T18 -> 0.95271818 | Y18: =MIN(1.1*W18,X18*W18) -> 4.7635909 | Z18: 5 | AA18: =T18 -> 0.95271818 | AB18: =MIN(1.1*Z18,AA18*Z18) -> 4.7635909 | AC18: 5 | AD18: =T18 -> 0.95271818 | AE18: =MIN(1.1*AC18,AD18*AC18) -> 4.7635909
A19: 3 | B19: Total Revenue dari Agrowisata | C19: C | E19: Rp Miliar | F19: 215.79549 | G19: 215.79549 | H19: 156 | I19: Maximize | J19: 4 | L19: =IFERROR((MIN(1.1,(H19/G19)))*J19,0) -> 2.8916267 | N19: =IFERROR((MIN(1.1,(H19/F19)))*J19,0) -> 2.8916267 | P19: Revenue Agrowisata Rp 60,39 Milyar dari target Juni 2025 Rp 80,26 Milyar | Q19: =F19 -> 215.79549 | R19: =H19 -> 156 | S19: =J19 -> 4 | T19: =IFERROR(IF(I19="Minimize",F19/H19,IF(F19>0,H19/F19,IF(H19>0,1.1,F19/H19))),0) -> 0.72290668 | U19: =MIN(1.1*S19,T19*S19) -> 2.8916267 | W19: 4 | X19: =T19 -> 0.72290668 | Y19: =MIN(1.1*W19,X19*W19) -> 2.8916267 | Z19: 4 | AA19: =T19 -> 0.72290668 | AB19: =MIN(1.1*Z19,AA19*Z19) -> 2.8916267 | AC19: 4 | AD19: =T19 -> 0.72290668 | AE19: =MIN(1.1*AC19,AD19*AC19) -> 2.8916267
A20: 4 | B20: Implementasi ESG | C20: E | E20: % | F20: 100 | G20: 100 | H20: 100 | I20: Maximize | J20: 3 | L20: =IFERROR((MIN(1.1,(H20/G20)))*J20,0) -> 3 | N20: =IFERROR((MIN(1.1,(H20/F20)))*J20,0) -> 3 | P20: Progress Pengukuran emisi karbon 15% (Inventarisasi dan Penyusunan Kalkulator) Program Sustainability yaitu Implementasi EWS sudah mencapai 60% dari 100% pelaksanaan, Circular Economy belum dilaksanakan, rencana mulai pelaksanaan pada TW II | Q20: =F20 -> 100 | R20: =H20 -> 100 | S20: =J20 -> 3 | T20: =IFERROR(IF(I20="Minimize",F20/H20,IF(F20>0,H20/F20,IF(H20>0,1.1,F20/H20))),0) -> 1 | U20: =MIN(1.1*S20,T20*S20) -> 3 | W20: 3 | X20: =T20 -> 1 | Y20: =MIN(1.1*W20,X20*W20) -> 3 | Z20: 3 | AA20: =T20 -> 1 | AB20: =MIN(1.1*Z20,AA20*Z20) -> 3 | AC20: 3 | AD20: =T20 -> 1 | AE20: =MIN(1.1*AC20,AD20*AC20) -> 3
A21: C. Kepemimpinan Teknologi
A22: 1 | B22: Implementasi RSTI 2025 - 2029 | C22: C | E22: % | F22: 100 | G22: 100 | H22: 100 | I22: Maximize | J22: 8 | K22: =J22 -> 8 | L22: =IFERROR((MIN(1.1,(H22/G22)))*J22,0) -> 8 | M22: =L22 -> 8 | N22: =IFERROR((MIN(1.1,(H22/F22)))*J22,0) -> 8 | O22: =N22 -> 8 | P22: Progress Implementasi RSTI 67,1% Progress Implementasi RSTI tercapai 67,1%, dengan rincian:  Health Monitoring: 68,96%  Harvest Optimization: 88,42%  3rd Party Buying Platform: 83,5%  Optimized Transport Planning & Road Optimization: 58,13%  Real Time Monitoring & Mills Refinery: 61,94%  Trading System: 30,42%  Performance Management Dashboard: 78,33% | Q22: =F22 -> 100 | R22: =H22 -> 100 | S22: =J22 -> 8 | T22: =IFERROR(IF(I22="Minimize",F22/H22,IF(F22>0,H22/F22,IF(H22>0,1.1,F22/H22))),0) -> 1 | U22: =MIN(1.1*S22,T22*S22) -> 8 | W22: 10 | X22: =T22 -> 1 | Y22: =MIN(1.1*W22,X22*W22) -> 10 | Z22: 10 | AA22: =T22 -> 1 | AB22: =MIN(1.1*Z22,AA22*Z22) -> 10 | AC22: 10 | AD22: =T22 -> 1 | AE22: =MIN(1.1*AC22,AD22*AC22) -> 10
A23: D. Peningkatan Investasi
A24: 1 | B24: Realisasi PMN | C24: S | E24: % | F24: 96.6 | G24: 96.6 | H24: 81.78 | I24: Maximize | J24: 4 | K24: =SUM(J24:J26) -> 15 | L24: =IFERROR((MIN(1.1,(H24/G24)))*J24,0) -> 3.3863354 | M24: =SUM(L24:L26) -> 9.9734269 | N24: =IFERROR((MIN(1.1,(H24/F24)))*J24,0) -> 3.3863354 | O24: =SUM(N24:N26) -> 9.9734269 | P24: Realisasi PMN sebesar 81,78%, target tahun 2025 sebesar 96,60%. •Realisasi Penyerapan Dana sebesar 71,67% •Realisasi Penyerapan Fisik sebesar 91,89% Progress proyek WMS saat ini dalam tahap pemutakhiran kajian. | Q24: =F24 -> 96.6 | R24: =H24 -> 81.78 | S24: =J24 -> 4 | T24: =IFERROR(IF(I24="Minimize",F24/H24,IF(F24>0,H24/F24,IF(H24>0,1.1,F24/H24))),0) -> 0.84658385 | U24: =MIN(1.1*S24,T24*S24) -> 3.3863354 | W24: 4 | X24: =T24 -> 0.84658385 | Y24: =MIN(1.1*W24,X24*W24) -> 3.3863354 | Z24: 4 | AA24: =T24 -> 0.84658385 | AB24: =MIN(1.1*Z24,AA24*Z24) -> 3.3863354 | AC24: 4 | AD24: =T24 -> 0.84658385 | AE24: =MIN(1.1*AC24,AD24*AC24) -> 3.3863354
A25: 2 | B25: Monetisasi, dan/atau Pelepasan Aset Non-Inti | C25: G | E25: Rp. Miliar | F25: 1566.3405 | G25: 1566.3405 | H25: 489.39 | I25: Maximize | J25: 7 | L25: =IFERROR((MIN(1.1,(H25/G25)))*J25,0) -> 2.1870915 | N25: =IFERROR((MIN(1.1,(H25/F25)))*J25,0) -> 2.1870915 | P25: Realisasi Monetisasi, dan/atau Pelepasan Aset Non-Inti Juni 2025 tercapai 69% dari target RKAP (Real Rp114,4 Milyar, RKAP s.d Juni 2025 Rp 178,44 Milyar, Realisasi Optimalisasi Aset Rp 82,6 Milyar, tercapai lebih rendah yaitu 66% dari target RKAP s.d Juni Rp 125,59 Milyar Realisasi Divestasi Aset Rp 31,8 Milyar atau hanya tercapai 60% dari target RKAP s.d Juni Rp 52,85 Milyar | Q25: =F25 -> 1566.3405 | R25: =H25 -> 489.39 | S25: =J25 -> 7 | T25: =IFERROR(IF(I25="Minimize",F25/H25,IF(F25>0,H25/F25,IF(H25>0,1.1,F25/H25))),0) -> 0.31244165 | U25: =MIN(1.1*S25,T25*S25) -> 2.1870915 | W25: 7 | X25: =T25 -> 0.31244165 | Y25: =MIN(1.1*W25,X25*W25) -> 2.1870915 | Z25: 7 | AA25: =T25 -> 0.31244165 | AB25: =MIN(1.1*Z25,AA25*Z25) -> 2.1870915 | AC25: 7 | AD25: =T25 -> 0.31244165 | AE25: =MIN(1.1*AC25,AD25*AC25) -> 2.1870915
A26: 3 | B26: Replanting & Perluasan | C26: C | E26: Ha | F26: 3300.86 | G26: 3300.86 | H26: 3700.03 | I26: Maximize | J26: 4 | L26: =IFERROR((MIN(1.1,(H26/G26)))*J26,0) -> 4.4 | N26: =IFERROR((MIN(1.1,(H26/F26)))*J26,0) -> 4.4 | P26: Replanting & Perluasan tercapai 1.482 Ha yang merupakan perluasan areal tebu di Regional 8 berdasarkan hasil taksasi Maret 2025 pada areal bero dan optimalisasi MT24/25. Replanting karet akan dilaksanakan pada TW IV 2025, untuk Replanting sawit (Tanam Ulang) yang bersumber dari dana IP-PEN, saat ini sedang dalam tahap pengadaan untuk mekanisme pelaksanaan TU di Regional 7 dan 8 | Q26: =F26 -> 3300.86 | R26: =H26 -> 3700.03 | S26: =J26 -> 4 | T26: =IFERROR(IF(I26="Minimize",F26/H26,IF(F26>0,H26/F26,IF(H26>0,1.1,F26/H26))),0) -> 1.1209291 | U26: =MIN(1.1*S26,T26*S26) -> 4.4 | W26: 4 | X26: =T26 -> 1.1209291 | Y26: =MIN(1.1*W26,X26*W26) -> 4.4 | Z26: 4 | AA26: =T26 -> 1.1209291 | AB26: =MIN(1.1*Z26,AA26*Z26) -> 4.4 | AC26: 4 | AD26: =T26 -> 1.1209291 | AE26: =MIN(1.1*AC26,AD26*AC26) -> 4.4
A27: E. Pengembangan Talenta
A28: 1 | B28: Human Capital Transformation | C28: S | E28: % | F28: 100 | G28: 100 | H28: 99.94 | I28: Maximize | J28: 8 | K28: =J28 -> 8 | L28: =IFERROR((MIN(1.1,(H28/G28)))*J28,0) -> 7.9952 | M28: =L28 -> 7.9952 | N28: =IFERROR((MIN(1.1,(H28/F28)))*J28,0) -> 7.9952 | O28: =N28 -> 7.9952 | P28: Prosentase Bobot Skor Employee Productivity 31,75%, yang didapatkan dari:  Progress pelaksanaan Top Talent Muda dan Perempuan (Skor Diversity) tercapai 10% Skor Employee Productivity tercapai 53,49% | Q28: =F28 -> 100 | R28: =H28 -> 99.94 | S28: =J28 -> 8 | T28: =IFERROR(IF(I28="Minimize",F28/H28,IF(F28>0,H28/F28,IF(H28>0,1.1,F28/H28))),0) -> 0.9994 | U28: =MIN(1.1*S28,T28*S28) -> 7.9952 | W28: 10 | X28: =T28 -> 0.9994 | Y28: =MIN(1.1*W28,X28*W28) -> 9.994 | Z28: 10 | AA28: =T28 -> 0.9994 | AB28: =MIN(1.1*Z28,AA28*Z28) -> 9.994 | AC28: 10 | AD28: =T28 -> 0.9994 | AE28: =MIN(1.1*AC28,AD28*AC28) -> 9.994
B29: TOTAL | K29: =SUM(K8,K12,K15,K17,K24,K22,K28) -> 100 | M29: =M8+M17+M22+M24+M28+M15+M12 -> 85.369253 | O29: =O8+O17+O22+O24+O28+O12+O15 -> 81.726071 | S29: =SUM(S8:S28) -> 100 | T29: =IFERROR(U29/S29,0) -> 0.81726071 | U29: =SUM(U8:U28) -> 81.726071 | W29: =SUM(W8:W28) -> 100 | X29: =IFERROR(Y29/W29,0) -> 0.83447491 | Y29: =SUM(Y8:Y28) -> 83.447491 | Z29: =SUM(Z8:Z28) -> 100 | AA29: =IFERROR(AB29/Z29,0) -> 0.84828442 | AB29: =SUM(AB8:AB28) -> 84.828442 | AC29: =SUM(AC8:AC28) -> 100 | AD29: =IFERROR(AE29/AC29,0) -> 0.80966541 | AE29: =SUM(AE8:AE28) -> 80.966541

Sheet N1R1
A1: KEY PERFORMANCE INDICATOR (KPI) TAHUN 2025 BOARD OF REGIONAL MANAGEMENT PT PERKEBUNAN NUSANTARA I REGIONAL 1 Tahun 2025 Unaudited
A3: No. | B3: Key Performance Indicator | C3: ESG / C | D3: Satuan | E3: Polaritas | F3: Realisasi | G3: Target | I3: Skor Realisasi/ Target 2025 | K3: Target 2025 | L3: Realisasi 2025 | M3: Bobot KPI | N3: % Capaian Realisasi | O3: Skor Realisasi KPI
F4: S.d Bulan Des'25 | G4: 1 Tahun | H4: Bobot
A5: A. Nilai Ekonomi dan Sosial Untuk Indonesia
A6: A.1 Finansial
A7: 1 | B7: EBITDA Margin | C7: C | D7: % | E7: Maximize | F7: 79.36 | G7: 80.52 | H7: 15 | I7: 14.78 | K7: =G7 -> 80.52 | L7: =F7 -> 79.36 | M7: =H7 -> 15 | N7: =IFERROR(MAX(0,IF(E7="Minimize",G7/F7,IF(G7>0,F7/G7,IF(F7>0,1.1,G7/F7)))),0) -> 0.98559364 | O7: =MIN(1.1*M7,N7*M7) -> 14.783905
A8: Sub Total A.1 Finansial | H8: 15 | I8: 14.78
A9: A.2. Operasional
A10: A.3. Sosial
A11: Total A. Nilai Ekonomi dan Sosial Untuk Indonesia | H11: 15 | I11: 14.78
A12: B. Inovasi Model Bisnis
A13: 1 | B13: Implementasi Post Merger Integration dan Implementasi Integrated Management System
B14: a. Penerbitan SK BPHTB 0% | C14: C | D14: % | E14: Maximize | F14: 100 | G14: 100 | H14: 5 | I14: 5 | K14: =G14 -> 100 | L14: =F14 -> 100 | M14: =H14 -> 5 | N14: =IFERROR(MAX(0,IF(E14="Minimize",G14/F14,IF(G14>0,F14/G14,IF(F14>0,1.1,G14/F14)))),0) -> 1 | O14: =MIN(1.1*M14,N14*M14) -> 5
B15: b. Implementasi Integrated Management System | C15: C | D15: % | E15: Maximize | F15: 100 | G15: 100 | H15: 6 | I15: 6 | K15: =G15 -> 100 | L15: =F15 -> 100 | M15: =H15 -> 6 | N15: =IFERROR(MAX(0,IF(E15="Minimize",G15/F15,IF(G15>0,F15/G15,IF(F15>0,1.1,G15/F15)))),0) -> 1 | O15: =MIN(1.1*M15,N15*M15) -> 6
A16: 2 | B16: Penerbitan Surat Setoran Pajak Daerah (SSPD) Nihil | C16: C | D16: % | E16: Maximize | F16: 67 | G16: 75 | H16: 7 | I16: 6.22 | K16: =G16 -> 75 | L16: =F16 -> 67 | M16: =H16 -> 7 | N16: =IFERROR(MAX(0,IF(E16="Minimize",G16/F16,IF(G16>0,F16/G16,IF(F16>0,1.1,G16/F16)))),0) -> 0.89333333 | O16: =MIN(1.1*M16,N16*M16) -> 6.2533333
A17: 3 | B17: Sertifikasi Aset Tanah | C17: C | D17: % | E17: Maximize | F17: 86 | G17: 100 | H17: 7 | I17: 6.02 | K17: =G17 -> 100 | L17: =F17 -> 86 | M17: =H17 -> 7 | N17: =IFERROR(MAX(0,IF(E17="Minimize",G17/F17,IF(G17>0,F17/G17,IF(F17>0,1.1,G17/F17)))),0) -> 0.86 | O17: =MIN(1.1*M17,N17*M17) -> 6.02
A18: 4 | B18: Recovery Aset | C18: C | D18: Ha | E18: Maximize | F18: 7.15 | G18: 382 | H18: 7 | I18: 0.13 | K18: =G18 -> 382 | L18: =F18 -> 7.15 | M18: =H18 -> 7 | N18: =IFERROR(MAX(0,IF(E18="Minimize",G18/F18,IF(G18>0,F18/G18,IF(F18>0,1.1,G18/F18)))),0) -> 0.018717277 | O18: =MIN(1.1*M18,N18*M18) -> 0.13102094
A19: 5 | B19: Pengurusan Perizinan Berusaha Pasca Integrasi | C19: C | D19: Jumlah | E19: Maximize | F19: 32 | G19: 11 | H19: 6 | I19: 6.6 | K19: =G19 -> 11 | L19: =F19 -> 32 | M19: =H19 -> 6 | N19: =IFERROR(MAX(0,IF(E19="Minimize",G19/F19,IF(G19>0,F19/G19,IF(F19>0,1.1,G19/F19)))),0) -> 2.9090909 | O19: =MIN(1.1*M19,N19*M19) -> 6.6
A20: 6 | B20: Pemenuhan Mitigasi Risiko | C20: C | D20: % | E20: Maximize | F20: 100 | G20: 100 | H20: 5 | I20: 5 | K20: =G20 -> 100 | L20: =F20 -> 100 | M20: =H20 -> 5 | N20: =IFERROR(MAX(0,IF(E20="Minimize",G20/F20,IF(G20>0,F20/G20,IF(F20>0,1.1,G20/F20)))),0) -> 1 | O20: =MIN(1.1*M20,N20*M20) -> 5
A21: 7 | B21: Efisiensi Nilai SPPBJ dibandingkan HPS | C21: C | D21: % | E21: Maximize | F21: 8.31 | G21: 3 | H21: 3 | I21: 3.3 | K21: =G21 -> 3 | L21: =F21 -> 8.31 | M21: =H21 -> 3 | N21: =IFERROR(MAX(0,IF(E21="Minimize",G21/F21,IF(G21>0,F21/G21,IF(F21>0,1.1,G21/F21)))),0) -> 2.77 | O21: =MIN(1.1*M21,N21*M21) -> 3.3
A22: Total B. Inovasi Model Bisnis | H22: 46 | I22: 38.27
A23: C. Kepemimpinan Teknologi
A24: 1 | B24: Implementasi Aplikasi MONIKA untuk katalog rencana Optimalisasi dan Divestasi Aset | C24: C | D24: % | E24: Maximize | F24: 94 | G24: 100 | H24: 5 | I24: 4.7 | K24: =G24 -> 100 | L24: =F24 -> 94 | M24: =H24 -> 5 | N24: =IFERROR(MAX(0,IF(E24="Minimize",G24/F24,IF(G24>0,F24/G24,IF(F24>0,1.1,G24/F24)))),0) -> 0.94 | O24: =MIN(1.1*M24,N24*M24) -> 4.7
A25: Total C. Kepemimpinan Teknologi | H25: 5 | I25: 4.7
A26: D. Peningkatan Investasi
A27: 1 | B27: Monetisasi, dan/atau Pelepasan Aset Non-Inti | C27: G | D27: % | E27: Maximize | F27: 112 | G27: 100 | H27: 25 | I27: 27.5 | K27: =G27 -> 100 | L27: =F27 -> 112 | M27: =H27 -> 25 | N27: =IFERROR(MAX(0,IF(E27="Minimize",G27/F27,IF(G27>0,F27/G27,IF(F27>0,1.1,G27/F27)))),0) -> 1.12 | O27: =MIN(1.1*M27,N27*M27) -> 27.5
A28: Total C. Kepemimpinan Teknologi | H28: 25 | I28: 27.5
A29: E. Pengembangan Talenta
A30: F. Turunan KPI Direktur Bidang dan Usulan Direktorat
A31: 1 | B31: Persentase Temuan Audit Internal dan Eksternal yang ditindaklanjuti | C31: G | D31: % | E31: Maximize | F31: 61 | G31: 100 | H31: 2 | I31: 1.22 | K31: =G31 -> 100 | L31: =F31 -> 61 | M31: =H31 -> 2 | N31: =IFERROR(MAX(0,IF(E31="Minimize",G31/F31,IF(G31>0,F31/G31,IF(F31>0,1.1,G31/F31)))),0) -> 0.61 | O31: =MIN(1.1*M31,N31*M31) -> 1.22
A32: 2 | B32: Pemenuhan Permintaan Kajian (Kajian Ekonomis, Hukum, dan Risiko) terkait Divestasi Aset dan Optimalisasi Aset | C32: C | D32: % | E32: Maximize | F32: 100 | G32: 100 | H32: 2 | I32: 2 | K32: =G32 -> 100 | L32: =F32 -> 100 | M32: =H32 -> 2 | N32: =IFERROR(MAX(0,IF(E32="Minimize",G32/F32,IF(G32>0,F32/G32,IF(F32>0,1.1,G32/F32)))),0) -> 1 | O32: =MIN(1.1*M32,N32*M32) -> 2
A33: 3 | B33: Penyediaan Data Monitoring dan Evaluasi Divestasi Aset dan Optimalisasi Aset | C33: C | D33: Frekuensi | E33: Maximize | F33: 12 | G33: 12 | H33: 2 | I33: 2 | K33: =G33 -> 12 | L33: =F33 -> 12 | M33: =H33 -> 2 | N33: =IFERROR(MAX(0,IF(E33="Minimize",G33/F33,IF(G33>0,F33/G33,IF(F33>0,1.1,G33/F33)))),0) -> 1 | O33: =MIN(1.1*M33,N33*M33) -> 2
A34: 4 | B34: Penyelesaian Administrasi KSO Sawit dan KSO Tebu | C34: C | D34: % | E34: Maximize | F34: 100 | G34: 100 | H34: 3 | I34: 3 | K34: =G34 -> 100 | L34: =F34 -> 100 | M34: =H34 -> 3 | N34: =IFERROR(MAX(0,IF(E34="Minimize",G34/F34,IF(G34>0,F34/G34,IF(F34>0,1.1,G34/F34)))),0) -> 1 | O34: =MIN(1.1*M34,N34*M34) -> 3
A35: Total C. Kepemimpinan Teknologi | H35: 9 | I35: 8.22
B36: TOTAL | H36: 100 | I36: 93.48 | M36: =SUM(M4:M35) -> 100 | N36: =IFERROR(O36/M36,0) -> 0.93508259 | O36: =SUM(O4:O35) -> 93.508259
A38: CASCADE REGION HEAD & SEVP — N1R1 (EEI di Finansial)
A39: No. | B39: Key Performance Indicator | C39: Perspektif | D39: Satuan | E39: Target | F39: Polaritas | G39: Bobot Awal | K39: % Capaian | L39: RH Bobot | M39: RH Skor | N39: SEVP Op Bobot | O39: SEVP Op Skor | P39: SEVP BS Bobot | Q39: SEVP BS Skor
A40: 1 | B40: =B7 -> EBITDA Margin | C40: Finansial | D40: =D7 -> % | E40: =G7 -> 80.52 | F40: =E7 -> Maximize | G40: =H7 -> 15 | K40: =N7 -> 0.98559364 | L40: 25 | M40: =MIN(1.1*L40,K40*L40) -> 24.639841 | N40: 15 | O40: =MIN(1.1*N40,K40*N40) -> 14.783905 | P40: 35 | Q40: =MIN(1.1*P40,K40*P40) -> 34.495777
B41: Subtotal Finansial | G41: =SUM(G40) -> 15 | L41: =SUM(L40) -> 25 | M41: =SUM(M40) -> 24.639841 | N41: =SUM(N40) -> 15 | O41: =SUM(O40) -> 14.783905 | P41: =SUM(P40) -> 35 | Q41: =SUM(Q40) -> 34.495777
A42: 2 | B42: =B31 -> Persentase Temuan Audit Internal dan Eksternal yang ditindaklanjuti | C42: Operasional | D42: =D31 -> % | E42: =G31 -> 100 | F42: =E31 -> Maximize | G42: =H31 -> 2 | K42: =N31 -> 0.61 | L42: 6 | M42: =MIN(1.1*L42,K42*L42) -> 3.66 | N42: 8 | O42: =MIN(1.1*N42,K42*N42) -> 4.88 | P42: 4 | Q42: =MIN(1.1*P42,K42*P42) -> 2.44
A43: 3 | B43: =B32 -> Pemenuhan Permintaan Kajian (Kajian Ekonomis, Hukum, dan Risiko) terkait Divestasi Aset dan Optimalisasi Aset | C43: Operasional | D43: =D32 -> % | E43: =G32 -> 100 | F43: =E32 -> Maximize | G43: =H32 -> 2 | K43: =N32 -> 1 | L43: 6 | M43: =MIN(1.1*L43,K43*L43) -> 6 | N43: 8 | O43: =MIN(1.1*N43,K43*N43) -> 8 | P43: 3 | Q43: =MIN(1.1*P43,K43*P43) -> 3
A44: 4 | B44: =B33 -> Penyediaan Data Monitoring dan Evaluasi Divestasi Aset dan Optimalisasi Aset | C44: Operasional | D44: =D33 -> Frekuensi | E44: =G33 -> 12 | F44: =E33 -> Maximize | G44: =H33 -> 2 | K44: =N33 -> 1 | L44: 5 | M44: =MIN(1.1*L44,K44*L44) -> 5 | N44: 8 | O44: =MIN(1.1*N44,K44*N44) -> 8 | P44: 3 | Q44: =MIN(1.1*P44,K44*P44) -> 3
A45: 5 | B45: =B34 -> Penyelesaian Administrasi KSO Sawit dan KSO Tebu | C45: Operasional | D45: =D34 -> % | E45: =G34 -> 100 | F45: =E34 -> Maximize | G45: =H34 -> 3 | K45: =N34 -> 1 | L45: 8 | M45: =MIN(1.1*L45,K45*L45) -> 8 | N45: 11 | O45: =MIN(1.1*N45,K45*N45) -> 11 | P45: 5 | Q45: =MIN(1.1*P45,K45*P45) -> 5
B46: Subtotal Operasional | G46: =SUM(G42:G45) -> 9 | L46: =SUM(L42:L45) -> 25 | M46: =SUM(M42:M45) -> 22.66 | N46: =SUM(N42:N45) -> 35 | O46: =SUM(O42:O45) -> 31.88 | P46: =SUM(P42:P45) -> 15 | Q46: =SUM(Q42:Q45) -> 13.44
A47: 6 | B47: =B14 -> a. Penerbitan SK BPHTB 0% | C47: Inovasi Model Bisnis | D47: =D14 -> % | E47: =G14 -> 100 | F47: =E14 -> Maximize | G47: =H14 -> 5 | K47: =N14 -> 1 | L47: 2 | M47: =MIN(1.1*L47,K47*L47) -> 2 | N47: 2 | O47: =MIN(1.1*N47,K47*N47) -> 2 | P47: 2 | Q47: =MIN(1.1*P47,K47*P47) -> 2
A48: 7 | B48: =B15 -> b. Implementasi Integrated Management System | C48: Inovasi Model Bisnis | D48: =D15 -> % | E48: =G15 -> 100 | F48: =E15 -> Maximize | G48: =H15 -> 6 | K48: =N15 -> 1 | L48: 3 | M48: =MIN(1.1*L48,K48*L48) -> 3 | N48: 3 | O48: =MIN(1.1*N48,K48*N48) -> 3 | P48: 3 | Q48: =MIN(1.1*P48,K48*P48) -> 3
A49: 8 | B49: =B16 -> Penerbitan Surat Setoran Pajak Daerah (SSPD) Nihil | C49: Inovasi Model Bisnis | D49: =D16 -> % | E49: =G16 -> 75 | F49: =E16 -> Maximize | G49: =H16 -> 7 | K49: =N16 -> 0.89333333 | L49: 3 | M49: =MIN(1.1*L49,K49*L49) -> 2.68 | N49: 3 | O49: =MIN(1.1*N49,K49*N49) -> 2.68 | P49: 3 | Q49: =MIN(1.1*P49,K49*P49) -> 2.68
A50: 9 | B50: =B17 -> Sertifikasi Aset Tanah | C50: Inovasi Model Bisnis | D50: =D17 -> % | E50: =G17 -> 100 | F50: =E17 -> Maximize | G50: =H17 -> 7 | K50: =N17 -> 0.86 | L50: 3 | M50: =MIN(1.1*L50,K50*L50) -> 2.58 | N50: 3 | O50: =MIN(1.1*N50,K50*N50) -> 2.58 | P50: 3 | Q50: =MIN(1.1*P50,K50*P50) -> 2.58
A51: 10 | B51: =B18 -> Recovery Aset | C51: Inovasi Model Bisnis | D51: =D18 -> Ha | E51: =G18 -> 382 | F51: =E18 -> Maximize | G51: =H18 -> 7 | K51: =N18 -> 0.018717277 | L51: 3 | M51: =MIN(1.1*L51,K51*L51) -> 0.056151832 | N51: 3 | O51: =MIN(1.1*N51,K51*N51) -> 0.056151832 | P51: 3 | Q51: =MIN(1.1*P51,K51*P51) -> 0.056151832
A52: 11 | B52: =B19 -> Pengurusan Perizinan Berusaha Pasca Integrasi | C52: Inovasi Model Bisnis | D52: =D19 -> Jumlah | E52: =G19 -> 11 | F52: =E19 -> Maximize | G52: =H19 -> 6 | K52: =N19 -> 2.9090909 | L52: 3 | M52: =MIN(1.1*L52,K52*L52) -> 3.3 | N52: 3 | O52: =MIN(1.1*N52,K52*N52) -> 3.3 | P52: 3 | Q52: =MIN(1.1*P52,K52*P52) -> 3.3
A53: 12 | B53: =B20 -> Pemenuhan Mitigasi Risiko | C53: Inovasi Model Bisnis | D53: =D20 -> % | E53: =G20 -> 100 | F53: =E20 -> Maximize | G53: =H20 -> 5 | K53: =N20 -> 1 | L53: 2 | M53: =MIN(1.1*L53,K53*L53) -> 2 | N53: 2 | O53: =MIN(1.1*N53,K53*N53) -> 2 | P53: 2 | Q53: =MIN(1.1*P53,K53*P53) -> 2
A54: 13 | B54: =B21 -> Efisiensi Nilai SPPBJ dibandingkan HPS | C54: Inovasi Model Bisnis | D54: =D21 -> % | E54: =G21 -> 3 | F54: =E21 -> Maximize | G54: =H21 -> 3 | K54: =N21 -> 2.77 | L54: 1 | M54: =MIN(1.1*L54,K54*L54) -> 1.1 | N54: 1 | O54: =MIN(1.1*N54,K54*N54) -> 1.1 | P54: 1 | Q54: =MIN(1.1*P54,K54*P54) -> 1.1
B55: Subtotal Inovasi Model Bisnis | G55: =SUM(G47:G54) -> 46 | L55: =SUM(L47:L54) -> 20 | M55: =SUM(M47:M54) -> 16.716152 | N55: =SUM(N47:N54) -> 20 | O55: =SUM(O47:O54) -> 16.716152 | P55: =SUM(P47:P54) -> 20 | Q55: =SUM(Q47:Q54) -> 16.716152
A56: 14 | B56: =B24 -> Implementasi Aplikasi MONIKA untuk katalog rencana Optimalisasi dan Divestasi Aset | C56: Kepemimpinan Teknologi | D56: =D24 -> % | E56: =G24 -> 100 | F56: =E24 -> Maximize | G56: =H24 -> 5 | K56: =N24 -> 0.94 | L56: 10 | M56: =MIN(1.1*L56,K56*L56) -> 9.4 | N56: 10 | O56: =MIN(1.1*N56,K56*N56) -> 9.4 | P56: 10 | Q56: =MIN(1.1*P56,K56*P56) -> 9.4
B57: Subtotal Kepemimpinan Teknologi | G57: =SUM(G56) -> 5 | L57: =SUM(L56) -> 10 | M57: =SUM(M56) -> 9.4 | N57: =SUM(N56) -> 10 | O57: =SUM(O56) -> 9.4 | P57: =SUM(P56) -> 10 | Q57: =SUM(Q56) -> 9.4
A58: 15 | B58: =B27 -> Monetisasi, dan/atau Pelepasan Aset Non-Inti | C58: Peningkatan Investasi | D58: =D27 -> % | E58: =G27 -> 100 | F58: =E27 -> Maximize | G58: =H27 -> 25 | K58: =N27 -> 1.12 | L58: 20 | M58: =MIN(1.1*L58,K58*L58) -> 22 | N58: 20 | O58: =MIN(1.1*N58,K58*N58) -> 22 | P58: 20 | Q58: =MIN(1.1*P58,K58*P58) -> 22
B59: Subtotal Peningkatan Investasi | G59: =SUM(G58) -> 25 | L59: =SUM(L58) -> 20 | M59: =SUM(M58) -> 22 | N59: =SUM(N58) -> 20 | O59: =SUM(O58) -> 22 | P59: =SUM(P58) -> 20 | Q59: =SUM(Q58) -> 22
B60: TOTAL | G60: =G41+G46+G55+G57+G59 -> 100 | L60: =L41+L46+L55+L57+L59 -> 100 | M60: =M41+M46+M55+M57+M59 -> 95.415993 | N60: =N41+N46+N55+N57+N59 -> 100 | O60: =O41+O46+O55+O57+O59 -> 94.780056 | P60: =P41+P46+P55+P57+P59 -> 100 | Q60: =Q41+Q46+Q55+Q57+Q59 -> 96.051929

Sheet N1R2
A2: No. | B2: Key Performance Indicator | C2: ESG / C | D2: Satuan | E2: Polaritas | F2: Realisasi | G2: Target | I2: Skor Realisasi/ Target 2025 | K2: Target 2025 | L2: Realisasi 2025 | M2: Bobot KPI | N2: % Capaian Realisasi | O2: Skor Realisasi KPI
F3: S.d Bulan Des'25 | G3: 1 Tahun | H3: Bobot
A4: A. Nilai Ekonomi dan Sosial Untuk Indonesia
A5: A.1 Finansial
A6: 1 | B6: EBITDA Margin | C6: C | D6: % | E6: Maximize | F6: 18.82 | G6: 5.4 | H6: 15 | I6: 16.5 | K6: =G6 -> 5.4 | L6: =F6 -> 18.82 | M6: =H6 -> 15 | N6: =IFERROR(MAX(0,IF(E6="Minimize",G6/F6,IF(G6>0,F6/G6,IF(F6>0,1.1,G6/F6)))),0) -> 3.4851852 | O6: =MIN(1.1*M6,N6*M6) -> 16.5
A7: Sub Total A.1 Finansial | H7: 15 | I7: 16.5
A8: A.2. Operasional
A9: 3 | B9: Cash Cost Komoditi Utama
B10: a. Cash Cost Karet | C10: C | D10: Rp/Kg | E10: Minimize | F10: 24884 | G10: 21436 | H10: 7 | I10: 6.03 | K10: =G10 -> 21436 | L10: =F10 -> 24884 | M10: =H10 -> 7 | N10: =IFERROR(MAX(0,IF(E10="Minimize",G10/F10,IF(G10>0,F10/G10,IF(F10>0,1.1,G10/F10)))),0) -> 0.86143707 | O10: =MIN(1.1*M10,N10*M10) -> 6.0300595
B11: b. Cash Cost Teh | C11: C | D11: Rp/Kg | E11: Minimize | F11: 20253 | G11: 23034 | H11: 4 | I11: 4.4 | K11: =G11 -> 23034 | L11: =F11 -> 20253 | M11: =H11 -> 4 | N11: =IFERROR(MAX(0,IF(E11="Minimize",G11/F11,IF(G11>0,F11/G11,IF(F11>0,1.1,G11/F11)))),0) -> 1.137313 | O11: =MIN(1.1*M11,N11*M11) -> 4.4
A12: 4 | B12: Produktivitas Komoditi Utama
B13: a. Produktivitas Karet | C13: C | D13: Ton/Ha | E13: Maximize | F13: 1.06 | G13: 1.32 | H13: 7 | I13: 5.62 | K13: =G13 -> 1.32 | L13: =F13 -> 1.06 | M13: =H13 -> 7 | N13: =IFERROR(MAX(0,IF(E13="Minimize",G13/F13,IF(G13>0,F13/G13,IF(F13>0,1.1,G13/F13)))),0) -> 0.8030303 | O13: =MIN(1.1*M13,N13*M13) -> 5.6212121
B14: b. Produktivitas Teh | C14: C | D14: Ton/Ha | E14: Maximize | F14: 2,02 | G14: 2.17 | H14: 4 | I14: 3.72 | K14: =G14 -> 2.17 | L14: =F14 -> 2,02 | M14: =H14 -> 4 | N14: =IFERROR(MAX(0,IF(E14="Minimize",G14/F14,IF(G14>0,F14/G14,IF(F14>0,1.1,G14/F14)))),0) -> 0 | O14: =MIN(1.1*M14,N14*M14) -> 0
A15: 5 | B15: Kualitas Karet Mutu Tinggi (RSS 1) | C15: C | D15: % | E15: Maximize | F15: 97.35 | G15: 98 | H15: 5 | I15: 4.97 | K15: =G15 -> 98 | L15: =F15 -> 97.35 | M15: =H15 -> 5 | N15: =IFERROR(MAX(0,IF(E15="Minimize",G15/F15,IF(G15>0,F15/G15,IF(F15>0,1.1,G15/F15)))),0) -> 0.99336735 | O15: =MIN(1.1*M15,N15*M15) -> 4.9668367
A16: 6 | B16: Kualitas Teh Mutu Tinggi (Mutu 1)
B17: a. Orthodox | C17: C | D17: % | E17: Maximize | F17: 49.63 | G17: 62 | H17: 3 | I17: 2.4 | K17: =G17 -> 62 | L17: =F17 -> 49.63 | M17: =H17 -> 3 | N17: =IFERROR(MAX(0,IF(E17="Minimize",G17/F17,IF(G17>0,F17/G17,IF(F17>0,1.1,G17/F17)))),0) -> 0.80048387 | O17: =MIN(1.1*M17,N17*M17) -> 2.4014516
B18: b. CTC | C18: C | D18: % | E18: Maximize | F18: 60.18 | G18: 65.4 | H18: 3 | I18: 2.76 | K18: =G18 -> 65.4 | L18: =F18 -> 60.18 | M18: =H18 -> 3 | N18: =IFERROR(MAX(0,IF(E18="Minimize",G18/F18,IF(G18>0,F18/G18,IF(F18>0,1.1,G18/F18)))),0) -> 0.92018349 | O18: =MIN(1.1*M18,N18*M18) -> 2.7605505
A19: Sub Total A.2. Operasional | H19: 33 | I19: 29.91
A20: A.3. Sosial
A21: Total A. Nilai Ekonomi dan Sosial Untuk Indonesia | H21: 48 | I21: 46.41
A22: B. Inovasi Model Bisnis
A23: 1 | B23: Implementasi Post Merger Integration dan Intergrated Management System
B24: a. Penerbitan SK BPHTB 0% | C24: C | D24: % | E24: Maximize | F24: 100 | G24: 100 | H24: 3 | I24: 3 | K24: =G24 -> 100 | L24: =F24 -> 100 | M24: =H24 -> 3 | N24: =IFERROR(MAX(0,IF(E24="Minimize",G24/F24,IF(G24>0,F24/G24,IF(F24>0,1.1,G24/F24)))),0) -> 1 | O24: =MIN(1.1*M24,N24*M24) -> 3
B25: b. Implementasi Integrated Management System | C25: C | D25: % | E25: Maximize | F25: 100 | G25: 100 | H25: 3 | I25: 3 | K25: =G25 -> 100 | L25: =F25 -> 100 | M25: =H25 -> 3 | N25: =IFERROR(MAX(0,IF(E25="Minimize",G25/F25,IF(G25>0,F25/G25,IF(F25>0,1.1,G25/F25)))),0) -> 1 | O25: =MIN(1.1*M25,N25*M25) -> 3
A26: 2 | B26: Total Revenue dari Pemasaran Produk (Komoditi) | C26: C | D26: Rp Miliar | E26: Maximize | F26: 684 | G26: 868 | H26: 1.5 | I26: 2.23 | K26: =G26 -> 868 | L26: =F26 -> 684 | M26: =H26 -> 1.5 | N26: =IFERROR(MAX(0,IF(E26="Minimize",G26/F26,IF(G26>0,F26/G26,IF(F26>0,1.1,G26/F26)))),0) -> 0.78801843 | O26: =MIN(1.1*M26,N26*M26) -> 1.1820276
B27: Total Revenue dari Pemasaran Produk (Retail) | D27: Rp Miliar | E27: Maximize | F27: 41 | G27: 108 | H27: 1.5 | K27: =G27 -> 108 | L27: =F27 -> 41 | M27: =H27 -> 1.5 | N27: =IFERROR(MAX(0,IF(E27="Minimize",G27/F27,IF(G27>0,F27/G27,IF(F27>0,1.1,G27/F27)))),0) -> 0.37962963 | O27: =MIN(1.1*M27,N27*M27) -> 0.56944444
A28: 3 | B28: Total Revenue dari Agrowisata | C28: C | D28: Rp Miliar | E28: Maximize | F28: 103 | G28: 153 | H28: 3 | I28: 2.01 | K28: =G28 -> 153 | L28: =F28 -> 103 | M28: =H28 -> 3 | N28: =IFERROR(MAX(0,IF(E28="Minimize",G28/F28,IF(G28>0,F28/G28,IF(F28>0,1.1,G28/F28)))),0) -> 0.67320261 | O28: =MIN(1.1*M28,N28*M28) -> 2.0196078
A29: 4 | B29: Penerbitan Surat Setoran Pajak Daerah Nihil | C29: C | D29: % | E29: Maximize | F29: 56 | G29: 75 | H29: 3 | I29: 2.25 | K29: =G29 -> 75 | L29: =F29 -> 56 | M29: =H29 -> 3 | N29: =IFERROR(MAX(0,IF(E29="Minimize",G29/F29,IF(G29>0,F29/G29,IF(F29>0,1.1,G29/F29)))),0) -> 0.74666667 | O29: =MIN(1.1*M29,N29*M29) -> 2.24
A30: 5 | B30: Sertifikasi Aset Tanah | C30: C | D30: % | E30: Maximize | F30: 77 | G30: 100 | H30: 3 | I30: 2.31 | K30: =G30 -> 100 | L30: =F30 -> 77 | M30: =H30 -> 3 | N30: =IFERROR(MAX(0,IF(E30="Minimize",G30/F30,IF(G30>0,F30/G30,IF(F30>0,1.1,G30/F30)))),0) -> 0.77 | O30: =MIN(1.1*M30,N30*M30) -> 2.31
A31: 6 | B31: Recovery Aset | C31: C | D31: Ha | E31: Maximize | F31: 320.5 | G31: 233 | H31: 3 | I31: 3.3 | K31: =G31 -> 233 | L31: =F31 -> 320.5 | M31: =H31 -> 3 | N31: =IFERROR(MAX(0,IF(E31="Minimize",G31/F31,IF(G31>0,F31/G31,IF(F31>0,1.1,G31/F31)))),0) -> 1.3755365 | O31: =MIN(1.1*M31,N31*M31) -> 3.3
A32: 7 | B32: Pengurusan Perizinan Berusaha Pasca Integrasi | C32: C | D32: Jumlah | E32: Maximize | F32: 71 | G32: 19 | H32: 3 | I32: 3.3 | K32: =G32 -> 19 | L32: =F32 -> 71 | M32: =H32 -> 3 | N32: =IFERROR(MAX(0,IF(E32="Minimize",G32/F32,IF(G32>0,F32/G32,IF(F32>0,1.1,G32/F32)))),0) -> 3.7368421 | O32: =MIN(1.1*M32,N32*M32) -> 3.3
A33: 8 | B33: Pemenuhan Mitigasi Risiko | C33: C | D33: % | E33: Maximize | F33: 100 | G33: 100 | H33: 3 | I33: 3 | K33: =G33 -> 100 | L33: =F33 -> 100 | M33: =H33 -> 3 | N33: =IFERROR(MAX(0,IF(E33="Minimize",G33/F33,IF(G33>0,F33/G33,IF(F33>0,1.1,G33/F33)))),0) -> 1 | O33: =MIN(1.1*M33,N33*M33) -> 3
A34: 9 | B34: Efisiensi Nilai SPPBJ dibandingkan HPS | C34: C | D34: % | E34: Maximize | F34: 2.58 | G34: 3 | H34: 3 | I34: 2.58 | K34: =G34 -> 3 | L34: =F34 -> 2.58 | M34: =H34 -> 3 | N34: =IFERROR(MAX(0,IF(E34="Minimize",G34/F34,IF(G34>0,F34/G34,IF(F34>0,1.1,G34/F34)))),0) -> 0.86 | O34: =MIN(1.1*M34,N34*M34) -> 2.58
A35: Total B. Inovasi Model Bisnis | H35: 30 | I35: 26.98
A36: C. Kepemimpinan Teknologi
A37: 1 | B37: Implementasi Aplikasi MONIKA untuk katalog rencana Optimalisasi dan Divestasi Aset | C37: C | D37: % | E37: Maximize | F37: 95 | G37: 100 | H37: 3 | I37: 2.85 | K37: =G37 -> 100 | L37: =F37 -> 95 | M37: =H37 -> 3 | N37: =IFERROR(MAX(0,IF(E37="Minimize",G37/F37,IF(G37>0,F37/G37,IF(F37>0,1.1,G37/F37)))),0) -> 0.95 | O37: =MIN(1.1*M37,N37*M37) -> 2.85
A38: 2 | B38: Implementasi Aplikasi DFARM Teh | C38: C | D38: % | E38: Maximize | F38: 50.49 | G38: 100 | H38: 3 | I38: 1.51 | K38: =G38 -> 100 | L38: =F38 -> 50.49 | M38: =H38 -> 3 | N38: =IFERROR(MAX(0,IF(E38="Minimize",G38/F38,IF(G38>0,F38/G38,IF(F38>0,1.1,G38/F38)))),0) -> 0.5049 | O38: =MIN(1.1*M38,N38*M38) -> 1.5147
A39: 3 | B39: Implementasi Aplikasi DFARM Karet | C39: C | D39: % | E39: Maximize | F39: 64.33 | G39: 100 | H39: 3 | I39: 1.93 | K39: =G39 -> 100 | L39: =F39 -> 64.33 | M39: =H39 -> 3 | N39: =IFERROR(MAX(0,IF(E39="Minimize",G39/F39,IF(G39>0,F39/G39,IF(F39>0,1.1,G39/F39)))),0) -> 0.6433 | O39: =MIN(1.1*M39,N39*M39) -> 1.9299
A40: Total C. Kepemimpinan Teknologi | H40: 9 | I40: 6.29
A41: D. Peningkatan Investasi
A42: 1 | B42: Monetisasi, dan/atau Pelepasan Aset Non-Inti | C42: G | D42: % | E42: Maximize | F42: 46 | G42: 100 | H42: 5 | I42: 2.32 | K42: =G42 -> 100 | L42: =F42 -> 46 | M42: =H42 -> 5 | N42: =IFERROR(MAX(0,IF(E42="Minimize",G42/F42,IF(G42>0,F42/G42,IF(F42>0,1.1,G42/F42)))),0) -> 0.46 | O42: =MIN(1.1*M42,N42*M42) -> 2.3
A43: Total D. Peningkatan Investasi | H43: 5 | I43: 2.32
A44: E. Pengembangan Talenta
A45: F. Turunan KPI Direktur Bidang dan Usulan Direktorat
A46: 1 | B46: Persentase Temuan Audit Internal dan Eksternal yang ditindaklanjuti | C46: G | D46: % | E46: Maximize | F46: 98 | G46: 100 | H46: 2 | I46: 1.96 | K46: =G46 -> 100 | L46: =F46 -> 98 | M46: =H46 -> 2 | N46: =IFERROR(MAX(0,IF(E46="Minimize",G46/F46,IF(G46>0,F46/G46,IF(F46>0,1.1,G46/F46)))),0) -> 0.98 | O46: =MIN(1.1*M46,N46*M46) -> 1.96
A47: 2 | B47: Pemenuhan Permintaan Kajian (Kajian Ekonomis, Hukum, dan Risiko) terkait Divestasi Aset dan Optimalisasi Aset | C47: C | D47: % | E47: Maximize | F47: 100 | G47: 100 | H47: 2 | I47: 2 | K47: =G47 -> 100 | L47: =F47 -> 100 | M47: =H47 -> 2 | N47: =IFERROR(MAX(0,IF(E47="Minimize",G47/F47,IF(G47>0,F47/G47,IF(F47>0,1.1,G47/F47)))),0) -> 1 | O47: =MIN(1.1*M47,N47*M47) -> 2
A48: 3 | B48: Penyediaan Data Monitoring dan Evaluasi Divestasi Aset, Optimalisasi Aset dan Agrowisata | C48: C | D48: Frekuensi | E48: Maximize | F48: 12 | G48: 12 | H48: 2 | I48: 2 | K48: =G48 -> 12 | L48: =F48 -> 12 | M48: =H48 -> 2 | N48: =IFERROR(MAX(0,IF(E48="Minimize",G48/F48,IF(G48>0,F48/G48,IF(F48>0,1.1,G48/F48)))),0) -> 1 | O48: =MIN(1.1*M48,N48*M48) -> 2
A49: 4 | B49: Penyelesaian Administrasi KSO Sawit | C49: C | D49: % | E49: Maximize | F49: 100 | G49: 100 | H49: 2 | I49: 2 | K49: =G49 -> 100 | L49: =F49 -> 100 | M49: =H49 -> 2 | N49: =IFERROR(MAX(0,IF(E49="Minimize",G49/F49,IF(G49>0,F49/G49,IF(F49>0,1.1,G49/F49)))),0) -> 1 | O49: =MIN(1.1*M49,N49*M49) -> 2
A50: Total F. Turunan KPI Direktur Bidang dan Usulan Direktorat | H50: 8 | I50: 7.96
B51: TOTAL | H51: 100 | I51: 89.96 | M51: =SUM(M3:M50) -> 100 | N51: =IFERROR(O51/M51,0) -> 0.8573579 | O51: =SUM(O3:O50) -> 85.73579
A53: CASCADE REGION HEAD & SEVP — N1R2 (EEI di Finansial)
A54: No. | B54: Key Performance Indicator | C54: Perspektif | D54: Satuan | E54: Target | F54: Polaritas | G54: Bobot Awal | K54: % Capaian | L54: RH Bobot | M54: RH Skor | N54: SEVP Op Bobot | O54: SEVP Op Skor | P54: SEVP BS Bobot | Q54: SEVP BS Skor
A55: 1 | B55: =B6 -> EBITDA Margin | C55: Finansial | D55: =D6 -> % | E55: =G6 -> 5.4 | F55: =E6 -> Maximize | G55: =H6 -> 15 | K55: =N6 -> 3.4851852 | L55: 25 | M55: =MIN(1.1*L55,K55*L55) -> 27.5 | N55: 15 | O55: =MIN(1.1*N55,K55*N55) -> 16.5 | P55: 35 | Q55: =MIN(1.1*P55,K55*P55) -> 38.5
B56: Subtotal Finansial | G56: =SUM(G55) -> 15 | L56: =SUM(L55) -> 25 | M56: =SUM(M55) -> 27.5 | N56: =SUM(N55) -> 15 | O56: =SUM(O55) -> 16.5 | P56: =SUM(P55) -> 35 | Q56: =SUM(Q55) -> 38.5
A57: 2 | B57: =B10 -> a. Cash Cost Karet | C57: Operasional | D57: =D10 -> Rp/Kg | E57: =G10 -> 21436 | F57: =E10 -> Minimize | G57: =H10 -> 7 | K57: =N10 -> 0.86143707 | L57: 4 | M57: =MIN(1.1*L57,K57*L57) -> 3.4457483 | N57: 6 | O57: =MIN(1.1*N57,K57*N57) -> 5.1686224 | P57: 3 | Q57: =MIN(1.1*P57,K57*P57) -> 2.5843112
A58: 3 | B58: =B11 -> b. Cash Cost Teh | C58: Operasional | D58: =D11 -> Rp/Kg | E58: =G11 -> 23034 | F58: =E11 -> Minimize | G58: =H11 -> 4 | K58: =N11 -> 1.137313 | L58: 3 | M58: =MIN(1.1*L58,K58*L58) -> 3.3 | N58: 3 | O58: =MIN(1.1*N58,K58*N58) -> 3.3 | P58: 1 | Q58: =MIN(1.1*P58,K58*P58) -> 1.1
A59: 4 | B59: =B13 -> a. Produktivitas Karet | C59: Operasional | D59: =D13 -> Ton/Ha | E59: =G13 -> 1.32 | F59: =E13 -> Maximize | G59: =H13 -> 7 | K59: =N13 -> 0.8030303 | L59: 4 | M59: =MIN(1.1*L59,K59*L59) -> 3.2121212 | N59: 6 | O59: =MIN(1.1*N59,K59*N59) -> 4.8181818 | P59: 2 | Q59: =MIN(1.1*P59,K59*P59) -> 1.6060606
A60: 5 | B60: =B14 -> b. Produktivitas Teh | C60: Operasional | D60: =D14 -> Ton/Ha | E60: =G14 -> 2.17 | F60: =E14 -> Maximize | G60: =H14 -> 4 | K60: =N14 -> 0 | L60: 3 | M60: =MIN(1.1*L60,K60*L60) -> 0 | N60: 3 | O60: =MIN(1.1*N60,K60*N60) -> 0 | P60: 1 | Q60: =MIN(1.1*P60,K60*P60) -> 0
A61: 6 | B61: =B15 -> Kualitas Karet Mutu Tinggi (RSS 1) | C61: Operasional | D61: =D15 -> % | E61: =G15 -> 98 | F61: =E15 -> Maximize | G61: =H15 -> 5 | K61: =N15 -> 0.99336735 | L61: 3 | M61: =MIN(1.1*L61,K61*L61) -> 2.980102 | N61: 4 | O61: =MIN(1.1*N61,K61*N61) -> 3.9734694 | P61: 2 | Q61: =MIN(1.1*P61,K61*P61) -> 1.9867347
A62: 7 | B62: =B17 -> a. Orthodox | C62: Operasional | D62: =D17 -> % | E62: =G17 -> 62 | F62: =E17 -> Maximize | G62: =H17 -> 3 | K62: =N17 -> 0.80048387 | L62: 2 | M62: =MIN(1.1*L62,K62*L62) -> 1.6009677 | N62: 3 | O62: =MIN(1.1*N62,K62*N62) -> 2.4014516 | P62: 1 | Q62: =MIN(1.1*P62,K62*P62) -> 0.80048387
A63: 8 | B63: =B18 -> b. CTC | C63: Operasional | D63: =D18 -> % | E63: =G18 -> 65.4 | F63: =E18 -> Maximize | G63: =H18 -> 3 | K63: =N18 -> 0.92018349 | L63: 2 | M63: =MIN(1.1*L63,K63*L63) -> 1.840367 | N63: 2 | O63: =MIN(1.1*N63,K63*N63) -> 1.840367 | P63: 1 | Q63: =MIN(1.1*P63,K63*P63) -> 0.92018349
A64: 9 | B64: =B46 -> Persentase Temuan Audit Internal dan Eksternal yang ditindaklanjuti | C64: Operasional | D64: =D46 -> % | E64: =G46 -> 100 | F64: =E46 -> Maximize | G64: =H46 -> 2 | K64: =N46 -> 0.98 | L64: 1 | M64: =MIN(1.1*L64,K64*L64) -> 0.98 | N64: 2 | O64: =MIN(1.1*N64,K64*N64) -> 1.96 | P64: 1 | Q64: =MIN(1.1*P64,K64*P64) -> 0.98
A65: 10 | B65: =B47 -> Pemenuhan Permintaan Kajian (Kajian Ekonomis, Hukum, dan Risiko) terkait Divestasi Aset dan Optimalisasi Aset | C65: Operasional | D65: =D47 -> % | E65: =G47 -> 100 | F65: =E47 -> Maximize | G65: =H47 -> 2 | K65: =N47 -> 1 | L65: 1 | M65: =MIN(1.1*L65,K65*L65) -> 1 | N65: 2 | O65: =MIN(1.1*N65,K65*N65) -> 2 | P65: 1 | Q65: =MIN(1.1*P65,K65*P65) -> 1
A66: 11 | B66: =B48 -> Penyediaan Data Monitoring dan Evaluasi Divestasi Aset, Optimalisasi Aset dan Agrowisata | C66: Operasional | D66: =D48 -> Frekuensi | E66: =G48 -> 12 | F66: =E48 -> Maximize | G66: =H48 -> 2 | K66: =N48 -> 1 | L66: 1 | M66: =MIN(1.1*L66,K66*L66) -> 1 | N66: 2 | O66: =MIN(1.1*N66,K66*N66) -> 2 | P66: 1 | Q66: =MIN(1.1*P66,K66*P66) -> 1
A67: 12 | B67: =B49 -> Penyelesaian Administrasi KSO Sawit | C67: Operasional | D67: =D49 -> % | E67: =G49 -> 100 | F67: =E49 -> Maximize | G67: =H49 -> 2 | K67: =N49 -> 1 | L67: 1 | M67: =MIN(1.1*L67,K67*L67) -> 1 | N67: 2 | O67: =MIN(1.1*N67,K67*N67) -> 2 | P67: 1 | Q67: =MIN(1.1*P67,K67*P67) -> 1
B68: Subtotal Operasional | G68: =SUM(G57:G67) -> 41 | L68: =SUM(L57:L67) -> 25 | M68: =SUM(M57:M67) -> 20.359306 | N68: =SUM(N57:N67) -> 35 | O68: =SUM(O57:O67) -> 29.462092 | P68: =SUM(P57:P67) -> 15 | Q68: =SUM(Q57:Q67) -> 12.977774
A69: 13 | B69: =B24 -> a. Penerbitan SK BPHTB 0% | C69: Inovasi Model Bisnis | D69: =D24 -> % | E69: =G24 -> 100 | F69: =E24 -> Maximize | G69: =H24 -> 3 | K69: =N24 -> 1 | L69: 2 | M69: =MIN(1.1*L69,K69*L69) -> 2 | N69: 2 | O69: =MIN(1.1*N69,K69*N69) -> 2 | P69: 2 | Q69: =MIN(1.1*P69,K69*P69) -> 2
A70: 14 | B70: =B25 -> b. Implementasi Integrated Management System | C70: Inovasi Model Bisnis | D70: =D25 -> % | E70: =G25 -> 100 | F70: =E25 -> Maximize | G70: =H25 -> 3 | K70: =N25 -> 1 | L70: 2 | M70: =MIN(1.1*L70,K70*L70) -> 2 | N70: 2 | O70: =MIN(1.1*N70,K70*N70) -> 2 | P70: 2 | Q70: =MIN(1.1*P70,K70*P70) -> 2
A71: 15 | B71: =B26 -> Total Revenue dari Pemasaran Produk (Komoditi) | C71: Inovasi Model Bisnis | D71: =D26 -> Rp Miliar | E71: =G26 -> 868 | F71: =E26 -> Maximize | G71: =H26 -> 1.5 | K71: =N26 -> 0.78801843 | L71: 1 | M71: =MIN(1.1*L71,K71*L71) -> 0.78801843 | N71: 1 | O71: =MIN(1.1*N71,K71*N71) -> 0.78801843 | P71: 1 | Q71: =MIN(1.1*P71,K71*P71) -> 0.78801843
A72: 16 | B72: =B27 -> Total Revenue dari Pemasaran Produk (Retail) | C72: Inovasi Model Bisnis | D72: =D27 -> Rp Miliar | E72: =G27 -> 108 | F72: =E27 -> Maximize | G72: =H27 -> 1.5 | K72: =N27 -> 0.37962963 | L72: 1 | M72: =MIN(1.1*L72,K72*L72) -> 0.37962963 | N72: 1 | O72: =MIN(1.1*N72,K72*N72) -> 0.37962963 | P72: 1 | Q72: =MIN(1.1*P72,K72*P72) -> 0.37962963
A73: 17 | B73: =B28 -> Total Revenue dari Agrowisata | C73: Inovasi Model Bisnis | D73: =D28 -> Rp Miliar | E73: =G28 -> 153 | F73: =E28 -> Maximize | G73: =H28 -> 3 | K73: =N28 -> 0.67320261 | L73: 2 | M73: =MIN(1.1*L73,K73*L73) -> 1.3464052 | N73: 2 | O73: =MIN(1.1*N73,K73*N73) -> 1.3464052 | P73: 2 | Q73: =MIN(1.1*P73,K73*P73) -> 1.3464052
A74: 18 | B74: =B29 -> Penerbitan Surat Setoran Pajak Daerah Nihil | C74: Inovasi Model Bisnis | D74: =D29 -> % | E74: =G29 -> 75 | F74: =E29 -> Maximize | G74: =H29 -> 3 | K74: =N29 -> 0.74666667 | L74: 2 | M74: =MIN(1.1*L74,K74*L74) -> 1.4933333 | N74: 2 | O74: =MIN(1.1*N74,K74*N74) -> 1.4933333 | P74: 2 | Q74: =MIN(1.1*P74,K74*P74) -> 1.4933333
A75: 19 | B75: =B30 -> Sertifikasi Aset Tanah | C75: Inovasi Model Bisnis | D75: =D30 -> % | E75: =G30 -> 100 | F75: =E30 -> Maximize | G75: =H30 -> 3 | K75: =N30 -> 0.77 | L75: 2 | M75: =MIN(1.1*L75,K75*L75) -> 1.54 | N75: 2 | O75: =MIN(1.1*N75,K75*N75) -> 1.54 | P75: 2 | Q75: =MIN(1.1*P75,K75*P75) -> 1.54
A76: 20 | B76: =B31 -> Recovery Aset | C76: Inovasi Model Bisnis | D76: =D31 -> Ha | E76: =G31 -> 233 | F76: =E31 -> Maximize | G76: =H31 -> 3 | K76: =N31 -> 1.3755365 | L76: 2 | M76: =MIN(1.1*L76,K76*L76) -> 2.2 | N76: 2 | O76: =MIN(1.1*N76,K76*N76) -> 2.2 | P76: 2 | Q76: =MIN(1.1*P76,K76*P76) -> 2.2
A77: 21 | B77: =B32 -> Pengurusan Perizinan Berusaha Pasca Integrasi | C77: Inovasi Model Bisnis | D77: =D32 -> Jumlah | E77: =G32 -> 19 | F77: =E32 -> Maximize | G77: =H32 -> 3 | K77: =N32 -> 3.7368421 | L77: 2 | M77: =MIN(1.1*L77,K77*L77) -> 2.2 | N77: 2 | O77: =MIN(1.1*N77,K77*N77) -> 2.2 | P77: 2 | Q77: =MIN(1.1*P77,K77*P77) -> 2.2
A78: 22 | B78: =B33 -> Pemenuhan Mitigasi Risiko | C78: Inovasi Model Bisnis | D78: =D33 -> % | E78: =G33 -> 100 | F78: =E33 -> Maximize | G78: =H33 -> 3 | K78: =N33 -> 1 | L78: 2 | M78: =MIN(1.1*L78,K78*L78) -> 2 | N78: 2 | O78: =MIN(1.1*N78,K78*N78) -> 2 | P78: 2 | Q78: =MIN(1.1*P78,K78*P78) -> 2
A79: 23 | B79: =B34 -> Efisiensi Nilai SPPBJ dibandingkan HPS | C79: Inovasi Model Bisnis | D79: =D34 -> % | E79: =G34 -> 3 | F79: =E34 -> Maximize | G79: =H34 -> 3 | K79: =N34 -> 0.86 | L79: 2 | M79: =MIN(1.1*L79,K79*L79) -> 1.72 | N79: 2 | O79: =MIN(1.1*N79,K79*N79) -> 1.72 | P79: 2 | Q79: =MIN(1.1*P79,K79*P79) -> 1.72
B80: Subtotal Inovasi Model Bisnis | G80: =SUM(G69:G79) -> 30 | L80: =SUM(L69:L79) -> 20 | M80: =SUM(M69:M79) -> 17.667387 | N80: =SUM(N69:N79) -> 20 | O80: =SUM(O69:O79) -> 17.667387 | P80: =SUM(P69:P79) -> 20 | Q80: =SUM(Q69:Q79) -> 17.667387
A81: 24 | B81: =B37 -> Implementasi Aplikasi MONIKA untuk katalog rencana Optimalisasi dan Divestasi Aset | C81: Kepemimpinan Teknologi | D81: =D37 -> % | E81: =G37 -> 100 | F81: =E37 -> Maximize | G81: =H37 -> 3 | K81: =N37 -> 0.95 | L81: 4 | M81: =MIN(1.1*L81,K81*L81) -> 3.8 | N81: 4 | O81: =MIN(1.1*N81,K81*N81) -> 3.8 | P81: 4 | Q81: =MIN(1.1*P81,K81*P81) -> 3.8
A82: 25 | B82: =B38 -> Implementasi Aplikasi DFARM Teh | C82: Kepemimpinan Teknologi | D82: =D38 -> % | E82: =G38 -> 100 | F82: =E38 -> Maximize | G82: =H38 -> 3 | K82: =N38 -> 0.5049 | L82: 3 | M82: =MIN(1.1*L82,K82*L82) -> 1.5147 | N82: 3 | O82: =MIN(1.1*N82,K82*N82) -> 1.5147 | P82: 3 | Q82: =MIN(1.1*P82,K82*P82) -> 1.5147
A83: 26 | B83: =B39 -> Implementasi Aplikasi DFARM Karet | C83: Kepemimpinan Teknologi | D83: =D39 -> % | E83: =G39 -> 100 | F83: =E39 -> Maximize | G83: =H39 -> 3 | K83: =N39 -> 0.6433 | L83: 3 | M83: =MIN(1.1*L83,K83*L83) -> 1.9299 | N83: 3 | O83: =MIN(1.1*N83,K83*N83) -> 1.9299 | P83: 3 | Q83: =MIN(1.1*P83,K83*P83) -> 1.9299
B84: Subtotal Kepemimpinan Teknologi | G84: =SUM(G81:G83) -> 9 | L84: =SUM(L81:L83) -> 10 | M84: =SUM(M81:M83) -> 7.2446 | N84: =SUM(N81:N83) -> 10 | O84: =SUM(O81:O83) -> 7.2446 | P84: =SUM(P81:P83) -> 10 | Q84: =SUM(Q81:Q83) -> 7.2446
A85: 27 | B85: =B42 -> Monetisasi, dan/atau Pelepasan Aset Non-Inti | C85: Peningkatan Investasi | D85: =D42 -> % | E85: =G42 -> 100 | F85: =E42 -> Maximize | G85: =H42 -> 5 | K85: =N42 -> 0.46 | L85: 20 | M85: =MIN(1.1*L85,K85*L85) -> 9.2 | N85: 20 | O85: =MIN(1.1*N85,K85*N85) -> 9.2 | P85: 20 | Q85: =MIN(1.1*P85,K85*P85) -> 9.2
B86: Subtotal Peningkatan Investasi | G86: =SUM(G85) -> 5 | L86: =SUM(L85) -> 20 | M86: =SUM(M85) -> 9.2 | N86: =SUM(N85) -> 20 | O86: =SUM(O85) -> 9.2 | P86: =SUM(P85) -> 20 | Q86: =SUM(Q85) -> 9.2
B87: TOTAL | G87: =G56+G68+G80+G84+G86 -> 100 | L87: =L56+L68+L80+L84+L86 -> 100 | M87: =M56+M68+M80+M84+M86 -> 81.971293 | N87: =N56+N68+N80+N84+N86 -> 100 | O87: =O56+O68+O80+O84+O86 -> 80.074079 | P87: =P56+P68+P80+P84+P86 -> 100 | Q87: =Q56+Q68+Q80+Q84+Q86 -> 85.58976

Sheet N1R3
A1: No. | B1: Key Performance Indicator | C1: ESG / C | D1: Satuan | E1: Polaritas | F1: Realisasi | G1: Target | I1: Skor Realisasi/ Target 2025 | K1: Target 2025 | L1: Realisasi 2025 | M1: Bobot KPI | N1: % Capaian Realisasi | O1: Skor Realisasi KPI
F2: S.d Bulan Des'25 | G2: 1 Tahun | H2: Bobot
A4: A. Nilai Ekonomi dan Sosial Untuk Indonesia
A5: A.1 Finansial
A6: 1 | B6: EBITDA Margin | C6: C | D6: % | E6: Maximize | F6: 7.34 | G6: 6.22 | H6: 15 | I6: 16.5 | K6: =G6 -> 6.22 | L6: =F6 -> 7.34 | M6: =H6 -> 15 | N6: =IFERROR(MAX(0,IF(E6="Minimize",G6/F6,IF(G6>0,F6/G6,IF(F6>0,1.1,G6/F6)))),0) -> 1.1800643 | O6: =MIN(1.1*M6,N6*M6) -> 16.5
A7: Sub Total A.1 Finansial | H7: 15 | I7: 16.5
A8: A.2. Operasional
A9: 3 | B9: Cash Cost Komoditi Utama
B10: a. Cash Cost Karet | C10: C | D10: Rp/Kg | E10: Minimize | F10: 22279 | G10: 18402 | H10: 5 | I10: 4.13 | K10: =G10 -> 18402 | L10: =F10 -> 22279 | M10: =H10 -> 5 | N10: =IFERROR(MAX(0,IF(E10="Minimize",G10/F10,IF(G10>0,F10/G10,IF(F10>0,1.1,G10/F10)))),0) -> 0.82597962 | O10: =MIN(1.1*M10,N10*M10) -> 4.1298981
B11: b. Cash Cost Teh | C11: C | D11: Rp/Kg | E11: Minimize | F11: 18113 | G11: 20146 | H11: 4 | I11: 4.4 | K11: =G11 -> 20146 | L11: =F11 -> 18113 | M11: =H11 -> 4 | N11: =IFERROR(MAX(0,IF(E11="Minimize",G11/F11,IF(G11>0,F11/G11,IF(F11>0,1.1,G11/F11)))),0) -> 1.1122398 | O11: =MIN(1.1*M11,N11*M11) -> 4.4
B12: c. Cash Cost Kopi | C12: C | D12: Rp/Kg | E12: Minimize | F12: 51800 | G12: 48409 | H12: 2 | I12: 1.87 | K12: =G12 -> 48409 | L12: =F12 -> 51800 | M12: =H12 -> 2 | N12: =IFERROR(MAX(0,IF(E12="Minimize",G12/F12,IF(G12>0,F12/G12,IF(F12>0,1.1,G12/F12)))),0) -> 0.93453668 | O12: =MIN(1.1*M12,N12*M12) -> 1.8690734
A13: 4 | B13: Produktivitas Komoditi Utama
B14: a. Produktivitas Karet | C14: C | D14: Ton/Ha | E14: Maximize | F14: 1.21 | G14: 1.52 | H14: 5 | I14: 3.99 | K14: =G14 -> 1.52 | L14: =F14 -> 1.21 | M14: =H14 -> 5 | N14: =IFERROR(MAX(0,IF(E14="Minimize",G14/F14,IF(G14>0,F14/G14,IF(F14>0,1.1,G14/F14)))),0) -> 0.79605263 | O14: =MIN(1.1*M14,N14*M14) -> 3.9802632
B15: b. Produktivitas Teh | C15: C | D15: Ton/Ha | E15: Maximize | F15: 2.52 | G15: 2.55 | H15: 4 | I15: 3.96 | K15: =G15 -> 2.55 | L15: =F15 -> 2.52 | M15: =H15 -> 4 | N15: =IFERROR(MAX(0,IF(E15="Minimize",G15/F15,IF(G15>0,F15/G15,IF(F15>0,1.1,G15/F15)))),0) -> 0.98823529 | O15: =MIN(1.1*M15,N15*M15) -> 3.9529412
B16: c. Produktivitas Kopi | C16: C | D16: Ton/Ha | E16: Maximize | F16: 0.57 | G16: 0.65 | H16: 2 | I16: 1.75 | K16: =G16 -> 0.65 | L16: =F16 -> 0.57 | M16: =H16 -> 2 | N16: =IFERROR(MAX(0,IF(E16="Minimize",G16/F16,IF(G16>0,F16/G16,IF(F16>0,1.1,G16/F16)))),0) -> 0.87692308 | O16: =MIN(1.1*M16,N16*M16) -> 1.7538462
A17: 5 | B17: Kualitas Karet Mutu Tinggi (RSS 1) | C17: C | D17: % | E17: Maximize | F17: 95.12 | G17: 97 | H17: 2 | I17: 1.96 | K17: =G17 -> 97 | L17: =F17 -> 95.12 | M17: =H17 -> 2 | N17: =IFERROR(MAX(0,IF(E17="Minimize",G17/F17,IF(G17>0,F17/G17,IF(F17>0,1.1,G17/F17)))),0) -> 0.98061856 | O17: =MIN(1.1*M17,N17*M17) -> 1.9612371
A18: 6 | B18: Kualitas Teh Mutu Tinggi (Mutu 1) Orthodox | C18: C | D18: % | E18: Maximize | F18: 58.78 | G18: 64 | H18: 2 | I18: 1.84 | K18: =G18 -> 64 | L18: =F18 -> 58.78 | M18: =H18 -> 2 | N18: =IFERROR(MAX(0,IF(E18="Minimize",G18/F18,IF(G18>0,F18/G18,IF(F18>0,1.1,G18/F18)))),0) -> 0.9184375 | O18: =MIN(1.1*M18,N18*M18) -> 1.836875
A19: Sub Total A.2. Operasional | H19: 26 | I19: 23.9
A20: A.3. Sosial
